No sourceclass G extends java.lang.Object {
    protected static F a;
    protected static F b;
    protected static java.io.BufferedOutputStream c;
    protected static java.io.BufferedOutputStream d;
    protected static Ro e;
    protected static Ro f;
    protected static Ro g;
    protected static Ro h;
    protected static Ro i;
    protected static Ro j;
    protected static Rp k;
    protected static Rp l;
    protected static Ro m;
    protected static Rp n;
    protected static Ro o;
    protected static Rq p;
    protected static Ro q;
    protected static Rx r;
    protected static Ro s;
    protected static Ry t;
    protected static Ro u;
    protected static R3 v;
    protected static R4 w;
    protected static Ro x;
    protected static Ro y;
    protected static java.lang.String z;
    public static {};
    protected static Ra a(F, int);
    protected static Rc b(Rc, Rc);
    protected static Ri c(Ri, Ri);
    protected static Rj d(Rj, Rj);
    protected static Rc e(F, Rc, Rc);
    protected static char f(int);
    protected static java.lang.String g(Rk);
    protected static java.lang.String h(Ri);
    protected static void i(java.io.BufferedOutputStream, java.lang.String);
    protected static int j(int, int)[];
    protected static Rc k(int, Rc)[];
    protected static int l(F, Rf, java.lang.String);
    protected static Rl m(F, Rd, Rc);
    protected static Rd n(Rc, F, int, Rd);
    protected static Rm o(F, Rf, Re);
    protected static Rf p(Re, F, java.lang.String, Rf);
    protected static Rd q(F, Rd);
    protected static int r(Rn, Rn);
    protected static Rc s(Rc, Rc);
    protected static int t(S);
    protected static Rc u(S);
    protected static Rc v(S);
    protected static char w(Ro, java.io.BufferedInputStream, Rr);
    protected static void x(Ro, java.io.BufferedInputStream, Rr);
    protected static S y(java.io.BufferedOutputStream, Ro, java.lang.String);
    protected static void z(java.io.BufferedOutputStream, Ro, java.lang.String);
    protected static S A(java.io.BufferedOutputStream, Ro, java.lang.String);
    protected static Rv B(java.io.BufferedOutputStream, Ro, java.lang.String);
    protected static void C(java.io.BufferedOutputStream, Ro, Ro, Rx, Ro, Ry, Ro);
    protected static int D(char);
    protected static int E(char);
    protected static int F(char);
    protected static int G(java.lang.String);
    protected static Ri H(java.lang.String, int, Ri);
    protected static char I(java.io.BufferedOutputStream, Ro, Ro, Rx);
    protected static char J(Ro, Rx);
    protected static java.lang.String K(Ro, Rx, Ri);
    protected static java.lang.String L(Ro, Rx, Ri);
    protected static S M(java.io.BufferedOutputStream, Ro, java.lang.String, int);
    protected static S N(java.io.BufferedOutputStream, Ro, Ro, Rx, Ro);
    protected static Rk O(java.io.BufferedOutputStream, Ro, Rx, Rk, java.lang.String);
    protected static int P(java.io.BufferedOutputStream, Ro, Ro, Rx, int, int[], Rz)[];
    protected static void Q(int, int[], Ro, int);
    protected static java.lang.String R(java.io.BufferedOutputStream, Ro, Rx, java.lang.String);
    protected static Ra S(java.io.BufferedOutputStream, Ro, Rx, java.lang.String, int);
    protected static java.lang.String T(Ro, Rx, int, Ri);
    protected static S U(java.io.BufferedOutputStream, Ro, Ro, Ro, Rx, Ro, Ry, Ro, R3);
    protected static S V(java.io.BufferedOutputStream, Ro, R3, java.lang.String);
    protected static S W(java.lang.String, F, R1);
    protected static S X(Ro, S);
    protected static S Y(int, int, S);
    protected static S Z(S, int, int);
    protected static S aa(java.io.BufferedOutputStream, Ro, Ro, Ro, Rx, Ro, Ry, Ro, R3, S);
    protected static S ab(java.io.BufferedOutputStream, Ro, Ro, Ro, Rx, Ro, Ry, Ro, R3);
    protected static S ac(java.io.BufferedOutputStream, Ro, Ro, Ro, Rx, Ro, Ry, Ro, R3, S, S);
    protected static void ad(F, F, java.io.BufferedOutputStream, java.io.BufferedOutputStream, Ro, Ro, Ro, Ro, Ro, Ro, Rp, Rp, Ro, Rp, Ro, Rq, Ro, Rx, Ro, Ry, Ro, R3, R4, Ro, Ro, java.lang.String);
    protected static Rt ae(java.io.BufferedOutputStream, Ro, Ro, Ro, Ro, Rx, Ro, Ry, Ro, R3, R4, Ro, Ro, R5, Rt);
    protected static Rc af(java.io.BufferedOutputStream, Ro, R4, Rk, Rc);
    protected static Rc ag(Ro, int, Rc);
    protected static Rc ah(Rc);
    protected static Rc ai(Rc);
    protected static S aj(Ro, S);
    protected static Rh ak(F, Rg, java.lang.String, Rh);
    protected static void al(java.io.BufferedOutputStream, Ro, Ro, Ro, Ro, Rp, Rp, Ro, Rp, Ro, Ro, Rx, Ro, Ry, Ro, R3, R4, Ro);
    protected static R1 am(java.lang.String, F, R0, R1);
    protected static void an(java.io.BufferedOutputStream, Ro, Ro, Rx, Ro, Ry, Ro, R4, Ro);
    protected static java.lang.String ao(Ro, Rx, Ri);
    protected static S ap(int, S, S[], int)[];
    protected static void aq(Rc[], S[], R8, Ro, S);
    protected static void ar(Rc[], S[], R8, Ro, Rt);
    protected static java.lang.String as(Rc);
    protected static void at(Ro, Ro, R4, R6, R6, R6, Rc[], S[], Rc, int);
    protected static int au(Ro, Ro, R4, R6, R6, R6, Rc[], S[], Rc);
    protected static Rc av(Ro, Ro, R4, R6, R6, R6, Rc[], S[], Rc);
    protected static Rc aw(S[], Rc, Rc);
    protected static Rc ax(S[], Rc, Rc);
    protected static Rc ay(Rc[], S[], int, Rc, Rc);
    protected static void az(Rc[], Rc, Rc);
    protected static void aA(Rc[], Rt);
    protected static R9 aB(Rc[], int, R9);
    protected static void aC(Ro, Ro, R4, R6, R6, R6, Rc[], S[], R9, int);
    protected static int aD(Rd, int);
    protected static S aE(R7, int);
    protected static int aF(int, R7);
    protected static Rj aG(R7, Rc, Rc);
    protected static Raa aH(R7, Rd, Raa, Rd);
    protected static Rc aI(int, Rd);
    protected static Rc aJ(R7, Rc, Rc);
    protected static int aK(int, R7);
    protected static Rc aL(int, Rc);
    protected static Rk aM(Ro, Rq, Ro, Rd, Rk, Rab);
    protected static Rn aN(Rc, java.lang.String, Rn, Rab);
    protected static java.lang.String aO(java.lang.StringBuffer, java.lang.String, int);
    protected static void aP(Rc, F, int);
    protected static Rab aQ(Rn, Rab);
    protected static int aR(Rc, int);
    protected static void aS(Rq, Rk, Raa);
    protected static void aT(Rq, Rj);
    protected static int aU(Rd, int);
    protected static void aV(Rq, Rf);
    protected static Rf aW(Rf, Rf);
    protected static void aX(Rq, Rh, int);
    protected static Rh aY(Rh, Rh);
    protected static void aZ(F, F, java.io.BufferedOutputStream, java.io.BufferedOutputStream, Ro, Ro, Ro, Ro, Ro, Ro, Rp, Rp, Ro, Rp, Ro, Rq, Ro, Rx, Ro, Ry, Ro, R3, R4, Ro, Ro, java.lang.String, int);
    protected static Ra ba(java.lang.String, int, int, int, int, int);
}

Method static {}
   0 ldc #79 <String "user.dir">
   2 new #830 <Class Ro>
   5 dup
   6 iconst_m1
   7 new #830 <Class Ro>
  10 dup
  11 iconst_0
  12 new #831 <Class R4>
  15 dup
  16 new #832 <Class Rm>
  19 dup
  20 new #834 <Class Fa>
  23 dup
  24 new #834 <Class Fa>
  27 dup
  28 invokespecial #1268 <Method Fa()>
  31 putstatic #1095 <Field F a>
  34 invokespecial #1268 <Method Fa()>
  37 dup
  38 astore_0
  39 aconst_null
  40 new #764 <Class R3>
  43 dup
  44 new #766 <Class R2>
  47 dup
  48 aload_0
  49 aconst_null
  50 new #830 <Class Ro>
  53 dup
  54 iconst_0
  55 new #768 <Class Ry>
  58 dup
  59 new #770 <Class S>
  62 dup
  63 iconst_5
  64 new #830 <Class Ro>
  67 dup
  68 iconst_0
  69 new #774 <Class Rx>
  72 dup
  73 new #777 <Class Rw>
  76 dup
  77 new #780 <Class java.io.BufferedInputStream>
  80 dup
  81 getstatic #1161 <Field java.io.InputStream in>
  84 invokespecial #1323 <Method java.io.BufferedInputStream(java.io.InputStream)>
  87 new #788 <Class Rr>
  90 dup
  91 new #789 <Class Rp>
  94 dup
  95 ldc #129 <String "">
  97 new #830 <Class Ro>
 100 dup
 101 iconst_1
 102 new #794 <Class Rq>
 105 dup
 106 new #796 <Class java.io.BufferedOutputStream>
 109 dup
 110 getstatic #1128 <Field java.io.PrintStream out>
 113 invokespecial #1221 <Method java.io.BufferedOutputStream(java.io.OutputStream)>
 116 dup
 117 astore_1
 118 new #830 <Class Ro>
 121 dup
 122 iconst_0
 123 new #789 <Class Rp>
 126 dup
 127 aconst_null
 128 new #830 <Class Ro>
 131 dup
 132 iconst_0
 133 new #789 <Class Rp>
 136 dup
 137 ldc #129 <String "">
 139 new #789 <Class Rp>
 142 dup
 143 ldc #136 <String "Mlex">
 145 new #830 <Class Ro>
 148 dup
 149 sipush 129
 152 new #830 <Class Ro>
 155 dup
 156 iconst_0
 157 new #830 <Class Ro>
 160 dup
 161 iconst_0
 162 new #830 <Class Ro>
 165 dup
 166 iconst_0
 167 new #830 <Class Ro>
 170 dup
 171 iconst_0
 172 new #830 <Class Ro>
 175 dup
 176 iconst_0
 177 new #796 <Class java.io.BufferedOutputStream>
 180 dup
 181 getstatic #1187 <Field java.io.PrintStream err>
 184 invokespecial #1221 <Method java.io.BufferedOutputStream(java.io.OutputStream)>
 187 putstatic #1188 <Field java.io.BufferedOutputStream d>
 190 invokespecial #1344 <Method Ro(int)>
 193 putstatic #1171 <Field Ro e>
 196 invokespecial #1344 <Method Ro(int)>
 199 putstatic #1186 <Field Ro f>
 202 invokespecial #1344 <Method Ro(int)>
 205 putstatic #1088 <Field Ro g>
 208 invokespecial #1344 <Method Ro(int)>
 211 putstatic #1107 <Field Ro h>
 214 invokespecial #1344 <Method Ro(int)>
 217 putstatic #1126 <Field Ro i>
 220 invokespecial #1344 <Method Ro(int)>
 223 putstatic #1141 <Field Ro j>
 226 invokespecial #1327 <Method Rp(java.lang.String)>
 229 putstatic #1125 <Field Rp k>
 232 invokespecial #1327 <Method Rp(java.lang.String)>
 235 putstatic #1138 <Field Rp l>
 238 invokespecial #1344 <Method Ro(int)>
 241 putstatic #1153 <Field Ro m>
 244 invokespecial #1327 <Method Rp(java.lang.String)>
 247 putstatic #1169 <Field Rp n>
 250 invokespecial #1344 <Method Ro(int)>
 253 putstatic #1183 <Field Ro o>
 256 invokespecial #1377 <Method Rq(java.io.BufferedOutputStream)>
 259 putstatic #1167 <Field Rq p>
 262 invokespecial #1344 <Method Ro(int)>
 265 putstatic #1181 <Field Ro q>
 268 invokespecial #1327 <Method Rp(java.lang.String)>
 271 new #830 <Class Ro>
 274 dup
 275 iconst_0
 276 invokespecial #1344 <Method Ro(int)>
 279 invokespecial #1269 <Method Rr(Rp,Ro)>
 282 invokespecial #1326 <Method Rw(java.io.BufferedInputStream,Rr)>
 285 invokespecial #1211 <Method Rx(Rw)>
 288 putstatic #1100 <Field Rx r>
 291 invokespecial #1344 <Method Ro(int)>
 294 putstatic #1119 <Field Ro s>
 297 invokespecial #1362 <Method S(int)>
 300 invokespecial #1257 <Method Ry(S)>
 303 putstatic #1163 <Field Ry t>
 306 invokespecial #1344 <Method Ro(int)>
 309 putstatic #1179 <Field Ro u>
 312 invokespecial #1353 <Method R2(F,R1)>
 315 invokespecial #1232 <Method R3(R2)>
 318 putstatic #1133 <Field R3 v>
 321 invokespecial #1206 <Method Rm(F,Rf)>
 324 invokespecial #1267 <Method R4(Rm)>
 327 putstatic #1086 <Field R4 w>
 330 invokespecial #1344 <Method Ro(int)>
 333 putstatic #1097 <Field Ro x>
 336 invokespecial #1344 <Method Ro(int)>
 339 putstatic #1116 <Field Ro y>
 342 invokestatic #1262 <Method java.lang.String getProperty(java.lang.String)>
 345 putstatic #1162 <Field java.lang.String z>
 348 aload_1
 349 putstatic #1175 <Field java.io.BufferedOutputStream c>
 352 aload_0
 353 putstatic #1084 <Field F b>
 356 return

Method Ra a(F, int)
   0 aload_0
   1 iload_1
   2 invokevirtual #1203 <Method Rb b(int)>
   5 dup
   6 astore_2
   7 ifnull 135
  10 aload_2
  11 getfield #1191 <Field char a>
  14 dup
  15 istore_3
  16 lookupswitch 3: default=52
	   43: 122
	   45: 109
	  126: 96
  52 iload_3
  53 bipush 11
  55 aload_2
  56 getfield #1158 <Field int b>
  59 istore 4
  61 if_icmpne 145
  64 iconst_1
  65 istore 5
  67 iload 5
  69 ifne 151
  72 iload_1
  73 iload 4
  75 istore_1
  76 istore 6
  78 iload_3
  79 invokestatic #1213 <Method boolean isSpace(char)>
  82 ifne 0
  85 new #791 <Class Ra>
  88 dup
  89 iconst_0
  90 iload 6
  92 invokespecial #1201 <Method Ra(int,int)>
  95 areturn
  96 new #791 <Class Ra>
  99 dup
 100 iconst_1
 101 aload_2
 102 getfield #1158 <Field int b>
 105 invokespecial #1201 <Method Ra(int,int)>
 108 areturn
 109 new #791 <Class Ra>
 112 dup
 113 iconst_1
 114 aload_2
 115 getfield #1158 <Field int b>
 118 invokespecial #1201 <Method Ra(int,int)>
 121 areturn
 122 new #791 <Class Ra>
 125 dup
 126 iconst_0
 127 aload_2
 128 getfield #1158 <Field int b>
 131 invokespecial #1201 <Method Ra(int,int)>
 134 areturn
 135 new #791 <Class Ra>
 138 dup
 139 iconst_0
 140 iload_1
 141 invokespecial #1201 <Method Ra(int,int)>
 144 areturn
 145 iconst_0
 146 istore 5
 148 goto 67
 151 iload 4
 153 istore_1
 154 goto 0

Method Rc b(Rc, Rc)
   0 goto 21
   3 new #797 <Class Rc>
   6 dup
   7 aload_0
   8 getfield #1189 <Field int a>
  11 aload_1
  12 invokespecial #1256 <Method Rc(int,Rc)>
  15 astore_1
  16 aload_0
  17 getfield #1127 <Field Rc b>
  20 astore_0
  21 aload_0
  22 ifnonnull 3
  25 aload_1
  26 areturn

Method Ri c(Ri, Ri)
   0 goto 21
   3 new #801 <Class Ri>
   6 dup
   7 aload_0
   8 getfield #1103 <Field char a>
  11 aload_1
  12 invokespecial #1238 <Method Ri(char,Ri)>
  15 astore_1
  16 aload_0
  17 getfield #1098 <Field Ri b>
  20 astore_0
  21 aload_0
  22 ifnonnull 3
  25 aload_1
  26 areturn

Method Rj d(Rj, Rj)
   0 goto 21
   3 new #805 <Class Rj>
   6 dup
   7 aload_0
   8 getfield #1157 <Field S a>
  11 aload_1
  12 invokespecial #1322 <Method Rj(S,Rj)>
  15 astore_1
  16 aload_0
  17 getfield #1090 <Field Rj b>
  20 astore_0
  21 aload_0
  22 ifnonnull 3
  25 aload_1
  26 areturn

Method Rc e(F, Rc, Rc)
   0 aload_2
   1 ifnonnull 6
   4 aload_1
   5 areturn
   6 aload_0
   7 new #797 <Class Rc>
  10 dup
  11 aload_2
  12 getfield #1189 <Field int a>
  15 aload_0
  16 aload_1
  17 aload_2
  18 getfield #1127 <Field Rc b>
  21 invokestatic #1319 <Method Rc e(F, Rc, Rc)>
  24 invokespecial #1256 <Method Rc(int,Rc)>
  27 invokevirtual #1304 <Method Rc c(Rc)>
  30 areturn

Method char f(int)
   0 iload_0
   1 iflt 34
   4 iconst_0
   5 istore_1
   6 iload_1
   7 ifne 39
  10 iload_0
  11 sipush 255
  14 if_icmpgt 44
  17 iconst_0
  18 istore_2
  19 iload_2
  20 ifne 26
  23 iload_0
  24 i2c
  25 ireturn
  26 new #813 <Class Ea>
  29 dup
  30 invokespecial #1236 <Method Ea()>
  33 athrow
  34 iconst_1
  35 istore_1
  36 goto 6
  39 iconst_1
  40 istore_2
  41 goto 19
  44 iconst_1
  45 istore_2
  46 goto 19

Method java.lang.String g(Rk)
   0 aload_0
   1 ifnonnull 7
   4 ldc #129 <String "">
   6 areturn
   7 aload_0
   8 getfield #1129 <Field Rk b>
  11 dup
  12 astore_1
  13 ifnonnull 21
  16 aload_0
  17 getfield #1142 <Field java.lang.String a>
  20 areturn
  21 aload_1
  22 getfield #1129 <Field Rk b>
  25 ifnonnull 40
  28 aload_0
  29 getfield #1142 <Field java.lang.String a>
  32 aload_1
  33 getfield #1142 <Field java.lang.String a>
  36 invokevirtual #1235 <Method java.lang.String concat(java.lang.String)>
  39 areturn
  40 new #824 <Class java.lang.StringBuffer>
  43 dup
  44 aload_0
  45 getfield #1142 <Field java.lang.String a>
  48 invokespecial #1277 <Method java.lang.StringBuffer(java.lang.String)>
  51 astore_2
  52 goto 69
  55 aload_2
  56 aload_1
  57 getfield #1142 <Field java.lang.String a>
  60 invokevirtual #1332 <Method java.lang.StringBuffer append(java.lang.String)>
  63 pop
  64 aload_1
  65 getfield #1129 <Field Rk b>
  68 astore_1
  69 aload_1
  70 ifnonnull 55
  73 aload_2
  74 invokevirtual #1363 <Method java.lang.String toString()>
  77 areturn

Method java.lang.String h(Ri)
   0 aload_0
   1 ifnonnull 7
   4 ldc #129 <String "">
   6 areturn
   7 aload_0
   8 getfield #1098 <Field Ri b>
  11 ifnonnull 22
  14 aload_0
  15 getfield #1103 <Field char a>
  18 invokestatic #1342 <Method java.lang.String valueOf(char)>
  21 areturn
  22 new #824 <Class java.lang.StringBuffer>
  25 dup
  26 invokespecial #1247 <Method java.lang.StringBuffer()>
  29 astore_1
  30 goto 47
  33 aload_1
  34 aload_0
  35 getfield #1103 <Field char a>
  38 invokevirtual #1376 <Method java.lang.StringBuffer append(char)>
  41 pop
  42 aload_0
  43 getfield #1098 <Field Ri b>
  46 astore_0
  47 aload_0
  48 ifnonnull 33
  51 aload_1
  52 invokevirtual #1363 <Method java.lang.String toString()>
  55 areturn

Method void i(java.io.BufferedOutputStream, java.lang.String)
   0 aload_1
   1 invokevirtual #1356 <Method int length()>
   4 dup
   5 istore_2
   6 newarray byte
   8 dup
   9 astore_3
  10 aload_1
  11 iconst_0
  12 iload_2
  13 aload_3
  14 iconst_0
  15 invokevirtual #1383 <Method void getBytes(int, int, byte[], int)>
  18 arraylength
  19 istore 4
  21 aload_0
  22 aload_3
  23 iconst_0
  24 iload 4
  26 invokevirtual #1272 <Method void write(byte[], int, int)>
  29 return
  30 astore 5
  32 new #835 <Class Eb>
  35 dup
  36 aload 5
  38 ldc #95 <String "output">
  40 ldc #98 <String "java.io.BufferedOutputStream">
  42 invokespecial #1259 <Method Eb(java.lang.Exception,java.lang.String,java.lang.String)>
  45 athrow
Exception table:
   from   to  target type
    21    29    30   <Class java.io.IOException>

Method int j(int, int)[]
   0 iload_0
   1 newarray int
   3 astore_2
   4 iconst_0
   5 istore_3
   6 goto 32
   9 aload_2
  10 areturn
  11 iconst_0
  12 istore 4
  14 iload 4
  16 ifne 9
  19 iload_3
  20 istore 5
  22 iload 5
  24 iconst_1
  25 iadd
  26 istore_3
  27 aload_2
  28 iload 5
  30 iload_1
  31 iastore
  32 iload_3
  33 iload_0
  34 if_icmpne 11
  37 iconst_1
  38 istore 4
  40 goto 14

Method Rc k(int, Rc)[]
   0 iload_0
   1 anewarray class #797 <Class Rc>
   4 astore_2
   5 iconst_0
   6 istore_3
   7 goto 33
  10 aload_2
  11 areturn
  12 iconst_0
  13 istore 4
  15 iload 4
  17 ifne 10
  20 iload_3
  21 istore 5
  23 iload 5
  25 iconst_1
  26 iadd
  27 istore_3
  28 aload_2
  29 iload 5
  31 aload_1
  32 aastore
  33 iload_3
  34 iload_0
  35 if_icmpne 12
  38 iconst_1
  39 istore 4
  41 goto 15

Method int l(F, Rf, java.lang.String)
   0 goto 35
   3 aload_0
   4 new #771 <Class Rg>
   7 dup
   8 aload_2
   9 aload_1
  10 getfield #1156 <Field Re a>
  13 dup
  14 astore 4
  16 getfield #1087 <Field java.lang.String a>
  19 dup
  20 astore_3
  21 invokespecial #1294 <Method Rg(java.lang.String,java.lang.String)>
  24 invokevirtual #1266 <Method int d(Rg)>
  27 ifne 47
  30 aload_1
  31 getfield #1139 <Field Rf b>
  34 astore_1
  35 aload_1
  36 ifnonnull 3
  39 new #790 <Class Ec>
  42 dup
  43 invokespecial #1297 <Method Ec()>
  46 athrow
  47 aload_0
  48 new #771 <Class Rg>
  51 dup
  52 aload_3
  53 aload_2
  54 invokespecial #1294 <Method Rg(java.lang.String,java.lang.String)>
  57 invokevirtual #1266 <Method int d(Rg)>
  60 ifne 71
  63 new #790 <Class Ec>
  66 dup
  67 invokespecial #1297 <Method Ec()>
  70 athrow
  71 aload 4
  73 getfield #1160 <Field int b>
  76 ireturn

Method Rl m(F, Rd, Rc)
   0 new #795 <Class Rl>
   3 dup
   4 aload_0
   5 aload_2
   6 aload_0
   7 aload_2
   8 getfield #1189 <Field int a>
  11 aload_1
  12 invokestatic #1205 <Method Rd n(Rc, F, int, Rd)>
  15 invokespecial #1295 <Method Rl(F,Rd)>
  18 areturn

Method Rd n(Rc, F, int, Rd)
   0 aload_3
   1 ifnonnull 14
   4 new #800 <Class Rd>
   7 dup
   8 aload_0
   9 aconst_null
  10 invokespecial #1288 <Method Rd(Rc,Rd)>
  13 areturn
  14 aload_1
  15 new #791 <Class Ra>
  18 dup
  19 iload_2
  20 aload_3
  21 getfield #1093 <Field Rc a>
  24 dup
  25 astore 5
  27 getfield #1189 <Field int a>
  30 dup
  31 istore 6
  33 invokespecial #1201 <Method Ra(int,int)>
  36 invokevirtual #1349 <Method int a(Ra)>
  39 aload_3
  40 getfield #1145 <Field Rd b>
  43 astore 4
  45 ifne 54
  48 iconst_0
  49 istore 7
  51 goto 70
  54 aload_1
  55 new #791 <Class Ra>
  58 dup
  59 iload 6
  61 iload_2
  62 invokespecial #1201 <Method Ra(int,int)>
  65 invokevirtual #1349 <Method int a(Ra)>
  68 istore 7
  70 iload 7
  72 ifne 118
  75 aload_1
  76 new #791 <Class Ra>
  79 dup
  80 iload 6
  82 iload_2
  83 invokespecial #1201 <Method Ra(int,int)>
  86 invokevirtual #1349 <Method int a(Ra)>
  89 ifne 149
  92 iconst_1
  93 istore 8
  95 iload 8
  97 ifne 129
 100 new #800 <Class Rd>
 103 dup
 104 aload 5
 106 aload_0
 107 aload_1
 108 iload_2
 109 aload 4
 111 invokestatic #1205 <Method Rd n(Rc, F, int, Rd)>
 114 invokespecial #1288 <Method Rd(Rc,Rd)>
 117 areturn
 118 new #800 <Class Rd>
 121 dup
 122 aload_0
 123 aload 4
 125 invokespecial #1288 <Method Rd(Rc,Rd)>
 128 areturn
 129 new #800 <Class Rd>
 132 dup
 133 aload_0
 134 new #800 <Class Rd>
 137 dup
 138 aload 5
 140 aload 4
 142 invokespecial #1288 <Method Rd(Rc,Rd)>
 145 invokespecial #1288 <Method Rd(Rc,Rd)>
 148 areturn
 149 iconst_0
 150 istore 8
 152 goto 95

Method Rm o(F, Rf, Re)
   0 new #832 <Class Rm>
   3 dup
   4 aload_0
   5 aload_2
   6 aload_0
   7 aload_2
   8 getfield #1087 <Field java.lang.String a>
  11 aload_1
  12 invokestatic #1336 <Method Rf p(Re, F, java.lang.String, Rf)>
  15 invokespecial #1206 <Method Rm(F,Rf)>
  18 areturn

Method Rf p(Re, F, java.lang.String, Rf)
   0 aload_3
   1 ifnonnull 14
   4 new #775 <Class Rf>
   7 dup
   8 aload_0
   9 aconst_null
  10 invokespecial #1229 <Method Rf(Re,Rf)>
  13 areturn
  14 aload_1
  15 new #771 <Class Rg>
  18 dup
  19 aload_2
  20 aload_3
  21 getfield #1156 <Field Re a>
  24 dup
  25 astore 5
  27 getfield #1087 <Field java.lang.String a>
  30 dup
  31 astore 6
  33 invokespecial #1294 <Method Rg(java.lang.String,java.lang.String)>
  36 invokevirtual #1266 <Method int d(Rg)>
  39 aload_3
  40 getfield #1139 <Field Rf b>
  43 astore 4
  45 ifne 54
  48 iconst_0
  49 istore 7
  51 goto 70
  54 aload_1
  55 new #771 <Class Rg>
  58 dup
  59 aload 6
  61 aload_2
  62 invokespecial #1294 <Method Rg(java.lang.String,java.lang.String)>
  65 invokevirtual #1266 <Method int d(Rg)>
  68 istore 7
  70 iload 7
  72 ifne 118
  75 aload_1
  76 new #771 <Class Rg>
  79 dup
  80 aload 6
  82 aload_2
  83 invokespecial #1294 <Method Rg(java.lang.String,java.lang.String)>
  86 invokevirtual #1266 <Method int d(Rg)>
  89 ifne 149
  92 iconst_1
  93 istore 8
  95 iload 8
  97 ifne 129
 100 new #775 <Class Rf>
 103 dup
 104 aload 5
 106 aload_0
 107 aload_1
 108 aload_2
 109 aload 4
 111 invokestatic #1336 <Method Rf p(Re, F, java.lang.String, Rf)>
 114 invokespecial #1229 <Method Rf(Re,Rf)>
 117 areturn
 118 new #775 <Class Rf>
 121 dup
 122 aload_0
 123 aload 4
 125 invokespecial #1229 <Method Rf(Re,Rf)>
 128 areturn
 129 new #775 <Class Rf>
 132 dup
 133 aload_0
 134 new #775 <Class Rf>
 137 dup
 138 aload 5
 140 aload 4
 142 invokespecial #1229 <Method Rf(Re,Rf)>
 145 invokespecial #1229 <Method Rf(Re,Rf)>
 148 areturn
 149 iconst_0
 150 istore 8
 152 goto 95

Method Rd q(F, Rd)
   0 aconst_null
   1 astore_2
   2 goto 23
   5 new #800 <Class Rd>
   8 dup
   9 aload_1
  10 getfield #1093 <Field Rc a>
  13 aload_2
  14 invokespecial #1288 <Method Rd(Rc,Rd)>
  17 astore_2
  18 aload_1
  19 getfield #1145 <Field Rd b>
  22 astore_1
  23 aload_1
  24 ifnonnull 5
  27 aconst_null
  28 astore_3
  29 goto 50
  32 new #800 <Class Rd>
  35 dup
  36 aload_2
  37 getfield #1093 <Field Rc a>
  40 aload_3
  41 invokespecial #1288 <Method Rd(Rc,Rd)>
  44 astore_3
  45 aload_2
  46 getfield #1145 <Field Rd b>
  49 astore_2
  50 aload_2
  51 ifnonnull 32
  54 aload_3
  55 areturn

Method int r(Rn, Rn)
   0 aload_1
   1 getfield #1117 <Field Rc a>
   4 astore 4
   6 aload_0
   7 getfield #1117 <Field Rc a>
  10 astore 5
  12 aload 4
  14 ifnull 80
  17 aload 5
  19 ifnull 78
  22 aload 5
  24 getfield #1189 <Field int a>
  27 dup
  28 istore_2
  29 aload 4
  31 getfield #1189 <Field int a>
  34 dup
  35 istore_3
  36 aload 4
  38 getfield #1127 <Field Rc b>
  41 astore 4
  43 aload 5
  45 getfield #1127 <Field Rc b>
  48 astore 5
  50 if_icmple 82
  53 iconst_1
  54 istore 6
  56 iload 6
  58 ifne 76
  61 iload_2
  62 iload_3
  63 if_icmpne 88
  66 iconst_1
  67 istore 7
  69 iload 7
  71 ifne 12
  74 iconst_0
  75 ireturn
  76 iconst_1
  77 ireturn
  78 iconst_0
  79 ireturn
  80 iconst_0
  81 ireturn
  82 iconst_0
  83 istore 6
  85 goto 56
  88 iconst_0
  89 istore 7
  91 goto 69

Method Rc s(Rc, Rc)
   0 aload_1
   1 aconst_null
   2 aload_0
   3 aconst_null
   4 invokestatic #1308 <Method Rc b(Rc, Rc)>
   7 astore_2
   8 invokestatic #1308 <Method Rc b(Rc, Rc)>
  11 astore_3
  12 aconst_null
  13 astore 4
  15 goto 165
  18 iload 5
  20 iload 6
  22 if_icmple 206
  25 iconst_1
  26 istore 8
  28 iload 8
  30 ifeq 60
  33 new #797 <Class Rc>
  36 dup
  37 iload 5
  39 aload 4
  41 new #797 <Class Rc>
  44 dup
  45 iload 6
  47 aload_3
  48 invokespecial #1256 <Method Rc(int,Rc)>
  51 astore_3
  52 invokespecial #1256 <Method Rc(int,Rc)>
  55 astore 4
  57 goto 165
  60 new #797 <Class Rc>
  63 dup
  64 iload 6
  66 aload 4
  68 new #797 <Class Rc>
  71 dup
  72 iload 5
  74 aload_2
  75 invokespecial #1256 <Method Rc(int,Rc)>
  78 astore_2
  79 invokespecial #1256 <Method Rc(int,Rc)>
  82 astore 4
  84 goto 165
  87 new #797 <Class Rc>
  90 dup
  91 aload_3
  92 getfield #1189 <Field int a>
  95 aload 4
  97 invokespecial #1256 <Method Rc(int,Rc)>
 100 astore 4
 102 aload_3
 103 getfield #1127 <Field Rc b>
 106 astore_3
 107 aconst_null
 108 astore_2
 109 goto 165
 112 aload_2
 113 ifnull 141
 116 new #797 <Class Rc>
 119 dup
 120 aload_2
 121 getfield #1189 <Field int a>
 124 aload 4
 126 invokespecial #1256 <Method Rc(int,Rc)>
 129 astore 4
 131 aload_2
 132 getfield #1127 <Field Rc b>
 135 astore_2
 136 aconst_null
 137 astore_3
 138 goto 165
 141 aload 4
 143 areturn
 144 iconst_0
 145 istore 7
 147 iload 7
 149 ifeq 18
 152 new #797 <Class Rc>
 155 dup
 156 iload 5
 158 aload 4
 160 invokespecial #1256 <Method Rc(int,Rc)>
 163 astore 4
 165 aload_3
 166 ifnull 112
 169 aload_2
 170 ifnull 87
 173 aload_2
 174 getfield #1189 <Field int a>
 177 dup
 178 istore 5
 180 aload_3
 181 getfield #1189 <Field int a>
 184 dup
 185 istore 6
 187 aload_3
 188 getfield #1127 <Field Rc b>
 191 astore_3
 192 aload_2
 193 getfield #1127 <Field Rc b>
 196 astore_2
 197 if_icmpne 144
 200 iconst_1
 201 istore 7
 203 goto 147
 206 iconst_0
 207 istore 8
 209 goto 28

Method int t(S)
   0 goto 31
   3 iconst_1
   4 ireturn
   5 iconst_0
   6 ireturn
   7 iconst_1
   8 ireturn
   9 iconst_0
  10 ireturn
  11 aload_0
  12 checkcast #811 <Class Sa>
  15 dup
  16 astore_1
  17 getfield #1168 <Field S a>
  20 invokestatic #1253 <Method int t(S)>
  23 ifeq 95
  26 aload_1
  27 getfield #1120 <Field S b>
  30 astore_0
  31 aload_0
  32 getfield #1147 <Field int $>
  35 tableswitch 0 to 5: default=99
	    0: 72
	    1: 11
	    2: 9
	    3: 7
	    4: 5
	    5: 3
  72 aload_0
  73 checkcast #811 <Class Sa>
  76 dup
  77 astore_2
  78 getfield #1168 <Field S a>
  81 invokestatic #1253 <Method int t(S)>
  84 ifne 97
  87 aload_2
  88 getfield #1120 <Field S b>
  91 astore_0
  92 goto 31
  95 iconst_0
  96 ireturn
  97 iconst_1
  98 ireturn
  99 iconst_1
 100 ireturn

Method Rc u(S)
   0 goto 29
   3 aconst_null
   4 areturn
   5 new #797 <Class Rc>
   8 dup
   9 aload_0
  10 checkcast #816 <Class Sb>
  13 getfield #1118 <Field int a>
  16 aconst_null
  17 invokespecial #1256 <Method Rc(int,Rc)>
  20 areturn
  21 aload_0
  22 checkcast #820 <Class Sd>
  25 getfield #1178 <Field S a>
  28 astore_0
  29 aload_0
  30 getfield #1147 <Field int $>
  33 tableswitch 0 to 5: default=143
	    0: 120
	    1: 72
	    2: 104
	    3: 21
	    4: 5
	    5: 3
  72 aload_0
  73 checkcast #811 <Class Sa>
  76 dup
  77 astore_1
  78 getfield #1120 <Field S b>
  81 dup
  82 astore_0
  83 invokestatic #1253 <Method int t(S)>
  86 ifeq 29
  89 aload_1
  90 getfield #1168 <Field S a>
  93 invokestatic #1251 <Method Rc u(S)>
  96 aload_0
  97 invokestatic #1251 <Method Rc u(S)>
 100 invokestatic #1366 <Method Rc s(Rc, Rc)>
 103 areturn
 104 new #797 <Class Rc>
 107 dup
 108 aload_0
 109 checkcast #825 <Class Sc>
 112 getfield #1112 <Field int b>
 115 aconst_null
 116 invokespecial #1256 <Method Rc(int,Rc)>
 119 areturn
 120 aload_0
 121 checkcast #811 <Class Sa>
 124 dup
 125 astore_2
 126 getfield #1168 <Field S a>
 129 invokestatic #1251 <Method Rc u(S)>
 132 aload_2
 133 getfield #1120 <Field S b>
 136 invokestatic #1251 <Method Rc u(S)>
 139 invokestatic #1366 <Method Rc s(Rc, Rc)>
 142 areturn
 143 new #797 <Class Rc>
 146 dup
 147 aload_0
 148 checkcast #816 <Class Sb>
 151 getfield #1118 <Field int a>
 154 aconst_null
 155 invokespecial #1256 <Method Rc(int,Rc)>
 158 areturn

Method Rc v(S)
   0 goto 29
   3 aconst_null
   4 areturn
   5 new #797 <Class Rc>
   8 dup
   9 aload_0
  10 checkcast #816 <Class Sb>
  13 getfield #1118 <Field int a>
  16 aconst_null
  17 invokespecial #1256 <Method Rc(int,Rc)>
  20 areturn
  21 aload_0
  22 checkcast #820 <Class Sd>
  25 getfield #1178 <Field S a>
  28 astore_0
  29 aload_0
  30 getfield #1147 <Field int $>
  33 tableswitch 0 to 5: default=143
	    0: 120
	    1: 72
	    2: 104
	    3: 21
	    4: 5
	    5: 3
  72 aload_0
  73 checkcast #811 <Class Sa>
  76 dup
  77 astore_1
  78 getfield #1168 <Field S a>
  81 dup
  82 astore_0
  83 invokestatic #1253 <Method int t(S)>
  86 ifeq 29
  89 aload_0
  90 invokestatic #1352 <Method Rc v(S)>
  93 aload_1
  94 getfield #1120 <Field S b>
  97 invokestatic #1352 <Method Rc v(S)>
 100 invokestatic #1366 <Method Rc s(Rc, Rc)>
 103 areturn
 104 new #797 <Class Rc>
 107 dup
 108 aload_0
 109 checkcast #825 <Class Sc>
 112 getfield #1112 <Field int b>
 115 aconst_null
 116 invokespecial #1256 <Method Rc(int,Rc)>
 119 areturn
 120 aload_0
 121 checkcast #811 <Class Sa>
 124 dup
 125 astore_2
 126 getfield #1168 <Field S a>
 129 invokestatic #1352 <Method Rc v(S)>
 132 aload_2
 133 getfield #1120 <Field S b>
 136 invokestatic #1352 <Method Rc v(S)>
 139 invokestatic #1366 <Method Rc s(Rc, Rc)>
 142 areturn
 143 new #797 <Class Rc>
 146 dup
 147 aload_0
 148 checkcast #816 <Class Sb>
 151 getfield #1118 <Field int a>
 154 aconst_null
 155 invokespecial #1256 <Method Rc(int,Rc)>
 158 areturn

Method char w(Ro, java.io.BufferedInputStream, Rr)
   0 aload_2
   1 getfield #1143 <Field Ro b>
   4 dup
   5 astore 10
   7 getfield #1150 <Field int a>
  10 aload_2
  11 getfield #1110 <Field Rp a>
  14 dup
  15 astore 9
  17 getfield #1094 <Field java.lang.String a>
  20 invokevirtual #1356 <Method int length()>
  23 if_icmpne 238
  26 iconst_1
  27 istore_3
  28 iload_3
  29 ifeq 184
  32 sipush 1024
  35 newarray byte
  37 astore 4
  39 aload_1
  40 aload 4
  42 iconst_0
  43 sipush 1024
  46 invokevirtual #1293 <Method int read(byte[], int, int)>
  49 istore 6
  51 iload 6
  53 ifge 243
  56 iconst_1
  57 istore 7
  59 iload 7
  61 ifeq 150
  64 new #823 <Class java.lang.String>
  67 dup
  68 aload 4
  70 iconst_0
  71 iconst_0
  72 iconst_0
  73 invokespecial #1313 <Method java.lang.String(byte[],int,int,int)>
  76 astore 11
  78 aload 9
  80 aload 10
  82 iconst_0
  83 aload 9
  85 aload 11
  87 putfield #1094 <Field java.lang.String a>
  90 putfield #1150 <Field int a>
  93 getfield #1094 <Field java.lang.String a>
  96 invokevirtual #1356 <Method int length()>
  99 ifne 249
 102 iconst_1
 103 istore 12
 105 iload 12
 107 ifeq 0
 110 new #827 <Class Ed>
 113 dup
 114 invokespecial #1359 <Method Ed()>
 117 athrow
 118 astore 5
 120 new #835 <Class Eb>
 123 dup
 124 aload 5
 126 ldc #174 <String "inputN">
 128 ldc #176 <String "java.io.BufferedInputStream">
 130 invokespecial #1259 <Method Eb(java.lang.Exception,java.lang.String,java.lang.String)>
 133 athrow
 134 astore 8
 136 new #835 <Class Eb>
 139 dup
 140 aload 8
 142 ldc #174 <String "inputN">
 144 ldc #176 <String "java.io.BufferedInputStream">
 146 invokespecial #1259 <Method Eb(java.lang.Exception,java.lang.String,java.lang.String)>
 149 athrow
 150 new #823 <Class java.lang.String>
 153 dup
 154 aload 4
 156 iconst_0
 157 iconst_0
 158 iload 6
 160 invokespecial #1313 <Method java.lang.String(byte[],int,int,int)>
 163 astore 11
 165 goto 78
 168 astore 13
 170 new #835 <Class Eb>
 173 dup
 174 aload 13
 176 ldc #174 <String "inputN">
 178 ldc #176 <String "java.io.BufferedInputStream">
 180 invokespecial #1259 <Method Eb(java.lang.Exception,java.lang.String,java.lang.String)>
 183 athrow
 184 aload 9
 186 getfield #1094 <Field java.lang.String a>
 189 aload 10
 191 getfield #1150 <Field int a>
 194 invokevirtual #1283 <Method char charAt(int)>
 197 dup
 198 istore 14
 200 bipush 10
 202 if_icmpne 255
 205 iconst_1
 206 istore 15
 208 iload 15
 210 ifeq 223
 213 aload_0
 214 aload_0
 215 getfield #1150 <Field int a>
 218 iconst_1
 219 iadd
 220 putfield #1150 <Field int a>
 223 iload 14
 225 aload 10
 227 aload 10
 229 getfield #1150 <Field int a>
 232 iconst_1
 233 iadd
 234 putfield #1150 <Field int a>
 237 ireturn
 238 iconst_0
 239 istore_3
 240 goto 28
 243 iconst_0
 244 istore 7
 246 goto 59
 249 iconst_0
 250 istore 12
 252 goto 105
 255 iconst_0
 256 istore 15
 258 goto 208
Exception table:
   from   to  target type
   150   165   168   <Class java.io.IOException>
    64    78   134   <Class java.io.IOException>
    39    51   118   <Class java.io.IOException>

Method void x(Ro, java.io.BufferedInputStream, Rr)
   0 aload_2
   1 getfield #1110 <Field Rp a>
   4 aload_2
   5 getfield #1143 <Field Ro b>
   8 dup
   9 astore_3
  10 aload_3
  11 getfield #1150 <Field int a>
  14 iconst_m1
  15 iadd
  16 putfield #1150 <Field int a>
  19 getfield #1094 <Field java.lang.String a>
  22 aload_3
  23 getfield #1150 <Field int a>
  26 invokevirtual #1283 <Method char charAt(int)>
  29 bipush 10
  31 if_icmpne 54
  34 iconst_1
  35 istore 4
  37 iload 4
  39 ifne 43
  42 return
  43 aload_0
  44 aload_0
  45 getfield #1150 <Field int a>
  48 iconst_m1
  49 iadd
  50 putfield #1150 <Field int a>
  53 return
  54 iconst_0
  55 istore 4
  57 goto 37

Method S y(java.io.BufferedOutputStream, Ro, java.lang.String)
   0 new #833 <Class Ee>
   3 dup
   4 aload_0
   5 new #815 <Class Rk>
   8 dup
   9 ldc #182 <String "ml-lex: error, line ">
  11 new #815 <Class Rk>
  14 dup
  15 aload_1
  16 getfield #1150 <Field int a>
  19 bipush 10
  21 invokestatic #1341 <Method java.lang.String toString(int, int)>
  24 bipush 45
  26 bipush 126
  28 invokevirtual #1245 <Method java.lang.String replace(char, char)>
  31 new #815 <Class Rk>
  34 dup
  35 ldc #9 <String ": ">
  37 new #815 <Class Rk>
  40 dup
  41 aload_2
  42 new #815 <Class Rk>
  45 dup
  46 ldc #11 <String "
">
  48 aconst_null
  49 invokespecial #1331 <Method Rk(java.lang.String,Rk)>
  52 invokespecial #1331 <Method Rk(java.lang.String,Rk)>
  55 invokespecial #1331 <Method Rk(java.lang.String,Rk)>
  58 invokespecial #1331 <Method Rk(java.lang.String,Rk)>
  61 invokespecial #1331 <Method Rk(java.lang.String,Rk)>
  64 invokestatic #1286 <Method java.lang.String g(Rk)>
  67 invokestatic #1208 <Method void i(java.io.BufferedOutputStream, java.lang.String)>
  70 invokespecial #1371 <Method Ee()>
  73 athrow

Method void z(java.io.BufferedOutputStream, Ro, java.lang.String)
   0 new #833 <Class Ee>
   3 dup
   4 aload_0
   5 new #815 <Class Rk>
   8 dup
   9 ldc #182 <String "ml-lex: error, line ">
  11 new #815 <Class Rk>
  14 dup
  15 aload_1
  16 getfield #1150 <Field int a>
  19 bipush 10
  21 invokestatic #1341 <Method java.lang.String toString(int, int)>
  24 bipush 45
  26 bipush 126
  28 invokevirtual #1245 <Method java.lang.String replace(char, char)>
  31 new #815 <Class Rk>
  34 dup
  35 ldc #9 <String ": ">
  37 new #815 <Class Rk>
  40 dup
  41 aload_2
  42 new #815 <Class Rk>
  45 dup
  46 ldc #11 <String "
">
  48 aconst_null
  49 invokespecial #1331 <Method Rk(java.lang.String,Rk)>
  52 invokespecial #1331 <Method Rk(java.lang.String,Rk)>
  55 invokespecial #1331 <Method Rk(java.lang.String,Rk)>
  58 invokespecial #1331 <Method Rk(java.lang.String,Rk)>
  61 invokespecial #1331 <Method Rk(java.lang.String,Rk)>
  64 invokestatic #1286 <Method java.lang.String g(Rk)>
  67 invokestatic #1208 <Method void i(java.io.BufferedOutputStream, java.lang.String)>
  70 invokespecial #1371 <Method Ee()>
  73 athrow

Method S A(java.io.BufferedOutputStream, Ro, java.lang.String)
   0 new #833 <Class Ee>
   3 dup
   4 aload_0
   5 new #815 <Class Rk>
   8 dup
   9 ldc #17 <String "ml-lex: syntax error, line ">
  11 new #815 <Class Rk>
  14 dup
  15 aload_1
  16 getfield #1150 <Field int a>
  19 bipush 10
  21 invokestatic #1341 <Method java.lang.String toString(int, int)>
  24 bipush 45
  26 bipush 126
  28 invokevirtual #1245 <Method java.lang.String replace(char, char)>
  31 new #815 <Class Rk>
  34 dup
  35 ldc #9 <String ": ">
  37 new #815 <Class Rk>
  40 dup
  41 aload_2
  42 new #815 <Class Rk>
  45 dup
  46 ldc #11 <String "
">
  48 aconst_null
  49 invokespecial #1331 <Method Rk(java.lang.String,Rk)>
  52 invokespecial #1331 <Method Rk(java.lang.String,Rk)>
  55 invokespecial #1331 <Method Rk(java.lang.String,Rk)>
  58 invokespecial #1331 <Method Rk(java.lang.String,Rk)>
  61 invokespecial #1331 <Method Rk(java.lang.String,Rk)>
  64 invokestatic #1286 <Method java.lang.String g(Rk)>
  67 invokestatic #1208 <Method void i(java.io.BufferedOutputStream, java.lang.String)>
  70 invokespecial #1371 <Method Ee()>
  73 athrow

Method Rv B(java.io.BufferedOutputStream, Ro, java.lang.String)
   0 new #833 <Class Ee>
   3 dup
   4 aload_0
   5 new #815 <Class Rk>
   8 dup
   9 ldc #17 <String "ml-lex: syntax error, line ">
  11 new #815 <Class Rk>
  14 dup
  15 aload_1
  16 getfield #1150 <Field int a>
  19 bipush 10
  21 invokestatic #1341 <Method java.lang.String toString(int, int)>
  24 bipush 45
  26 bipush 126
  28 invokevirtual #1245 <Method java.lang.String replace(char, char)>
  31 new #815 <Class Rk>
  34 dup
  35 ldc #9 <String ": ">
  37 new #815 <Class Rk>
  40 dup
  41 aload_2
  42 new #815 <Class Rk>
  45 dup
  46 ldc #11 <String "
">
  48 aconst_null
  49 invokespecial #1331 <Method Rk(java.lang.String,Rk)>
  52 invokespecial #1331 <Method Rk(java.lang.String,Rk)>
  55 invokespecial #1331 <Method Rk(java.lang.String,Rk)>
  58 invokespecial #1331 <Method Rk(java.lang.String,Rk)>
  61 invokespecial #1331 <Method Rk(java.lang.String,Rk)>
  64 invokestatic #1286 <Method java.lang.String g(Rk)>
  67 invokestatic #1208 <Method void i(java.io.BufferedOutputStream, java.lang.String)>
  70 invokespecial #1371 <Method Ee()>
  73 athrow

Method void C(java.io.BufferedOutputStream, Ro, Ro, Rx, Ro, Ry, Ro)
   0 aload 4
   2 getfield #1150 <Field int a>
   5 tableswitch 0 to 2: default=648
	    0: 256
	    1: 221
	    2: 32
  32 aload_2
  33 aload_3
  34 invokestatic #1282 <Method char J(Ro, Rx)>
  37 istore 7
  39 iload 7
  41 lookupswitch 2: default=68
	   40: 180
	   59: 165
  68 iload 7
  70 invokestatic #1342 <Method java.lang.String valueOf(char)>
  73 astore 10
  75 ldc #19 <String "invalid character ">
  77 aload 10
  79 invokevirtual #1235 <Method java.lang.String concat(java.lang.String)>
  82 astore 12
  84 aload_0
  85 aload_2
  86 aload 12
  88 invokestatic #1312 <Method S A(java.io.BufferedOutputStream, Ro, java.lang.String)>
  91 astore 13
  93 aload 5
  95 aload 13
  97 putfield #1115 <Field S a>
 100 return
 101 pop
 102 aload 5
 104 new #770 <Class S>
 107 dup
 108 bipush 10
 110 invokespecial #1362 <Method S(int)>
 113 putfield #1115 <Field S a>
 116 return
 117 pop
 118 aload 5
 120 new #770 <Class S>
 123 dup
 124 bipush 10
 126 invokespecial #1362 <Method S(int)>
 129 putfield #1115 <Field S a>
 132 return
 133 pop
 134 aload 5
 136 new #770 <Class S>
 139 dup
 140 bipush 10
 142 invokespecial #1362 <Method S(int)>
 145 putfield #1115 <Field S a>
 148 return
 149 pop
 150 aload 5
 152 new #770 <Class S>
 155 dup
 156 bipush 10
 158 invokespecial #1362 <Method S(int)>
 161 putfield #1115 <Field S a>
 164 return
 165 aload 5
 167 new #770 <Class S>
 170 dup
 171 bipush 22
 173 invokespecial #1362 <Method S(int)>
 176 putfield #1115 <Field S a>
 179 return
 180 aload_2
 181 aload_3
 182 iconst_0
 183 aconst_null
 184 invokestatic #1300 <Method java.lang.String T(Ro, Rx, int, Ri)>
 187 astore 15
 189 aload 5
 191 new #798 <Class Sf>
 194 dup
 195 aload 15
 197 iconst_0
 198 invokespecial #1223 <Method Sf(java.lang.String,int)>
 201 putfield #1115 <Field S a>
 204 return
 205 pop
 206 aload 5
 208 new #770 <Class S>
 211 dup
 212 bipush 10
 214 invokespecial #1362 <Method S(int)>
 217 putfield #1115 <Field S a>
 220 return
 221 aload_0
 222 aload_1
 223 aload_2
 224 aload_3
 225 aload 6
 227 invokestatic #1309 <Method S N(java.io.BufferedOutputStream, Ro, Ro, Rx, Ro)>
 230 astore 17
 232 aload 5
 234 aload 17
 236 putfield #1115 <Field S a>
 239 return
 240 pop
 241 aload 5
 243 new #770 <Class S>
 246 dup
 247 bipush 10
 249 invokespecial #1362 <Method S(int)>
 252 putfield #1115 <Field S a>
 255 return
 256 aload_2
 257 aload_3
 258 invokestatic #1282 <Method char J(Ro, Rx)>
 261 istore 23
 263 iload 23
 265 lookupswitch 2: default=292
	   37: 466
	   59: 451
 292 iload 23
 294 invokestatic #1337 <Method int D(char)>
 297 ifne 349
 300 iload 23
 302 invokestatic #1342 <Method java.lang.String valueOf(char)>
 305 astore 25
 307 ldc #33 <String "bad character: ">
 309 aload 25
 311 invokevirtual #1235 <Method java.lang.String concat(java.lang.String)>
 314 astore 27
 316 aload_0
 317 aload_2
 318 aload 27
 320 invokestatic #1312 <Method S A(java.io.BufferedOutputStream, Ro, java.lang.String)>
 323 astore 28
 325 aload 5
 327 aload 28
 329 putfield #1115 <Field S a>
 332 return
 333 pop
 334 aload 5
 336 new #770 <Class S>
 339 dup
 340 bipush 10
 342 invokespecial #1362 <Method S(int)>
 345 putfield #1115 <Field S a>
 348 return
 349 new #801 <Class Ri>
 352 dup
 353 iload 23
 355 aconst_null
 356 invokespecial #1238 <Method Ri(char,Ri)>
 359 astore 20
 361 aload_2
 362 aload_3
 363 aload 20
 365 invokestatic #1278 <Method java.lang.String K(Ro, Rx, Ri)>
 368 astore 21
 370 aload 5
 372 new #798 <Class Sf>
 375 dup
 376 aload 21
 378 bipush 13
 380 invokespecial #1223 <Method Sf(java.lang.String,int)>
 383 putfield #1115 <Field S a>
 386 return
 387 pop
 388 aload 5
 390 new #770 <Class S>
 393 dup
 394 bipush 10
 396 invokespecial #1362 <Method S(int)>
 399 putfield #1115 <Field S a>
 402 return
 403 pop
 404 aload 5
 406 new #770 <Class S>
 409 dup
 410 bipush 10
 412 invokespecial #1362 <Method S(int)>
 415 putfield #1115 <Field S a>
 418 return
 419 pop
 420 aload 5
 422 new #770 <Class S>
 425 dup
 426 bipush 10
 428 invokespecial #1362 <Method S(int)>
 431 putfield #1115 <Field S a>
 434 return
 435 pop
 436 aload 5
 438 new #770 <Class S>
 441 dup
 442 bipush 10
 444 invokespecial #1362 <Method S(int)>
 447 putfield #1115 <Field S a>
 450 return
 451 aload 5
 453 new #770 <Class S>
 456 dup
 457 bipush 22
 459 invokespecial #1362 <Method S(int)>
 462 putfield #1115 <Field S a>
 465 return
 466 aload_3
 467 getfield #1164 <Field Rw a>
 470 dup
 471 astore 30
 473 getfield #1135 <Field java.io.BufferedInputStream a>
 476 astore 31
 478 aload 30
 480 getfield #1101 <Field Rr b>
 483 astore 32
 485 aload_2
 486 aload 31
 488 aload 32
 490 invokestatic #1219 <Method char w(Ro, java.io.BufferedInputStream, Rr)>
 493 istore 33
 495 bipush 37
 497 iload 33
 499 if_icmpne 533
 502 aload 5
 504 new #770 <Class S>
 507 dup
 508 bipush 14
 510 invokespecial #1362 <Method S(int)>
 513 putfield #1115 <Field S a>
 516 return
 517 pop
 518 aload 5
 520 new #770 <Class S>
 523 dup
 524 bipush 10
 526 invokespecial #1362 <Method S(int)>
 529 putfield #1115 <Field S a>
 532 return
 533 new #801 <Class Ri>
 536 dup
 537 iload 33
 539 aconst_null
 540 invokespecial #1238 <Method Ri(char,Ri)>
 543 astore 35
 545 aload_2
 546 aload_3
 547 aload 35
 549 invokestatic #1276 <Method java.lang.String L(Ro, Rx, Ri)>
 552 astore 36
 554 aload 36
 556 ldc #46 <String "reject">
 558 invokevirtual #1198 <Method boolean equals(java.lang.Object)>
 561 ifne 614
 564 aload_0
 565 aload_2
 566 aload 36
 568 iconst_0
 569 invokestatic #1252 <Method S M(java.io.BufferedOutputStream, Ro, java.lang.String, int)>
 572 astore 38
 574 aload 5
 576 aload 38
 578 putfield #1115 <Field S a>
 581 return
 582 pop
 583 aload 5
 585 new #770 <Class S>
 588 dup
 589 bipush 10
 591 invokespecial #1362 <Method S(int)>
 594 putfield #1115 <Field S a>
 597 return
 598 pop
 599 aload 5
 601 new #770 <Class S>
 604 dup
 605 bipush 10
 607 invokespecial #1362 <Method S(int)>
 610 putfield #1115 <Field S a>
 613 return
 614 aload_0
 615 aload_2
 616 aload 36
 618 iconst_1
 619 invokestatic #1252 <Method S M(java.io.BufferedOutputStream, Ro, java.lang.String, int)>
 622 astore 40
 624 aload 5
 626 aload 40
 628 putfield #1115 <Field S a>
 631 return
 632 pop
 633 aload 5
 635 new #770 <Class S>
 638 dup
 639 bipush 10
 641 invokespecial #1362 <Method S(int)>
 644 putfield #1115 <Field S a>
 647 return
 648 new #818 <Class Ef>
 651 dup
 652 invokespecial #1241 <Method Ef()>
 655 athrow
Exception table:
   from   to  target type
   614   624   632   <Class Ed>
   564   574   598   <Class Ed>
   545   554   582   <Class Ed>
   485   495   517   <Class Ed>
   361   370   387   <Class Ed>
   316   325   435   <Class Ed>
   307   316   419   <Class Ed>
   300   307   403   <Class Ed>
   256   263   333   <Class Ed>
   221   232   240   <Class Ed>
   180   189   205   <Class Ed>
    84    93   149   <Class Ed>
    75    84   133   <Class Ed>
    68    75   117   <Class Ed>
    32    39   101   <Class Ed>

Method int D(char)
   0 iload_0
   1 bipush 97
   3 if_icmplt 38
   6 iload_0
   7 bipush 122
   9 if_icmpgt 43
  12 iconst_1
  13 istore_1
  14 iload_1
  15 ifne 32
  18 iload_0
  19 bipush 65
  21 if_icmplt 34
  24 iload_0
  25 bipush 90
  27 if_icmpgt 36
  30 iconst_1
  31 ireturn
  32 iconst_1
  33 ireturn
  34 iconst_0
  35 ireturn
  36 iconst_0
  37 ireturn
  38 iconst_0
  39 istore_1
  40 goto 14
  43 iconst_0
  44 istore_1
  45 goto 14

Method int E(char)
   0 iload_0
   1 bipush 48
   3 if_icmplt 14
   6 iload_0
   7 bipush 57
   9 if_icmpgt 16
  12 iconst_1
  13 ireturn
  14 iconst_0
  15 ireturn
  16 iconst_0
  17 ireturn

Method int F(char)
   0 iload_0
   1 invokestatic #1337 <Method int D(char)>
   4 ifne 22
   7 iload_0
   8 invokestatic #1200 <Method int E(char)>
  11 ifne 24
  14 iload_0
  15 bipush 95
  17 if_icmpne 26
  20 iconst_1
  21 ireturn
  22 iconst_1
  23 ireturn
  24 iconst_1
  25 ireturn
  26 iload_0
  27 bipush 39
  29 if_icmpne 34
  32 iconst_1
  33 ireturn
  34 iconst_0
  35 ireturn

Method int G(java.lang.String)
   0 aload_0
   1 aload_0
   2 invokevirtual #1356 <Method int length()>
   5 aconst_null
   6 invokestatic #1378 <Method Ri H(java.lang.String, int, Ri)>
   9 astore_1
  10 iconst_0
  11 istore_2
  12 goto 30
  15 iload_2
  16 bipush 10
  18 imul
  19 iload_3
  20 bipush -48
  22 iadd
  23 iadd
  24 istore_2
  25 aload_1
  26 getfield #1098 <Field Ri b>
  29 astore_1
  30 aload_1
  31 ifnull 48
  34 aload_1
  35 getfield #1103 <Field char a>
  38 dup
  39 istore_3
  40 invokestatic #1200 <Method int E(char)>
  43 ifne 15
  46 iload_2
  47 ireturn
  48 iload_2
  49 ireturn

Method Ri H(java.lang.String, int, Ri)
   0 goto 21
   3 new #801 <Class Ri>
   6 dup
   7 aload_0
   8 iload_1
   9 iconst_m1
  10 iadd
  11 dup
  12 istore_1
  13 invokevirtual #1283 <Method char charAt(int)>
  16 aload_2
  17 invokespecial #1238 <Method Ri(char,Ri)>
  20 astore_2
  21 iload_1
  22 ifne 3
  25 aload_2
  26 areturn

Method char I(java.io.BufferedOutputStream, Ro, Ro, Rx)
   0 aload_2
   1 aload_3
   2 getfield #1164 <Field Rw a>
   5 dup
   6 astore 4
   8 getfield #1135 <Field java.io.BufferedInputStream a>
  11 aload 4
  13 getfield #1101 <Field Rr b>
  16 invokestatic #1219 <Method char w(Ro, java.io.BufferedInputStream, Rr)>
  19 dup
  20 istore 5
  22 lookupswitch 4: default=64
	   98: 229
	  104: 225
	  110: 222
	  116: 219
  64 iload 5
  66 invokestatic #1200 <Method int E(char)>
  69 ifne 75
  72 iload 5
  74 ireturn
  75 new #801 <Class Ri>
  78 dup
  79 iload 5
  81 aconst_null
  82 invokespecial #1238 <Method Ri(char,Ri)>
  85 astore 8
  87 iload 5
  89 bipush -48
  91 iadd
  92 istore 6
  94 iconst_1
  95 istore 7
  97 goto 300
 100 iload 6
 102 aload_1
 103 getfield #1150 <Field int a>
 106 if_icmplt 312
 109 iconst_1
 110 istore 10
 112 iload 10
 114 ifne 123
 117 iload 6
 119 invokestatic #1250 <Method char f(int)>
 122 ireturn
 123 new #833 <Class Ee>
 126 dup
 127 aload_0
 128 new #815 <Class Rk>
 131 dup
 132 ldc #182 <String "ml-lex: error, line ">
 134 new #815 <Class Rk>
 137 dup
 138 aload_2
 139 ldc #58 <String "illegal ascii escape '">
 141 aload 8
 143 aconst_null
 144 invokestatic #1274 <Method Ri c(Ri, Ri)>
 147 invokestatic #1199 <Method java.lang.String h(Ri)>
 150 invokevirtual #1235 <Method java.lang.String concat(java.lang.String)>
 153 ldc #63 <String "'">
 155 invokevirtual #1235 <Method java.lang.String concat(java.lang.String)>
 158 astore 11
 160 getfield #1150 <Field int a>
 163 bipush 10
 165 invokestatic #1341 <Method java.lang.String toString(int, int)>
 168 bipush 45
 170 bipush 126
 172 invokevirtual #1245 <Method java.lang.String replace(char, char)>
 175 new #815 <Class Rk>
 178 dup
 179 ldc #9 <String ": ">
 181 new #815 <Class Rk>
 184 dup
 185 aload 11
 187 new #815 <Class Rk>
 190 dup
 191 ldc #11 <String "
">
 193 aconst_null
 194 invokespecial #1331 <Method Rk(java.lang.String,Rk)>
 197 invokespecial #1331 <Method Rk(java.lang.String,Rk)>
 200 invokespecial #1331 <Method Rk(java.lang.String,Rk)>
 203 invokespecial #1331 <Method Rk(java.lang.String,Rk)>
 206 invokespecial #1331 <Method Rk(java.lang.String,Rk)>
 209 invokestatic #1286 <Method java.lang.String g(Rk)>
 212 invokestatic #1208 <Method void i(java.io.BufferedOutputStream, java.lang.String)>
 215 invokespecial #1371 <Method Ee()>
 218 athrow
 219 bipush 9
 221 ireturn
 222 bipush 10
 224 ireturn
 225 sipush 128
 228 ireturn
 229 bipush 8
 231 ireturn
 232 iconst_0
 233 istore 9
 235 iload 9
 237 ifne 100
 240 aload_2
 241 aload_3
 242 getfield #1164 <Field Rw a>
 245 dup
 246 astore 12
 248 getfield #1135 <Field java.io.BufferedInputStream a>
 251 aload 12
 253 getfield #1101 <Field Rr b>
 256 invokestatic #1219 <Method char w(Ro, java.io.BufferedInputStream, Rr)>
 259 dup
 260 istore 13
 262 invokestatic #1200 <Method int E(char)>
 265 ifeq 123
 268 new #801 <Class Ri>
 271 dup
 272 iload 13
 274 aload 8
 276 invokespecial #1238 <Method Ri(char,Ri)>
 279 astore 8
 281 iload 7
 283 iconst_1
 284 iadd
 285 istore 7
 287 iload 6
 289 bipush 10
 291 imul
 292 iload 13
 294 bipush -48
 296 iadd
 297 iadd
 298 istore 6
 300 iload 7
 302 iconst_3
 303 if_icmpne 232
 306 iconst_1
 307 istore 9
 309 goto 235
 312 iconst_0
 313 istore 10
 315 goto 112

Method char J(Ro, Rx)
   0 aload_0
   1 aload_1
   2 getfield #1164 <Field Rw a>
   5 dup
   6 astore_2
   7 getfield #1135 <Field java.io.BufferedInputStream a>
  10 aload_2
  11 getfield #1101 <Field Rr b>
  14 invokestatic #1219 <Method char w(Ro, java.io.BufferedInputStream, Rr)>
  17 dup
  18 istore_3
  19 lookupswitch 3: default=52
	    9: 0
	   10: 0
	   32: 0
  52 iload_3
  53 ireturn

Method java.lang.String K(Ro, Rx, Ri)
   0 goto 14
   3 new #801 <Class Ri>
   6 dup
   7 iload 4
   9 aload_2
  10 invokespecial #1238 <Method Ri(char,Ri)>
  13 astore_2
  14 aload_0
  15 aload_1
  16 getfield #1164 <Field Rw a>
  19 dup
  20 astore_3
  21 getfield #1135 <Field java.io.BufferedInputStream a>
  24 aload_3
  25 getfield #1101 <Field Rr b>
  28 invokestatic #1219 <Method char w(Ro, java.io.BufferedInputStream, Rr)>
  31 dup
  32 istore 4
  34 invokestatic #1228 <Method int F(char)>
  37 ifne 3
  40 aload_2
  41 aconst_null
  42 aload_0
  43 aload_1
  44 getfield #1164 <Field Rw a>
  47 dup
  48 astore 5
  50 getfield #1135 <Field java.io.BufferedInputStream a>
  53 aload 5
  55 getfield #1101 <Field Rr b>
  58 invokestatic #1330 <Method void x(Ro, java.io.BufferedInputStream, Rr)>
  61 invokestatic #1274 <Method Ri c(Ri, Ri)>
  64 invokestatic #1199 <Method java.lang.String h(Ri)>
  67 areturn

Method java.lang.String L(Ro, Rx, Ri)
   0 goto 14
   3 new #801 <Class Ri>
   6 dup
   7 iload 4
   9 aload_2
  10 invokespecial #1238 <Method Ri(char,Ri)>
  13 astore_2
  14 aload_0
  15 aload_1
  16 getfield #1164 <Field Rw a>
  19 dup
  20 astore_3
  21 getfield #1135 <Field java.io.BufferedInputStream a>
  24 aload_3
  25 getfield #1101 <Field Rr b>
  28 invokestatic #1219 <Method char w(Ro, java.io.BufferedInputStream, Rr)>
  31 dup
  32 istore 4
  34 invokestatic #1337 <Method int D(char)>
  37 ifne 3
  40 aload_2
  41 aconst_null
  42 aload_0
  43 aload_1
  44 getfield #1164 <Field Rw a>
  47 dup
  48 astore 5
  50 getfield #1135 <Field java.io.BufferedInputStream a>
  53 aload 5
  55 getfield #1101 <Field Rr b>
  58 invokestatic #1330 <Method void x(Ro, java.io.BufferedInputStream, Rr)>
  61 invokestatic #1274 <Method Ri c(Ri, Ri)>
  64 invokestatic #1199 <Method java.lang.String h(Ri)>
  67 areturn

Method S M(java.io.BufferedOutputStream, Ro, java.lang.String, int)
   0 iload_3
   1 ifne 131
   4 aload_2
   5 ldc #68 <String "count">
   7 invokevirtual #1198 <Method boolean equals(java.lang.Object)>
  10 ifne 210
  13 iconst_0
  14 istore 4
  16 iload 4
  18 ifne 141
  21 aload_2
  22 ldc #70 <String "full">
  24 invokevirtual #1198 <Method boolean equals(java.lang.Object)>
  27 ifne 216
  30 iconst_0
  31 istore 5
  33 iload 5
  35 ifne 151
  38 aload_2
  39 ldc #62 <String "s">
  41 invokevirtual #1198 <Method boolean equals(java.lang.Object)>
  44 ifne 222
  47 iconst_0
  48 istore 6
  50 iload 6
  52 ifne 161
  55 aload_2
  56 ldc #107 <String "S">
  58 invokevirtual #1198 <Method boolean equals(java.lang.Object)>
  61 ifne 228
  64 iconst_0
  65 istore 7
  67 iload 7
  69 ifne 171
  72 aload_2
  73 ldc #76 <String "structure">
  75 invokevirtual #1198 <Method boolean equals(java.lang.Object)>
  78 ifne 234
  81 iconst_0
  82 istore 8
  84 iload 8
  86 ifne 181
  89 aload_2
  90 ldc #80 <String "header">
  92 invokevirtual #1198 <Method boolean equals(java.lang.Object)>
  95 ifne 240
  98 iconst_0
  99 istore 9
 101 iload 9
 103 ifne 191
 106 aload_2
 107 ldc #83 <String "arg">
 109 invokevirtual #1198 <Method boolean equals(java.lang.Object)>
 112 ifne 246
 115 iconst_0
 116 istore 10
 118 iload 10
 120 ifne 201
 123 aload_0
 124 aload_1
 125 ldc #86 <String "unknown % operator ">
 127 invokestatic #1248 <Method S y(java.io.BufferedOutputStream, Ro, java.lang.String)>
 130 areturn
 131 new #770 <Class S>
 134 dup
 135 bipush 19
 137 invokespecial #1362 <Method S(int)>
 140 areturn
 141 new #770 <Class S>
 144 dup
 145 bipush 8
 147 invokespecial #1362 <Method S(int)>
 150 areturn
 151 new #770 <Class S>
 154 dup
 155 bipush 11
 157 invokespecial #1362 <Method S(int)>
 160 areturn
 161 new #770 <Class S>
 164 dup
 165 bipush 15
 167 invokespecial #1362 <Method S(int)>
 170 areturn
 171 new #770 <Class S>
 174 dup
 175 bipush 15
 177 invokespecial #1362 <Method S(int)>
 180 areturn
 181 new #770 <Class S>
 184 dup
 185 bipush 26
 187 invokespecial #1362 <Method S(int)>
 190 areturn
 191 new #770 <Class S>
 194 dup
 195 bipush 12
 197 invokespecial #1362 <Method S(int)>
 200 areturn
 201 new #770 <Class S>
 204 dup
 205 iconst_1
 206 invokespecial #1362 <Method S(int)>
 209 areturn
 210 iconst_1
 211 istore 4
 213 goto 16
 216 iconst_1
 217 istore 5
 219 goto 33
 222 iconst_1
 223 istore 6
 225 goto 50
 228 iconst_1
 229 istore 7
 231 goto 67
 234 iconst_1
 235 istore 8
 237 goto 84
 240 iconst_1
 241 istore 9
 243 goto 101
 246 iconst_1
 247 istore 10
 249 goto 118

Method S N(java.io.BufferedOutputStream, Ro, Ro, Rx, Ro)
   0 goto 9
   3 aload 4
   5 iconst_0
   6 putfield #1150 <Field int a>
   9 aload 4
  11 getfield #1150 <Field int a>
  14 ifeq 100
  17 aload_2
  18 aload_3
  19 getfield #1164 <Field Rw a>
  22 dup
  23 astore 5
  25 getfield #1135 <Field java.io.BufferedInputStream a>
  28 aload 5
  30 getfield #1101 <Field Rr b>
  33 invokestatic #1219 <Method char w(Ro, java.io.BufferedInputStream, Rr)>
  36 dup
  37 istore 6
  39 lookupswitch 2: default=73
	   34: 3
	   92: 64
  64 aload_0
  65 aload_1
  66 aload_2
  67 aload_3
  68 invokestatic #1358 <Method char I(java.io.BufferedOutputStream, Ro, Ro, Rx)>
  71 istore 6
  73 new #837 <Class Se>
  76 dup
  77 aload_1
  78 getfield #1150 <Field int a>
  81 iconst_0
  82 invokestatic #1195 <Method int j(int, int)[]>
  85 dup
  86 astore 7
  88 bipush 7
  90 aload 7
  92 iload 6
  94 iconst_1
  95 iastore
  96 invokespecial #1261 <Method Se(int[],int)>
  99 areturn
 100 aload_2
 101 aload_3
 102 invokestatic #1282 <Method char J(Ro, Rx)>
 105 dup
 106 istore 6
 108 lookupswitch 18: default=73
	   34: 264
	   36: 765
	   37: 697
	   40: 687
	   41: 677
	   42: 667
	   43: 657
	   46: 630
	   47: 620
	   59: 610
	   60: 591
	   61: 522
	   63: 512
	   91: 402
	   92: 390
	   94: 380
	  123: 282
	  124: 273
 264 aload 4
 266 iconst_1
 267 putfield #1150 <Field int a>
 270 goto 9
 273 new #770 <Class S>
 276 dup
 277 iconst_4
 278 invokespecial #1362 <Method S(int)>
 281 areturn
 282 aload_2
 283 aload_3
 284 getfield #1164 <Field Rw a>
 287 dup
 288 astore 8
 290 getfield #1135 <Field java.io.BufferedInputStream a>
 293 aload 8
 295 getfield #1101 <Field Rr b>
 298 invokestatic #1219 <Method char w(Ro, java.io.BufferedInputStream, Rr)>
 301 dup
 302 istore 9
 304 invokestatic #1337 <Method int D(char)>
 307 ifne 326
 310 iload 9
 312 invokestatic #1200 <Method int E(char)>
 315 ifne 347
 318 aload_0
 319 aload_2
 320 ldc #103 <String "bad repetitions spec">
 322 invokestatic #1248 <Method S y(java.io.BufferedOutputStream, Ro, java.lang.String)>
 325 areturn
 326 new #798 <Class Sf>
 329 dup
 330 aload_0
 331 aload_2
 332 aload_3
 333 iload 9
 335 invokestatic #1342 <Method java.lang.String valueOf(char)>
 338 invokestatic #1210 <Method java.lang.String R(java.io.BufferedOutputStream, Ro, Rx, java.lang.String)>
 341 bipush 13
 343 invokespecial #1223 <Method Sf(java.lang.String,int)>
 346 areturn
 347 new #773 <Class Sh>
 350 dup
 351 aload_0
 352 aload_2
 353 aload_3
 354 iload 9
 356 invokestatic #1342 <Method java.lang.String valueOf(char)>
 359 iconst_m1
 360 invokestatic #1384 <Method Ra S(java.io.BufferedOutputStream, Ro, Rx, java.lang.String, int)>
 363 dup
 364 astore 10
 366 getfield #1182 <Field int a>
 369 aload 10
 371 getfield #1170 <Field int b>
 374 bipush 20
 376 invokespecial #1379 <Method Sh(int,int,int)>
 379 areturn
 380 new #770 <Class S>
 383 dup
 384 bipush 6
 386 invokespecial #1362 <Method S(int)>
 389 areturn
 390 aload_0
 391 aload_1
 392 aload_2
 393 aload_3
 394 invokestatic #1358 <Method char I(java.io.BufferedOutputStream, Ro, Ro, Rx)>
 397 istore 6
 399 goto 73
 402 aload_2
 403 aload_3
 404 invokestatic #1282 <Method char J(Ro, Rx)>
 407 dup
 408 istore 12
 410 bipush 92
 412 if_icmpne 775
 415 iconst_1
 416 istore 11
 418 iload 11
 420 ifeq 432
 423 aload_0
 424 aload_1
 425 aload_2
 426 aload_3
 427 invokestatic #1358 <Method char I(java.io.BufferedOutputStream, Ro, Ro, Rx)>
 430 istore 12
 432 iload 12
 434 bipush 94
 436 if_icmpne 781
 439 iconst_0
 440 istore 13
 442 iload 13
 444 aload_1
 445 getfield #1150 <Field int a>
 448 istore 14
 450 ifne 787
 453 iconst_1
 454 istore 15
 456 iload 12
 458 bipush 94
 460 iload 14
 462 iload 15
 464 invokestatic #1195 <Method int j(int, int)[]>
 467 astore 16
 469 if_icmpne 478
 472 aconst_null
 473 astore 17
 475 goto 489
 478 new #786 <Class Rz>
 481 dup
 482 iload 12
 484 invokespecial #1374 <Method Rz(char)>
 487 astore 17
 489 new #837 <Class Se>
 492 dup
 493 aload_0
 494 aload_1
 495 aload_2
 496 aload_3
 497 iload 13
 499 aload 16
 501 aload 17
 503 invokestatic #1382 <Method int P(java.io.BufferedOutputStream, Ro, Ro, Rx, int, int[], Rz)[]>
 506 bipush 7
 508 invokespecial #1261 <Method Se(int[],int)>
 511 areturn
 512 new #770 <Class S>
 515 dup
 516 bipush 18
 518 invokespecial #1362 <Method S(int)>
 521 areturn
 522 aload_2
 523 aload_3
 524 getfield #1164 <Field Rw a>
 527 dup
 528 astore 18
 530 getfield #1135 <Field java.io.BufferedInputStream a>
 533 aload 18
 535 getfield #1101 <Field Rr b>
 538 invokestatic #1219 <Method char w(Ro, java.io.BufferedInputStream, Rr)>
 541 bipush 62
 543 if_icmpne 793
 546 iconst_1
 547 istore 19
 549 iload 19
 551 ifne 582
 554 new #770 <Class S>
 557 dup
 558 iconst_3
 559 aload_2
 560 aload_3
 561 getfield #1164 <Field Rw a>
 564 dup
 565 astore 20
 567 getfield #1135 <Field java.io.BufferedInputStream a>
 570 aload 20
 572 getfield #1101 <Field Rr b>
 575 invokestatic #1330 <Method void x(Ro, java.io.BufferedInputStream, Rr)>
 578 invokespecial #1362 <Method S(int)>
 581 areturn
 582 new #770 <Class S>
 585 dup
 586 iconst_2
 587 invokespecial #1362 <Method S(int)>
 590 areturn
 591 new #792 <Class Sg>
 594 dup
 595 aload_0
 596 aload_2
 597 aload_3
 598 aconst_null
 599 ldc #129 <String "">
 601 invokestatic #1324 <Method Rk O(java.io.BufferedOutputStream, Ro, Rx, Rk, java.lang.String)>
 604 bipush 25
 606 invokespecial #1231 <Method Sg(Rk,int)>
 609 areturn
 610 new #770 <Class S>
 613 dup
 614 bipush 22
 616 invokespecial #1362 <Method S(int)>
 619 areturn
 620 new #770 <Class S>
 623 dup
 624 bipush 23
 626 invokespecial #1362 <Method S(int)>
 629 areturn
 630 new #837 <Class Se>
 633 dup
 634 aload_1
 635 getfield #1150 <Field int a>
 638 iconst_1
 639 invokestatic #1195 <Method int j(int, int)[]>
 642 dup
 643 astore 21
 645 bipush 7
 647 aload 21
 649 bipush 10
 651 iconst_0
 652 iastore
 653 invokespecial #1261 <Method Se(int[],int)>
 656 areturn
 657 new #770 <Class S>
 660 dup
 661 bipush 17
 663 invokespecial #1362 <Method S(int)>
 666 areturn
 667 new #770 <Class S>
 670 dup
 671 bipush 24
 673 invokespecial #1362 <Method S(int)>
 676 areturn
 677 new #770 <Class S>
 680 dup
 681 bipush 21
 683 invokespecial #1362 <Method S(int)>
 686 areturn
 687 new #770 <Class S>
 690 dup
 691 bipush 16
 693 invokespecial #1362 <Method S(int)>
 696 areturn
 697 aload_2
 698 aload_3
 699 getfield #1164 <Field Rw a>
 702 dup
 703 astore 22
 705 getfield #1135 <Field java.io.BufferedInputStream a>
 708 aload 22
 710 getfield #1101 <Field Rr b>
 713 invokestatic #1219 <Method char w(Ro, java.io.BufferedInputStream, Rr)>
 716 bipush 37
 718 if_icmpne 799
 721 iconst_1
 722 istore 23
 724 iload 23
 726 ifne 755
 729 aload_2
 730 aload_3
 731 getfield #1164 <Field Rw a>
 734 dup
 735 astore 24
 737 getfield #1135 <Field java.io.BufferedInputStream a>
 740 aload 24
 742 getfield #1101 <Field Rr b>
 745 invokestatic #1330 <Method void x(Ro, java.io.BufferedInputStream, Rr)>
 748 bipush 37
 750 istore 6
 752 goto 73
 755 new #770 <Class S>
 758 dup
 759 bipush 14
 761 invokespecial #1362 <Method S(int)>
 764 areturn
 765 new #770 <Class S>
 768 dup
 769 bipush 9
 771 invokespecial #1362 <Method S(int)>
 774 areturn
 775 iconst_0
 776 istore 11
 778 goto 418
 781 iconst_1
 782 istore 13
 784 goto 442
 787 iconst_0
 788 istore 15
 790 goto 456
 793 iconst_0
 794 istore 19
 796 goto 549
 799 iconst_0
 800 istore 23
 802 goto 724

Method Rk O(java.io.BufferedOutputStream, Ro, Rx, Rk, java.lang.String)
   0 goto 23
   3 iload 6
   5 invokestatic #1228 <Method int F(char)>
   8 ifeq 90
  11 aload 4
  13 iload 6
  15 invokestatic #1342 <Method java.lang.String valueOf(char)>
  18 invokevirtual #1235 <Method java.lang.String concat(java.lang.String)>
  21 astore 4
  23 aload_1
  24 aload_2
  25 getfield #1164 <Field Rw a>
  28 dup
  29 astore 5
  31 getfield #1135 <Field java.io.BufferedInputStream a>
  34 aload 5
  36 getfield #1101 <Field Rr b>
  39 invokestatic #1219 <Method char w(Ro, java.io.BufferedInputStream, Rr)>
  42 dup
  43 istore 6
  45 lookupswitch 2: default=3
	   44: 72
	   62: 165
  72 new #815 <Class Rk>
  75 dup
  76 aload 4
  78 aload_3
  79 invokespecial #1331 <Method Rk(java.lang.String,Rk)>
  82 astore_3
  83 ldc #129 <String "">
  85 astore 4
  87 goto 23
  90 new #833 <Class Ee>
  93 dup
  94 aload_0
  95 new #815 <Class Rk>
  98 dup
  99 ldc #17 <String "ml-lex: syntax error, line ">
 101 new #815 <Class Rk>
 104 dup
 105 aload_1
 106 getfield #1150 <Field int a>
 109 bipush 10
 111 invokestatic #1341 <Method java.lang.String toString(int, int)>
 114 bipush 45
 116 bipush 126
 118 invokevirtual #1245 <Method java.lang.String replace(char, char)>
 121 new #815 <Class Rk>
 124 dup
 125 ldc #9 <String ": ">
 127 new #815 <Class Rk>
 130 dup
 131 ldc #132 <String "bad start state list">
 133 new #815 <Class Rk>
 136 dup
 137 ldc #11 <String "
">
 139 aconst_null
 140 invokespecial #1331 <Method Rk(java.lang.String,Rk)>
 143 invokespecial #1331 <Method Rk(java.lang.String,Rk)>
 146 invokespecial #1331 <Method Rk(java.lang.String,Rk)>
 149 invokespecial #1331 <Method Rk(java.lang.String,Rk)>
 152 invokespecial #1331 <Method Rk(java.lang.String,Rk)>
 155 invokestatic #1286 <Method java.lang.String g(Rk)>
 158 invokestatic #1208 <Method void i(java.io.BufferedOutputStream, java.lang.String)>
 161 invokespecial #1371 <Method Ee()>
 164 athrow
 165 new #815 <Class Rk>
 168 dup
 169 aload 4
 171 aload_3
 172 invokespecial #1331 <Method Rk(java.lang.String,Rk)>
 175 areturn

Method int P(java.io.BufferedOutputStream, Ro, Ro, Rx, int, int[], Rz)[]
   0 goto 29
   3 aload 6
   5 ifnull 173
   8 new #786 <Class Rz>
  11 dup
  12 iload 7
  14 aload 5
  16 aload 6
  18 getfield #1085 <Field char a>
  21 iload 4
  23 iastore
  24 invokespecial #1374 <Method Rz(char)>
  27 astore 6
  29 aload_2
  30 aload_3
  31 invokestatic #1282 <Method char J(Ro, Rx)>
  34 dup
  35 istore 7
  37 bipush 92
  39 if_icmpne 271
  42 iconst_1
  43 istore 8
  45 iload 8
  47 ifeq 59
  50 aload_0
  51 aload_1
  52 aload_2
  53 aload_3
  54 invokestatic #1358 <Method char I(java.io.BufferedOutputStream, Ro, Ro, Rx)>
  57 istore 7
  59 iload 7
  61 lookupswitch 2: default=3
	   45: 88
	   93: 187
  88 aload 6
  90 ifnull 257
  93 aload_2
  94 aload_3
  95 invokestatic #1282 <Method char J(Ro, Rx)>
  98 dup
  99 istore 11
 101 bipush 92
 103 aload 6
 105 getfield #1085 <Field char a>
 108 istore 10
 110 if_icmpne 277
 113 iconst_1
 114 istore 9
 116 iload 9
 118 ifeq 130
 121 aload_0
 122 aload_1
 123 aload_2
 124 aload_3
 125 invokestatic #1358 <Method char I(java.io.BufferedOutputStream, Ro, Ro, Rx)>
 128 istore 11
 130 iload 11
 132 bipush 93
 134 if_icmpne 283
 137 iconst_1
 138 istore 12
 140 iload 12
 142 ifne 208
 145 iload 10
 147 iload 11
 149 if_icmple 289
 152 iconst_1
 153 istore 13
 155 iload 13
 157 ifeq 233
 160 aload_0
 161 aload_2
 162 ldc #135 <String "bad char. range">
 164 invokestatic #1299 <Method void z(java.io.BufferedOutputStream, Ro, java.lang.String)>
 167 aconst_null
 168 astore 6
 170 goto 29
 173 new #786 <Class Rz>
 176 dup
 177 iload 7
 179 invokespecial #1374 <Method Rz(char)>
 182 astore 6
 184 goto 29
 187 aload 6
 189 ifnonnull 195
 192 aload 5
 194 areturn
 195 aload 5
 197 aload 5
 199 aload 6
 201 getfield #1085 <Field char a>
 204 iload 4
 206 iastore
 207 areturn
 208 aload 6
 210 ifnull 223
 213 aload 5
 215 aload 6
 217 getfield #1085 <Field char a>
 220 iload 4
 222 iastore
 223 aload 5
 225 aload 5
 227 bipush 45
 229 iload 4
 231 iastore
 232 areturn
 233 iload 4
 235 aload 5
 237 new #830 <Class Ro>
 240 dup
 241 iload 10
 243 invokespecial #1344 <Method Ro(int)>
 246 iload 11
 248 invokestatic #1321 <Method void Q(int, int[], Ro, int)>
 251 aconst_null
 252 astore 6
 254 goto 29
 257 new #786 <Class Rz>
 260 dup
 261 bipush 45
 263 invokespecial #1374 <Method Rz(char)>
 266 astore 6
 268 goto 29
 271 iconst_0
 272 istore 8
 274 goto 45
 277 iconst_0
 278 istore 9
 280 goto 116
 283 iconst_0
 284 istore 12
 286 goto 140
 289 iconst_0
 290 istore 13
 292 goto 155

Method void Q(int, int[], Ro, int)
   0 goto 32
   3 return
   4 iconst_0
   5 istore 4
   7 iload 4
   9 ifeq 3
  12 aload_2
  13 aload_2
  14 aload_1
  15 aload_2
  16 getfield #1150 <Field int a>
  19 invokestatic #1250 <Method char f(int)>
  22 iload_0
  23 iastore
  24 getfield #1150 <Field int a>
  27 iconst_1
  28 iadd
  29 putfield #1150 <Field int a>
  32 aload_2
  33 getfield #1150 <Field int a>
  36 iload_3
  37 if_icmpgt 4
  40 iconst_1
  41 istore 4
  43 goto 7

Method java.lang.String R(java.io.BufferedOutputStream, Ro, Rx, java.lang.String)
   0 goto 13
   3 aload_3
   4 iload 5
   6 invokestatic #1342 <Method java.lang.String valueOf(char)>
   9 invokevirtual #1235 <Method java.lang.String concat(java.lang.String)>
  12 astore_3
  13 bipush 125
  15 aload_1
  16 aload_2
  17 getfield #1164 <Field Rw a>
  20 dup
  21 astore 4
  23 getfield #1135 <Field java.io.BufferedInputStream a>
  26 aload 4
  28 getfield #1101 <Field Rr b>
  31 invokestatic #1219 <Method char w(Ro, java.io.BufferedInputStream, Rr)>
  34 dup
  35 istore 5
  37 if_icmpeq 123
  40 iload 5
  42 invokestatic #1228 <Method int F(char)>
  45 ifne 3
  48 new #833 <Class Ee>
  51 dup
  52 aload_0
  53 new #815 <Class Rk>
  56 dup
  57 ldc #182 <String "ml-lex: error, line ">
  59 new #815 <Class Rk>
  62 dup
  63 aload_1
  64 getfield #1150 <Field int a>
  67 bipush 10
  69 invokestatic #1341 <Method java.lang.String toString(int, int)>
  72 bipush 45
  74 bipush 126
  76 invokevirtual #1245 <Method java.lang.String replace(char, char)>
  79 new #815 <Class Rk>
  82 dup
  83 ldc #9 <String ": ">
  85 new #815 <Class Rk>
  88 dup
  89 ldc #139 <String "invalid char. class name">
  91 new #815 <Class Rk>
  94 dup
  95 ldc #11 <String "
">
  97 aconst_null
  98 invokespecial #1331 <Method Rk(java.lang.String,Rk)>
 101 invokespecial #1331 <Method Rk(java.lang.String,Rk)>
 104 invokespecial #1331 <Method Rk(java.lang.String,Rk)>
 107 invokespecial #1331 <Method Rk(java.lang.String,Rk)>
 110 invokespecial #1331 <Method Rk(java.lang.String,Rk)>
 113 invokestatic #1286 <Method java.lang.String g(Rk)>
 116 invokestatic #1208 <Method void i(java.io.BufferedOutputStream, java.lang.String)>
 119 invokespecial #1371 <Method Ee()>
 122 athrow
 123 aload_3
 124 areturn

Method Ra S(java.io.BufferedOutputStream, Ro, Rx, java.lang.String, int)
   0 goto 21
   3 iload 6
   5 invokestatic #1200 <Method int E(char)>
   8 ifeq 130
  11 aload_3
  12 iload 6
  14 invokestatic #1342 <Method java.lang.String valueOf(char)>
  17 invokevirtual #1235 <Method java.lang.String concat(java.lang.String)>
  20 astore_3
  21 aload_1
  22 aload_2
  23 getfield #1164 <Field Rw a>
  26 dup
  27 astore 5
  29 getfield #1135 <Field java.io.BufferedInputStream a>
  32 aload 5
  34 getfield #1101 <Field Rr b>
  37 invokestatic #1219 <Method char w(Ro, java.io.BufferedInputStream, Rr)>
  40 dup
  41 istore 6
  43 lookupswitch 2: default=3
	   44: 68
	  125: 94
  68 iload 4
  70 iconst_m1
  71 if_icmpne 209
  74 iconst_1
  75 istore 9
  77 iload 9
  79 ifeq 215
  82 aload_3
  83 invokestatic #1355 <Method int G(java.lang.String)>
  86 istore 4
  88 ldc #129 <String "">
  90 astore_3
  91 goto 21
  94 iload 4
  96 iconst_m1
  97 aload_3
  98 invokestatic #1355 <Method int G(java.lang.String)>
 101 istore 8
 103 if_icmpne 118
 106 new #791 <Class Ra>
 109 dup
 110 iload 8
 112 iload 8
 114 invokespecial #1201 <Method Ra(int,int)>
 117 areturn
 118 new #791 <Class Ra>
 121 dup
 122 iload 4
 124 iload 8
 126 invokespecial #1201 <Method Ra(int,int)>
 129 areturn
 130 ldc #140 <String "invalid char in repetitions spec">
 132 astore 7
 134 new #833 <Class Ee>
 137 dup
 138 aload_0
 139 new #815 <Class Rk>
 142 dup
 143 ldc #182 <String "ml-lex: error, line ">
 145 new #815 <Class Rk>
 148 dup
 149 aload_1
 150 getfield #1150 <Field int a>
 153 bipush 10
 155 invokestatic #1341 <Method java.lang.String toString(int, int)>
 158 bipush 45
 160 bipush 126
 162 invokevirtual #1245 <Method java.lang.String replace(char, char)>
 165 new #815 <Class Rk>
 168 dup
 169 ldc #9 <String ": ">
 171 new #815 <Class Rk>
 174 dup
 175 aload 7
 177 new #815 <Class Rk>
 180 dup
 181 ldc #11 <String "
">
 183 aconst_null
 184 invokespecial #1331 <Method Rk(java.lang.String,Rk)>
 187 invokespecial #1331 <Method Rk(java.lang.String,Rk)>
 190 invokespecial #1331 <Method Rk(java.lang.String,Rk)>
 193 invokespecial #1331 <Method Rk(java.lang.String,Rk)>
 196 invokespecial #1331 <Method Rk(java.lang.String,Rk)>
 199 invokestatic #1286 <Method java.lang.String g(Rk)>
 202 invokestatic #1208 <Method void i(java.io.BufferedOutputStream, java.lang.String)>
 205 invokespecial #1371 <Method Ee()>
 208 athrow
 209 iconst_0
 210 istore 9
 212 goto 77
 215 ldc #142 <String "invalid repetitions spec.">
 217 astore 7
 219 goto 134

Method java.lang.String T(Ro, Rx, int, Ri)
   0 goto 30
   3 iload_2
   4 ifne 117
   7 iconst_1
   8 istore 6
  10 iload 6
  12 ifne 94
  15 new #801 <Class Ri>
  18 dup
  19 bipush 41
  21 aload_3
  22 invokespecial #1238 <Method Ri(char,Ri)>
  25 astore_3
  26 iload_2
  27 iconst_m1
  28 iadd
  29 istore_2
  30 aload_0
  31 aload_1
  32 getfield #1164 <Field Rw a>
  35 dup
  36 astore 4
  38 getfield #1135 <Field java.io.BufferedInputStream a>
  41 aload 4
  43 getfield #1101 <Field Rr b>
  46 invokestatic #1219 <Method char w(Ro, java.io.BufferedInputStream, Rr)>
  49 dup
  50 istore 5
  52 tableswitch 40 to 41: default=103
	   40: 76
	   41: 3
  76 new #801 <Class Ri>
  79 dup
  80 bipush 40
  82 aload_3
  83 invokespecial #1238 <Method Ri(char,Ri)>
  86 astore_3
  87 iload_2
  88 iconst_1
  89 iadd
  90 istore_2
  91 goto 30
  94 aload_3
  95 aconst_null
  96 invokestatic #1274 <Method Ri c(Ri, Ri)>
  99 invokestatic #1199 <Method java.lang.String h(Ri)>
 102 areturn
 103 new #801 <Class Ri>
 106 dup
 107 iload 5
 109 aload_3
 110 invokespecial #1238 <Method Ri(char,Ri)>
 113 astore_3
 114 goto 30
 117 iconst_0
 118 istore 6
 120 goto 10

Method S U(java.io.BufferedOutputStream, Ro, Ro, Ro, Rx, Ro, Ry, Ro, R3)
   0 aload_0
   1 aload_1
   2 aload_2
   3 aload_3
   4 aload 4
   6 aload 5
   8 aload 6
  10 aload 7
  12 aload 8
  14 invokestatic #1369 <Method S ab(java.io.BufferedOutputStream, Ro, Ro, Ro, Rx, Ro, Ry, Ro, R3)>
  17 areturn

Method S V(java.io.BufferedOutputStream, Ro, R3, java.lang.String)
   0 aload_2
   1 getfield #1159 <Field R2 a>
   4 dup
   5 astore 4
   7 getfield #1102 <Field F a>
  10 astore 5
  12 aload 4
  14 getfield #1192 <Field R1 b>
  17 astore 6
  19 aload_3
  20 aload 5
  22 aload 6
  24 invokestatic #1217 <Method S W(java.lang.String, F, R1)>
  27 astore 7
  29 aload 7
  31 areturn
  32 pop
  33 aload_0
  34 aload_1
  35 ldc #153 <String "bad regular expression name: ">
  37 aload_3
  38 invokevirtual #1235 <Method java.lang.String concat(java.lang.String)>
  41 invokestatic #1248 <Method S y(java.io.BufferedOutputStream, Ro, java.lang.String)>
  44 areturn
Exception table:
   from   to  target type
    19    29    32   <Class Ec>

Method S W(java.lang.String, F, R1)
   0 goto 35
   3 aload_1
   4 new #771 <Class Rg>
   7 dup
   8 aload_0
   9 aload_2
  10 getfield #1172 <Field R0 a>
  13 dup
  14 astore 4
  16 getfield #1146 <Field java.lang.String a>
  19 dup
  20 astore_3
  21 invokespecial #1294 <Method Rg(java.lang.String,java.lang.String)>
  24 invokevirtual #1266 <Method int d(Rg)>
  27 ifne 47
  30 aload_2
  31 getfield #1144 <Field R1 b>
  34 astore_2
  35 aload_2
  36 ifnonnull 3
  39 new #790 <Class Ec>
  42 dup
  43 invokespecial #1297 <Method Ec()>
  46 athrow
  47 aload_1
  48 new #771 <Class Rg>
  51 dup
  52 aload_3
  53 aload_0
  54 invokespecial #1294 <Method Rg(java.lang.String,java.lang.String)>
  57 invokevirtual #1266 <Method int d(Rg)>
  60 ifne 71
  63 new #790 <Class Ec>
  66 dup
  67 invokespecial #1297 <Method Ec()>
  70 athrow
  71 aload 4
  73 getfield #1132 <Field S b>
  76 areturn

Method S X(Ro, S)
   0 new #811 <Class Sa>
   3 dup
   4 new #811 <Class Sa>
   7 dup
   8 aload_1
   9 new #816 <Class Sb>
  12 dup
  13 iconst_0
  14 bipush 6
  16 new #825 <Class Sc>
  19 dup
  20 aload_0
  21 getfield #1150 <Field int a>
  24 iconst_0
  25 invokestatic #1195 <Method int j(int, int)[]>
  28 dup
  29 astore_2
  30 iconst_0
  31 iconst_2
  32 aload_2
  33 bipush 10
  35 iconst_1
  36 iastore
  37 invokespecial #1351 <Method Sc(int[],int,int)>
  40 astore_3
  41 invokespecial #1329 <Method Sb(int,int)>
  44 iconst_1
  45 invokespecial #1360 <Method Sa(S,S,int)>
  48 aload_3
  49 iconst_1
  50 invokespecial #1360 <Method Sa(S,S,int)>
  53 areturn

Method S Y(int, int, S)
   0 aload_2
   1 iload_0
   2 iload_1
   3 invokestatic #1249 <Method S Z(S, int, int)>
   6 areturn

Method S Z(S, int, int)
   0 iload_1
   1 ifne 50
   4 iload_2
   5 tableswitch 0 to 1: default=226
	    0: 190
	    1: 28
  28 iload_1
  29 ifne 167
  32 new #811 <Class Sa>
  35 dup
  36 aload_0
  37 new #770 <Class S>
  40 dup
  41 iconst_5
  42 invokespecial #1362 <Method S(int)>
  45 iconst_0
  46 invokespecial #1360 <Method Sa(S,S,int)>
  49 areturn
  50 iload_2
  51 tableswitch 0 to 1: default=147
	    0: 114
	    1: 72
  72 iload_1
  73 ifne 94
  76 new #811 <Class Sa>
  79 dup
  80 aload_0
  81 new #770 <Class S>
  84 dup
  85 iconst_5
  86 invokespecial #1362 <Method S(int)>
  89 iconst_0
  90 invokespecial #1360 <Method Sa(S,S,int)>
  93 areturn
  94 new #811 <Class Sa>
  97 dup
  98 aload_0
  99 aload_0
 100 iload_1
 101 iconst_m1
 102 iadd
 103 iload_2
 104 iconst_m1
 105 iadd
 106 invokestatic #1249 <Method S Z(S, int, int)>
 109 iconst_1
 110 invokespecial #1360 <Method Sa(S,S,int)>
 113 areturn
 114 iload_1
 115 ifne 127
 118 new #770 <Class S>
 121 dup
 122 iconst_5
 123 invokespecial #1362 <Method S(int)>
 126 areturn
 127 new #811 <Class Sa>
 130 dup
 131 aload_0
 132 aload_0
 133 iload_1
 134 iconst_m1
 135 iadd
 136 iload_2
 137 iconst_m1
 138 iadd
 139 invokestatic #1249 <Method S Z(S, int, int)>
 142 iconst_1
 143 invokespecial #1360 <Method Sa(S,S,int)>
 146 areturn
 147 new #811 <Class Sa>
 150 dup
 151 aload_0
 152 aload_0
 153 iload_1
 154 iconst_m1
 155 iadd
 156 iload_2
 157 iconst_m1
 158 iadd
 159 invokestatic #1249 <Method S Z(S, int, int)>
 162 iconst_1
 163 invokespecial #1360 <Method Sa(S,S,int)>
 166 areturn
 167 new #811 <Class Sa>
 170 dup
 171 aload_0
 172 iconst_0
 173 iconst_1
 174 invokestatic #1249 <Method S Z(S, int, int)>
 177 aload_0
 178 iconst_0
 179 iload_2
 180 iconst_m1
 181 iadd
 182 invokestatic #1249 <Method S Z(S, int, int)>
 185 iconst_1
 186 invokespecial #1360 <Method Sa(S,S,int)>
 189 areturn
 190 iload_1
 191 ifne 203
 194 new #770 <Class S>
 197 dup
 198 iconst_5
 199 invokespecial #1362 <Method S(int)>
 202 areturn
 203 new #811 <Class Sa>
 206 dup
 207 aload_0
 208 iconst_0
 209 iconst_1
 210 invokestatic #1249 <Method S Z(S, int, int)>
 213 aload_0
 214 iconst_0
 215 iload_2
 216 iconst_m1
 217 iadd
 218 invokestatic #1249 <Method S Z(S, int, int)>
 221 iconst_1
 222 invokespecial #1360 <Method Sa(S,S,int)>
 225 areturn
 226 new #811 <Class Sa>
 229 dup
 230 aload_0
 231 iconst_0
 232 iconst_1
 233 invokestatic #1249 <Method S Z(S, int, int)>
 236 aload_0
 237 iconst_0
 238 iload_2
 239 iconst_m1
 240 iadd
 241 invokestatic #1249 <Method S Z(S, int, int)>
 244 iconst_1
 245 invokespecial #1360 <Method Sa(S,S,int)>
 248 areturn

Method S aa(java.io.BufferedOutputStream, Ro, Ro, Ro, Rx, Ro, Ry, Ro, R3, S)
   0 goto 15
   3 new #820 <Class Sd>
   6 dup
   7 aload 9
   9 iconst_3
  10 invokespecial #1301 <Method Sd(S,int)>
  13 astore 9
  15 aload 6
  17 getfield #1115 <Field S a>
  20 dup
  21 astore 10
  23 getfield #1147 <Field int $>
  26 lookupswitch 5: default=76
	    2: 487
	   10: 484
	   16: 447
	   21: 444
	   22: 441
  76 aload 10
  78 aload_0
  79 aload_2
  80 aload_3
  81 aload 4
  83 aload 5
  85 aload 6
  87 aload 7
  89 invokestatic #1347 <Method void C(java.io.BufferedOutputStream, Ro, Ro, Rx, Ro, Ry, Ro)>
  92 getfield #1147 <Field int $>
  95 tableswitch 4 to 24: default=273
	    4: 413
	    5: 273
	    6: 273
	    7: 376
	    8: 273
	    9: 364
	   10: 273
	   11: 273
	   12: 273
	   13: 329
	   14: 273
	   15: 273
	   16: 273
	   17: 304
	   18: 281
	   19: 273
	   20: 192
	   21: 273
	   22: 273
	   23: 218
	   24: 3
 192 aload 10
 194 checkcast #773 <Class Sh>
 197 dup
 198 astore 12
 200 getfield #1165 <Field int a>
 203 aload 12
 205 getfield #1154 <Field int b>
 208 aload 9
 210 invokestatic #1375 <Method S Y(int, int, S)>
 213 astore 9
 215 goto 15
 218 new #811 <Class Sa>
 221 dup
 222 new #811 <Class Sa>
 225 dup
 226 aload 9
 228 new #816 <Class Sb>
 231 dup
 232 iconst_0
 233 bipush 6
 235 aload_0
 236 aload_1
 237 aload_2
 238 aload_3
 239 aload 4
 241 aload 5
 243 aload 6
 245 aload 7
 247 aload 8
 249 aload_1
 250 iconst_1
 251 putfield #1150 <Field int a>
 254 invokestatic #1369 <Method S ab(java.io.BufferedOutputStream, Ro, Ro, Ro, Rx, Ro, Ry, Ro, R3)>
 257 astore 11
 259 invokespecial #1329 <Method Sb(int,int)>
 262 iconst_1
 263 invokespecial #1360 <Method Sa(S,S,int)>
 266 aload 11
 268 iconst_1
 269 invokespecial #1360 <Method Sa(S,S,int)>
 272 areturn
 273 new #829 <Class Eg>
 276 dup
 277 invokespecial #1365 <Method Eg()>
 280 athrow
 281 new #811 <Class Sa>
 284 dup
 285 new #770 <Class S>
 288 dup
 289 iconst_5
 290 invokespecial #1362 <Method S(int)>
 293 aload 9
 295 iconst_0
 296 invokespecial #1360 <Method Sa(S,S,int)>
 299 astore 9
 301 goto 15
 304 new #811 <Class Sa>
 307 dup
 308 aload 9
 310 new #820 <Class Sd>
 313 dup
 314 aload 9
 316 iconst_3
 317 invokespecial #1301 <Method Sd(S,int)>
 320 iconst_1
 321 invokespecial #1360 <Method Sa(S,S,int)>
 324 astore 9
 326 goto 15
 329 aload_0
 330 aload_1
 331 aload_2
 332 aload_3
 333 aload 4
 335 aload 5
 337 aload 6
 339 aload 7
 341 aload 8
 343 aload 9
 345 aload_0
 346 aload_3
 347 aload 8
 349 aload 10
 351 checkcast #798 <Class Sf>
 354 getfield #1104 <Field java.lang.String a>
 357 invokestatic #1316 <Method S V(java.io.BufferedOutputStream, Ro, R3, java.lang.String)>
 360 invokestatic #1345 <Method S ac(java.io.BufferedOutputStream, Ro, Ro, Ro, Rx, Ro, Ry, Ro, R3, S, S)>
 363 areturn
 364 aload_2
 365 aload 9
 367 aload_1
 368 iconst_1
 369 putfield #1150 <Field int a>
 372 invokestatic #1263 <Method S X(Ro, S)>
 375 areturn
 376 aload_0
 377 aload_1
 378 aload_2
 379 aload_3
 380 aload 4
 382 aload 5
 384 aload 6
 386 aload 7
 388 aload 8
 390 aload 9
 392 new #825 <Class Sc>
 395 dup
 396 aload 10
 398 checkcast #837 <Class Se>
 401 getfield #1131 <Field int a[]>
 404 iconst_0
 405 iconst_2
 406 invokespecial #1351 <Method Sc(int[],int,int)>
 409 invokestatic #1345 <Method S ac(java.io.BufferedOutputStream, Ro, Ro, Ro, Rx, Ro, Ry, Ro, R3, S, S)>
 412 areturn
 413 new #811 <Class Sa>
 416 dup
 417 aload 9
 419 aload_0
 420 aload_1
 421 aload_2
 422 aload_3
 423 aload 4
 425 aload 5
 427 aload 6
 429 aload 7
 431 aload 8
 433 invokestatic #1369 <Method S ab(java.io.BufferedOutputStream, Ro, Ro, Ro, Rx, Ro, Ry, Ro, R3)>
 436 iconst_0
 437 invokespecial #1360 <Method Sa(S,S,int)>
 440 areturn
 441 aload 9
 443 areturn
 444 aload 9
 446 areturn
 447 aload_0
 448 aload_1
 449 aload_2
 450 aload_3
 451 aload 4
 453 aload 5
 455 aload 6
 457 aload 7
 459 aload 8
 461 aload 9
 463 aload_0
 464 aload_1
 465 aload_2
 466 aload_3
 467 aload 4
 469 aload 5
 471 aload 6
 473 aload 7
 475 aload 8
 477 invokestatic #1369 <Method S ab(java.io.BufferedOutputStream, Ro, Ro, Ro, Rx, Ro, Ry, Ro, R3)>
 480 invokestatic #1345 <Method S ac(java.io.BufferedOutputStream, Ro, Ro, Ro, Rx, Ro, Ry, Ro, R3, S, S)>
 483 areturn
 484 aload 9
 486 areturn
 487 aload 9
 489 areturn

Method S ab(java.io.BufferedOutputStream, Ro, Ro, Ro, Rx, Ro, Ry, Ro, R3)
   0 aload 6
   2 getfield #1115 <Field S a>
   5 dup
   6 astore 9
   8 aload_0
   9 aload_2
  10 aload_3
  11 aload 4
  13 aload 5
  15 aload 6
  17 aload 7
  19 invokestatic #1347 <Method void C(java.io.BufferedOutputStream, Ro, Ro, Rx, Ro, Ry, Ro)>
  22 getfield #1147 <Field int $>
  25 tableswitch 7 to 16: default=80
	    7: 203
	    8: 80
	    9: 80
	   10: 80
	   11: 80
	   12: 80
	   13: 170
	   14: 80
	   15: 80
	   16: 88
  80 new #829 <Class Eg>
  83 dup
  84 invokespecial #1365 <Method Eg()>
  87 athrow
  88 bipush 21
  90 aload 6
  92 aload_0
  93 aload_1
  94 aload_2
  95 aload_3
  96 aload 4
  98 aload 5
 100 aload 6
 102 aload 7
 104 aload 8
 106 invokestatic #1369 <Method S ab(java.io.BufferedOutputStream, Ro, Ro, Ro, Rx, Ro, Ry, Ro, R3)>
 109 astore 10
 111 getfield #1115 <Field S a>
 114 getfield #1147 <Field int $>
 117 if_icmpne 238
 120 iconst_1
 121 istore 11
 123 iload 11
 125 ifne 136
 128 aload_0
 129 aload_3
 130 ldc #4 <String "missing '('">
 132 invokestatic #1312 <Method S A(java.io.BufferedOutputStream, Ro, java.lang.String)>
 135 areturn
 136 aload_0
 137 aload_1
 138 aload_2
 139 aload_3
 140 aload 4
 142 aload 5
 144 aload 6
 146 aload 7
 148 aload 8
 150 aload 10
 152 aload_0
 153 aload_2
 154 aload_3
 155 aload 4
 157 aload 5
 159 aload 6
 161 aload 7
 163 invokestatic #1347 <Method void C(java.io.BufferedOutputStream, Ro, Ro, Rx, Ro, Ry, Ro)>
 166 invokestatic #1357 <Method S aa(java.io.BufferedOutputStream, Ro, Ro, Ro, Rx, Ro, Ry, Ro, R3, S)>
 169 areturn
 170 aload_0
 171 aload_1
 172 aload_2
 173 aload_3
 174 aload 4
 176 aload 5
 178 aload 6
 180 aload 7
 182 aload 8
 184 aload_0
 185 aload_3
 186 aload 8
 188 aload 9
 190 checkcast #798 <Class Sf>
 193 getfield #1104 <Field java.lang.String a>
 196 invokestatic #1316 <Method S V(java.io.BufferedOutputStream, Ro, R3, java.lang.String)>
 199 invokestatic #1357 <Method S aa(java.io.BufferedOutputStream, Ro, Ro, Ro, Rx, Ro, Ry, Ro, R3, S)>
 202 areturn
 203 aload_0
 204 aload_1
 205 aload_2
 206 aload_3
 207 aload 4
 209 aload 5
 211 aload 6
 213 aload 7
 215 aload 8
 217 new #825 <Class Sc>
 220 dup
 221 aload 9
 223 checkcast #837 <Class Se>
 226 getfield #1131 <Field int a[]>
 229 iconst_0
 230 iconst_2
 231 invokespecial #1351 <Method Sc(int[],int,int)>
 234 invokestatic #1357 <Method S aa(java.io.BufferedOutputStream, Ro, Ro, Ro, Rx, Ro, Ry, Ro, R3, S)>
 237 areturn
 238 iconst_0
 239 istore 11
 241 goto 123

Method S ac(java.io.BufferedOutputStream, Ro, Ro, Ro, Rx, Ro, Ry, Ro, R3, S, S)
   0 goto 288
   3 aload_0
   4 aload_1
   5 aload_2
   6 aload_3
   7 aload 4
   9 aload 5
  11 aload 6
  13 aload 7
  15 aload 8
  17 new #811 <Class Sa>
  20 dup
  21 aload 9
  23 new #820 <Class Sd>
  26 dup
  27 aload 10
  29 iconst_3
  30 invokespecial #1301 <Method Sd(S,int)>
  33 iconst_1
  34 invokespecial #1360 <Method Sa(S,S,int)>
  37 invokestatic #1357 <Method S aa(java.io.BufferedOutputStream, Ro, Ro, Ro, Rx, Ro, Ry, Ro, R3, S)>
  40 areturn
  41 new #811 <Class Sa>
  44 dup
  45 new #811 <Class Sa>
  48 dup
  49 new #811 <Class Sa>
  52 dup
  53 aload 9
  55 aload 10
  57 iconst_1
  58 aload_1
  59 iconst_1
  60 putfield #1150 <Field int a>
  63 invokespecial #1360 <Method Sa(S,S,int)>
  66 new #816 <Class Sb>
  69 dup
  70 iconst_0
  71 bipush 6
  73 aload_0
  74 aload_1
  75 aload_2
  76 aload_3
  77 aload 4
  79 aload 5
  81 aload 6
  83 aload 7
  85 aload 8
  87 invokestatic #1369 <Method S ab(java.io.BufferedOutputStream, Ro, Ro, Ro, Rx, Ro, Ry, Ro, R3)>
  90 astore 12
  92 invokespecial #1329 <Method Sb(int,int)>
  95 iconst_1
  96 invokespecial #1360 <Method Sa(S,S,int)>
  99 aload 12
 101 iconst_1
 102 invokespecial #1360 <Method Sa(S,S,int)>
 105 areturn
 106 new #829 <Class Eg>
 109 dup
 110 invokespecial #1365 <Method Eg()>
 113 athrow
 114 aload_0
 115 aload_1
 116 aload_2
 117 aload_3
 118 aload 4
 120 aload 5
 122 aload 6
 124 aload 7
 126 aload 8
 128 new #811 <Class Sa>
 131 dup
 132 aload 9
 134 aload 11
 136 checkcast #773 <Class Sh>
 139 dup
 140 astore 13
 142 getfield #1165 <Field int a>
 145 aload 13
 147 getfield #1154 <Field int b>
 150 aload 10
 152 invokestatic #1375 <Method S Y(int, int, S)>
 155 iconst_1
 156 invokespecial #1360 <Method Sa(S,S,int)>
 159 invokestatic #1357 <Method S aa(java.io.BufferedOutputStream, Ro, Ro, Ro, Rx, Ro, Ry, Ro, R3, S)>
 162 areturn
 163 aload_0
 164 aload_1
 165 aload_2
 166 aload_3
 167 aload 4
 169 aload 5
 171 aload 6
 173 aload 7
 175 aload 8
 177 new #811 <Class Sa>
 180 dup
 181 aload 9
 183 new #811 <Class Sa>
 186 dup
 187 new #770 <Class S>
 190 dup
 191 iconst_5
 192 invokespecial #1362 <Method S(int)>
 195 aload 10
 197 iconst_0
 198 invokespecial #1360 <Method Sa(S,S,int)>
 201 iconst_1
 202 invokespecial #1360 <Method Sa(S,S,int)>
 205 invokestatic #1357 <Method S aa(java.io.BufferedOutputStream, Ro, Ro, Ro, Rx, Ro, Ry, Ro, R3, S)>
 208 areturn
 209 aload_0
 210 aload_1
 211 aload_2
 212 aload_3
 213 aload 4
 215 aload 5
 217 aload 6
 219 aload 7
 221 aload 8
 223 new #811 <Class Sa>
 226 dup
 227 aload 9
 229 new #811 <Class Sa>
 232 dup
 233 aload 10
 235 new #820 <Class Sd>
 238 dup
 239 aload 10
 241 iconst_3
 242 invokespecial #1301 <Method Sd(S,int)>
 245 iconst_1
 246 invokespecial #1360 <Method Sa(S,S,int)>
 249 iconst_1
 250 invokespecial #1360 <Method Sa(S,S,int)>
 253 invokestatic #1357 <Method S aa(java.io.BufferedOutputStream, Ro, Ro, Ro, Rx, Ro, Ry, Ro, R3, S)>
 256 areturn
 257 aload_0
 258 aload_3
 259 aload 8
 261 aload 11
 263 checkcast #798 <Class Sf>
 266 getfield #1104 <Field java.lang.String a>
 269 new #811 <Class Sa>
 272 dup
 273 aload 9
 275 aload 10
 277 iconst_1
 278 invokespecial #1360 <Method Sa(S,S,int)>
 281 astore 9
 283 invokestatic #1316 <Method S V(java.io.BufferedOutputStream, Ro, R3, java.lang.String)>
 286 astore 10
 288 aload 6
 290 getfield #1115 <Field S a>
 293 dup
 294 astore 11
 296 getfield #1147 <Field int $>
 299 lookupswitch 5: default=348
	    2: 635
	   10: 622
	   16: 586
	   21: 573
	   22: 560
 348 aload 11
 350 aload_0
 351 aload_2
 352 aload_3
 353 aload 4
 355 aload 5
 357 aload 6
 359 aload 7
 361 invokestatic #1347 <Method void C(java.io.BufferedOutputStream, Ro, Ro, Rx, Ro, Ry, Ro)>
 364 getfield #1147 <Field int $>
 367 tableswitch 4 to 24: default=106
	    4: 522
	    5: 106
	    6: 106
	    7: 464
	    8: 106
	    9: 500
	   10: 106
	   11: 106
	   12: 106
	   13: 257
	   14: 106
	   15: 106
	   16: 106
	   17: 209
	   18: 163
	   19: 106
	   20: 114
	   21: 106
	   22: 106
	   23: 41
	   24: 3
 464 new #825 <Class Sc>
 467 dup
 468 aload 11
 470 checkcast #837 <Class Se>
 473 getfield #1131 <Field int a[]>
 476 iconst_0
 477 iconst_2
 478 new #811 <Class Sa>
 481 dup
 482 aload 9
 484 aload 10
 486 iconst_1
 487 invokespecial #1360 <Method Sa(S,S,int)>
 490 astore 9
 492 invokespecial #1351 <Method Sc(int[],int,int)>
 495 astore 10
 497 goto 288
 500 aload_2
 501 new #811 <Class Sa>
 504 dup
 505 aload 9
 507 aload 10
 509 iconst_1
 510 aload_1
 511 iconst_1
 512 putfield #1150 <Field int a>
 515 invokespecial #1360 <Method Sa(S,S,int)>
 518 invokestatic #1263 <Method S X(Ro, S)>
 521 areturn
 522 new #811 <Class Sa>
 525 dup
 526 new #811 <Class Sa>
 529 dup
 530 aload 9
 532 aload 10
 534 iconst_1
 535 invokespecial #1360 <Method Sa(S,S,int)>
 538 aload_0
 539 aload_1
 540 aload_2
 541 aload_3
 542 aload 4
 544 aload 5
 546 aload 6
 548 aload 7
 550 aload 8
 552 invokestatic #1369 <Method S ab(java.io.BufferedOutputStream, Ro, Ro, Ro, Rx, Ro, Ry, Ro, R3)>
 555 iconst_0
 556 invokespecial #1360 <Method Sa(S,S,int)>
 559 areturn
 560 new #811 <Class Sa>
 563 dup
 564 aload 9
 566 aload 10
 568 iconst_1
 569 invokespecial #1360 <Method Sa(S,S,int)>
 572 areturn
 573 new #811 <Class Sa>
 576 dup
 577 aload 9
 579 aload 10
 581 iconst_1
 582 invokespecial #1360 <Method Sa(S,S,int)>
 585 areturn
 586 aload_0
 587 aload_1
 588 aload_2
 589 aload_3
 590 aload 4
 592 aload 5
 594 aload 6
 596 aload 7
 598 aload 8
 600 new #811 <Class Sa>
 603 dup
 604 aload 9
 606 aload 10
 608 iconst_1
 609 invokespecial #1360 <Method Sa(S,S,int)>
 612 astore 9
 614 invokestatic #1369 <Method S ab(java.io.BufferedOutputStream, Ro, Ro, Ro, Rx, Ro, Ry, Ro, R3)>
 617 astore 10
 619 goto 288
 622 new #811 <Class Sa>
 625 dup
 626 aload 9
 628 aload 10
 630 iconst_1
 631 invokespecial #1360 <Method Sa(S,S,int)>
 634 areturn
 635 new #811 <Class Sa>
 638 dup
 639 aload 9
 641 aload 10
 643 iconst_1
 644 invokespecial #1360 <Method Sa(S,S,int)>
 647 areturn

Method void ad(F, F, java.io.BufferedOutputStream, java.io.BufferedOutputStream, Ro, Ro, Ro, Ro, Ro, Ro, Rp, Rp, Ro, Rp, Ro, Rq, Ro, Rx, Ro, Ry, Ro, R3, R4, Ro, Ro, java.lang.String)
   0 aload 14
   2 iconst_0
   3 aload 13
   5 aconst_null
   6 aload 12
   8 iconst_0
   9 aload 11
  11 ldc #129 <String "">
  13 aload 10
  15 ldc #136 <String "Mlex">
  17 aload 9
  19 sipush 129
  22 aload 5
  24 iconst_0
  25 aload 8
  27 iconst_0
  28 aload 7
  30 iconst_0
  31 aload 6
  33 iconst_0
  34 aload 25
  36 ldc #8 <String ".sml">
  38 invokevirtual #1235 <Method java.lang.String concat(java.lang.String)>
  41 astore 26
  43 putfield #1150 <Field int a>
  46 putfield #1150 <Field int a>
  49 putfield #1150 <Field int a>
  52 putfield #1150 <Field int a>
  55 putfield #1150 <Field int a>
  58 putfield #1094 <Field java.lang.String a>
  61 putfield #1094 <Field java.lang.String a>
  64 putfield #1150 <Field int a>
  67 putfield #1094 <Field java.lang.String a>
  70 putfield #1150 <Field int a>
  73 new #769 <Class java.io.FileInputStream>
  76 dup
  77 aload 25
  79 invokespecial #1224 <Method java.io.FileInputStream(java.lang.String)>
  82 astore 28
  84 new #780 <Class java.io.BufferedInputStream>
  87 dup
  88 aload 28
  90 invokespecial #1323 <Method java.io.BufferedInputStream(java.io.InputStream)>
  93 astore 29
  95 aload 20
  97 iconst_0
  98 aload 19
 100 new #770 <Class S>
 103 dup
 104 iconst_5
 105 aload 17
 107 new #777 <Class Rw>
 110 dup
 111 aload 29
 113 new #788 <Class Rr>
 116 dup
 117 new #789 <Class Rp>
 120 dup
 121 ldc #129 <String "">
 123 invokespecial #1327 <Method Rp(java.lang.String)>
 126 new #830 <Class Ro>
 129 dup
 130 iconst_0
 131 invokespecial #1344 <Method Ro(int)>
 134 invokespecial #1269 <Method Rr(Rp,Ro)>
 137 invokespecial #1326 <Method Rw(java.io.BufferedInputStream,Rr)>
 140 putfield #1164 <Field Rw a>
 143 invokespecial #1362 <Method S(int)>
 146 putfield #1115 <Field S a>
 149 putfield #1150 <Field int a>
 152 new #776 <Class java.io.FileOutputStream>
 155 dup
 156 aload 26
 158 invokespecial #1227 <Method java.io.FileOutputStream(java.lang.String)>
 161 astore 32
 163 new #796 <Class java.io.BufferedOutputStream>
 166 dup
 167 aload 32
 169 invokespecial #1221 <Method java.io.BufferedOutputStream(java.io.OutputStream)>
 172 astore 33
 174 new #779 <Class R5>
 177 dup
 178 new #784 <Class Ru>
 181 dup
 182 aload_1
 183 aconst_null
 184 aload 24
 186 iconst_m1
 187 aload 22
 189 aload_1
 190 aconst_null
 191 new #783 <Class Re>
 194 dup
 195 ldc #16 <String "INITIAL">
 197 iconst_1
 198 aload 16
 200 iconst_1
 201 aload 23
 203 iconst_2
 204 aload 15
 206 aload 33
 208 putfield #1109 <Field java.io.BufferedOutputStream a>
 211 putfield #1150 <Field int a>
 214 putfield #1150 <Field int a>
 217 invokespecial #1296 <Method Re(java.lang.String,int)>
 220 invokestatic #1260 <Method Rm o(F, Rf, Re)>
 223 putfield #1121 <Field Rm a>
 226 putfield #1150 <Field int a>
 229 invokespecial #1310 <Method Ru(F,Rh)>
 232 invokespecial #1381 <Method R5(Ru)>
 235 astore 35
 237 aload 16
 239 aload 17
 241 aconst_null
 242 invokestatic #1339 <Method java.lang.String ao(Ro, Rx, Ri)>
 245 astore 84
 247 aload_3
 248 aload 5
 250 aload 7
 252 aload 8
 254 aload 9
 256 aload 10
 258 aload 11
 260 aload 12
 262 aload 13
 264 aload 14
 266 aload 16
 268 aload 17
 270 aload 18
 272 aload 19
 274 aload 20
 276 aload 21
 278 aload 22
 280 aload 23
 282 invokestatic #1370 <Method void al(java.io.BufferedOutputStream, Ro, Ro, Ro, Ro, Rp, Rp, Ro, Rp, Ro, Ro, Rx, Ro, Ry, Ro, R3, R4, Ro)>
 285 aload_3
 286 aload 5
 288 aload 6
 290 aload 9
 292 aload 16
 294 aload 17
 296 aload 18
 298 aload 19
 300 aload 20
 302 aload 21
 304 aload 22
 306 aload 23
 308 aload 24
 310 aload 35
 312 aconst_null
 313 invokestatic #1204 <Method Rt ae(java.io.BufferedOutputStream, Ro, Ro, Ro, Ro, Rx, Ro, Ry, Ro, R3, R4, Ro, Ro, R5, Rt)>
 316 astore 42
 318 aload 35
 320 getfield #1184 <Field Ru a>
 323 astore 56
 325 goto 433
 328 astore 27
 330 new #835 <Class Eb>
 333 dup
 334 aload 27
 336 ldc #30 <String "openIn">
 338 ldc #176 <String "java.io.BufferedInputStream">
 340 invokespecial #1259 <Method Eb(java.lang.Exception,java.lang.String,java.lang.String)>
 343 athrow
 344 astore 30
 346 new #835 <Class Eb>
 349 dup
 350 aload 30
 352 ldc #30 <String "openIn">
 354 ldc #176 <String "java.io.BufferedInputStream">
 356 invokespecial #1259 <Method Eb(java.lang.Exception,java.lang.String,java.lang.String)>
 359 athrow
 360 astore 31
 362 new #835 <Class Eb>
 365 dup
 366 aload 31
 368 ldc #32 <String "openOut">
 370 ldc #98 <String "java.io.BufferedOutputStream">
 372 invokespecial #1259 <Method Eb(java.lang.Exception,java.lang.String,java.lang.String)>
 375 athrow
 376 astore 34
 378 new #835 <Class Eb>
 381 dup
 382 aload 34
 384 ldc #32 <String "openOut">
 386 ldc #98 <String "java.io.BufferedOutputStream">
 388 invokespecial #1259 <Method Eb(java.lang.Exception,java.lang.String,java.lang.String)>
 391 athrow
 392 astore 36
 394 aload 36
 396 instanceof #829 <Class Eg>
 399 ifeq 815
 402 aload_3
 403 aload 16
 405 ldc #129 <String "">
 407 invokestatic #1220 <Method Rv B(java.io.BufferedOutputStream, Ro, java.lang.String)>
 410 astore 41
 412 aload 41
 414 getfield #1122 <Field java.lang.String a>
 417 astore 84
 419 aload 41
 421 getfield #1089 <Field Rt b>
 424 astore 42
 426 aload 41
 428 getfield #1108 <Field Ru c>
 431 astore 56
 433 aload 5
 435 new #809 <Class R6>
 438 dup
 439 new #795 <Class Rl>
 442 dup
 443 aload_0
 444 aconst_null
 445 new #809 <Class R6>
 448 dup
 449 new #795 <Class Rl>
 452 dup
 453 aload_0
 454 aconst_null
 455 new #809 <Class R6>
 458 dup
 459 new #795 <Class Rl>
 462 dup
 463 aload_0
 464 aconst_null
 465 new #831 <Class R4>
 468 dup
 469 new #832 <Class Rm>
 472 dup
 473 aload_1
 474 aconst_null
 475 invokespecial #1206 <Method Rm(F,Rf)>
 478 invokespecial #1267 <Method R4(Rm)>
 481 astore 43
 483 invokespecial #1295 <Method Rl(F,Rd)>
 486 invokespecial #1209 <Method R6(Rl)>
 489 astore 44
 491 invokespecial #1295 <Method Rl(F,Rd)>
 494 invokespecial #1209 <Method R6(Rl)>
 497 astore 45
 499 invokespecial #1295 <Method Rl(F,Rd)>
 502 invokespecial #1209 <Method R6(Rl)>
 505 dup
 506 astore 46
 508 aload 45
 510 aload 44
 512 aload 9
 514 aload 23
 516 aload 43
 518 aload 44
 520 aload 45
 522 aload 46
 524 aload 24
 526 getfield #1150 <Field int a>
 529 iconst_1
 530 iadd
 531 aconst_null
 532 invokestatic #1368 <Method Rc k(int, Rc)[]>
 535 dup
 536 astore 47
 538 aload 24
 540 getfield #1150 <Field int a>
 543 iconst_1
 544 iadd
 545 dup
 546 istore 48
 548 new #770 <Class S>
 551 dup
 552 iconst_5
 553 invokespecial #1362 <Method S(int)>
 556 iload 48
 558 anewarray class #770 <Class S>
 561 iconst_0
 562 invokestatic #1202 <Method S ap(int, S, S[], int)[]>
 565 dup
 566 astore 49
 568 aload 23
 570 new #812 <Class R8>
 573 dup
 574 aconst_null
 575 invokespecial #1334 <Method R8(R7)>
 578 dup
 579 astore 50
 581 aload 47
 583 aload 49
 585 aload 50
 587 new #830 <Class Ro>
 590 dup
 591 iconst_m1
 592 invokespecial #1344 <Method Ro(int)>
 595 dup
 596 astore 51
 598 aload 42
 600 aload 51
 602 iconst_m1
 603 putfield #1150 <Field int a>
 606 invokestatic #1216 <Method void ar(Rc[], S[], R8, Ro, Rt)>
 609 getfield #1136 <Field R7 a>
 612 astore 57
 614 getfield #1150 <Field int a>
 617 iconst_1
 618 iadd
 619 aconst_null
 620 invokestatic #1368 <Method Rc k(int, Rc)[]>
 623 dup
 624 astore 52
 626 aload 23
 628 aload 52
 630 aload 42
 632 invokestatic #1306 <Method void aA(Rc[], Rt)>
 635 getfield #1150 <Field int a>
 638 iconst_1
 639 iadd
 640 iconst_m1
 641 iadd
 642 aconst_null
 643 invokestatic #1333 <Method R9 aB(Rc[], int, R9)>
 646 iconst_0
 647 invokestatic #1364 <Method void aC(Ro, Ro, R4, R6, R6, R6, Rc[], S[], R9, int)>
 650 getfield #1190 <Field Rl a>
 653 dup
 654 astore 53
 656 getfield #1130 <Field F a>
 659 aload 53
 661 getfield #1140 <Field Rd b>
 664 invokestatic #1265 <Method Rd q(F, Rd)>
 667 astore 58
 669 getfield #1190 <Field Rl a>
 672 dup
 673 astore 54
 675 getfield #1130 <Field F a>
 678 aload 54
 680 getfield #1140 <Field Rd b>
 683 invokestatic #1265 <Method Rd q(F, Rd)>
 686 astore 59
 688 getfield #1190 <Field Rl a>
 691 dup
 692 astore 55
 694 getfield #1130 <Field F a>
 697 aload 55
 699 getfield #1140 <Field Rd b>
 702 invokestatic #1265 <Method Rd q(F, Rd)>
 705 astore 60
 707 getfield #1150 <Field int a>
 710 ifeq 748
 713 aload 17
 715 getfield #1164 <Field Rw a>
 718 getfield #1135 <Field java.io.BufferedInputStream a>
 721 astore 61
 723 aload 61
 725 invokevirtual #1234 <Method void close()>
 728 aload 15
 730 getfield #1109 <Field java.io.BufferedOutputStream a>
 733 astore 63
 735 aload 63
 737 invokevirtual #1237 <Method void close()>
 740 aload_3
 741 aload 16
 743 ldc #74 <String "lookahead is unimplemented">
 745 invokestatic #1299 <Method void z(java.io.BufferedOutputStream, Ro, java.lang.String)>
 748 aload 12
 750 getfield #1150 <Field int a>
 753 ifne 877
 756 aload 15
 758 ldc #78 <String "structure ">
 760 aload 10
 762 getfield #1094 <Field java.lang.String a>
 765 invokevirtual #1235 <Method java.lang.String concat(java.lang.String)>
 768 astore 83
 770 getfield #1109 <Field java.io.BufferedOutputStream a>
 773 aload 83
 775 invokestatic #1208 <Method void i(java.io.BufferedOutputStream, java.lang.String)>
 778 goto 894
 781 astore 38
 783 new #835 <Class Eb>
 786 dup
 787 aload 38
 789 ldc #82 <String "closeIn">
 791 ldc #176 <String "java.io.BufferedInputStream">
 793 invokespecial #1259 <Method Eb(java.lang.Exception,java.lang.String,java.lang.String)>
 796 athrow
 797 astore 40
 799 new #835 <Class Eb>
 802 dup
 803 aload 40
 805 ldc #85 <String "closeOut">
 807 ldc #98 <String "java.io.BufferedOutputStream">
 809 invokespecial #1259 <Method Eb(java.lang.Exception,java.lang.String,java.lang.String)>
 812 athrow
 813 astore 36
 815 aload 17
 817 getfield #1164 <Field Rw a>
 820 getfield #1135 <Field java.io.BufferedInputStream a>
 823 astore 37
 825 aload 37
 827 invokevirtual #1234 <Method void close()>
 830 aload 15
 832 getfield #1109 <Field java.io.BufferedOutputStream a>
 835 astore 39
 837 aload 39
 839 invokevirtual #1237 <Method void close()>
 842 aload 36
 844 athrow
 845 astore 62
 847 new #835 <Class Eb>
 850 dup
 851 aload 62
 853 ldc #82 <String "closeIn">
 855 ldc #176 <String "java.io.BufferedInputStream">
 857 invokespecial #1259 <Method Eb(java.lang.Exception,java.lang.String,java.lang.String)>
 860 athrow
 861 astore 64
 863 new #835 <Class Eb>
 866 dup
 867 aload 64
 869 ldc #85 <String "closeOut">
 871 ldc #98 <String "java.io.BufferedOutputStream">
 873 invokespecial #1259 <Method Eb(java.lang.Exception,java.lang.String,java.lang.String)>
 876 athrow
 877 aload 15
 879 aload 11
 881 getfield #1094 <Field java.lang.String a>
 884 astore 65
 886 getfield #1109 <Field java.io.BufferedOutputStream a>
 889 aload 65
 891 invokestatic #1208 <Method void i(java.io.BufferedOutputStream, java.lang.String)>
 894 aload 59
 896 iconst_0
 897 new #830 <Class Ro>
 900 dup
 901 iconst_0
 902 aload 15
 904 aload 15
 906 aload 15
 908 aload 15
 910 aload 15
 912 aload 15
 914 aload 15
 916 getfield #1109 <Field java.io.BufferedOutputStream a>
 919 ldc #89 <String "=
">
 921 invokestatic #1208 <Method void i(java.io.BufferedOutputStream, java.lang.String)>
 924 getfield #1109 <Field java.io.BufferedOutputStream a>
 927 ldc #91 <String "   struct
    structure UserDeclarations =
      struct
">
 929 invokestatic #1208 <Method void i(java.io.BufferedOutputStream, java.lang.String)>
 932 getfield #1109 <Field java.io.BufferedOutputStream a>
 935 aload 84
 937 invokestatic #1208 <Method void i(java.io.BufferedOutputStream, java.lang.String)>
 940 getfield #1109 <Field java.io.BufferedOutputStream a>
 943 ldc #94 <String "end (* end of user routines *)
">
 945 invokestatic #1208 <Method void i(java.io.BufferedOutputStream, java.lang.String)>
 948 getfield #1109 <Field java.io.BufferedOutputStream a>
 951 ldc #97 <String "exception LexError (* raised if illegal leaf ">
 953 invokestatic #1208 <Method void i(java.io.BufferedOutputStream, java.lang.String)>
 956 getfield #1109 <Field java.io.BufferedOutputStream a>
 959 ldc #99 <String "action tried *)
">
 961 invokestatic #1208 <Method void i(java.io.BufferedOutputStream, java.lang.String)>
 964 getfield #1109 <Field java.io.BufferedOutputStream a>
 967 ldc #101 <String "structure Internal =
	struct
">
 969 invokestatic #1208 <Method void i(java.io.BufferedOutputStream, java.lang.String)>
 972 invokespecial #1344 <Method Ro(int)>
 975 astore 67
 977 invokestatic #1289 <Method int aD(Rd, int)>
 980 sipush 256
 983 if_icmplt 3405
 986 iconst_0
 987 istore 66
 989 iload 66
 991 ifne 1003
 994 aload 4
 996 iconst_0
 997 putfield #1150 <Field int a>
1000 goto 1009
1003 aload 4
1005 iconst_1
1006 putfield #1150 <Field int a>
1009 aload 5
1011 getfield #1150 <Field int a>
1014 ifne 1030
1017 aload 15
1019 getfield #1109 <Field java.io.BufferedOutputStream a>
1022 ldc #106 <String "
datatype yyfinstate = N of int">
1024 invokestatic #1208 <Method void i(java.io.BufferedOutputStream, java.lang.String)>
1027 goto 1040
1030 aload 15
1032 getfield #1109 <Field java.io.BufferedOutputStream a>
1035 ldc #109 <String "
datatype yyfinstate = N of int |  T of int | D of int
">
1037 invokestatic #1208 <Method void i(java.io.BufferedOutputStream, java.lang.String)>
1040 aload 4
1042 aload 15
1044 getfield #1109 <Field java.io.BufferedOutputStream a>
1047 ldc #111 <String "
type statedata = {fin : yyfinstate list, trans: ">
1049 invokestatic #1208 <Method void i(java.io.BufferedOutputStream, java.lang.String)>
1052 getfield #1150 <Field int a>
1055 ifne 1071
1058 aload 15
1060 getfield #1109 <Field java.io.BufferedOutputStream a>
1063 ldc #113 <String "int Vector.vector}">
1065 invokestatic #1208 <Method void i(java.io.BufferedOutputStream, java.lang.String)>
1068 goto 1081
1071 aload 15
1073 getfield #1109 <Field java.io.BufferedOutputStream a>
1076 ldc #115 <String "string}">
1078 invokestatic #1208 <Method void i(java.io.BufferedOutputStream, java.lang.String)>
1081 aload 4
1083 aload 15
1085 getfield #1109 <Field java.io.BufferedOutputStream a>
1088 ldc #117 <String "
(* transition & final state table *)
val tab = let
">
1090 invokestatic #1208 <Method void i(java.io.BufferedOutputStream, java.lang.String)>
1093 getfield #1150 <Field int a>
1096 ifne 1149
1099 aload 15
1101 aload 15
1103 aload 15
1105 aload 15
1107 aload 15
1109 getfield #1109 <Field java.io.BufferedOutputStream a>
1112 ldc #119 <String "fun decode s k =
">
1114 invokestatic #1208 <Method void i(java.io.BufferedOutputStream, java.lang.String)>
1117 getfield #1109 <Field java.io.BufferedOutputStream a>
1120 ldc #121 <String "  let val k' = k + k
">
1122 invokestatic #1208 <Method void i(java.io.BufferedOutputStream, java.lang.String)>
1125 getfield #1109 <Field java.io.BufferedOutputStream a>
1128 ldc #123 <String "      val hi = Char.ord(String.sub(s, k'))
">
1130 invokestatic #1208 <Method void i(java.io.BufferedOutputStream, java.lang.String)>
1133 getfield #1109 <Field java.io.BufferedOutputStream a>
1136 ldc #124 <String "      val lo = Char.ord(String.sub(s, k' + 1))
">
1138 invokestatic #1208 <Method void i(java.io.BufferedOutputStream, java.lang.String)>
1141 getfield #1109 <Field java.io.BufferedOutputStream a>
1144 ldc #126 <String "  in hi * 256 + lo end
">
1146 invokestatic #1208 <Method void i(java.io.BufferedOutputStream, java.lang.String)>
1149 aload_2
1150 ldc #128 <String "
Number of states = ">
1152 aload 59
1154 iconst_0
1155 aload 15
1157 aload 15
1159 aload 4
1161 aload 15
1163 aload 67
1165 aload 59
1167 aconst_null
1168 aconst_null
1169 aload 57
1171 aload 60
1173 aconst_null
1174 aload 58
1176 invokestatic #1280 <Method Raa aH(R7, Rd, Raa, Rd)>
1179 astore 68
1181 invokestatic #1311 <Method Rk aM(Ro, Rq, Ro, Rd, Rk, Rab)>
1184 aload 68
1186 aload 15
1188 getfield #1109 <Field java.io.BufferedOutputStream a>
1191 ldc #134 <String "in Vector.fromList
[">
1193 invokestatic #1208 <Method void i(java.io.BufferedOutputStream, java.lang.String)>
1196 invokestatic #1258 <Method void aS(Rq, Rk, Raa)>
1199 getfield #1109 <Field java.io.BufferedOutputStream a>
1202 ldc #138 <String "]
end
">
1204 invokestatic #1208 <Method void i(java.io.BufferedOutputStream, java.lang.String)>
1207 invokestatic #1244 <Method int aU(Rd, int)>
1210 bipush 10
1212 invokestatic #1341 <Method java.lang.String toString(int, int)>
1215 bipush 45
1217 bipush 126
1219 invokevirtual #1245 <Method java.lang.String replace(char, char)>
1222 invokevirtual #1235 <Method java.lang.String concat(java.lang.String)>
1225 invokestatic #1208 <Method void i(java.io.BufferedOutputStream, java.lang.String)>
1228 aload_2
1229 invokevirtual #1335 <Method void flush()>
1232 aload_2
1233 ldc #141 <String "
Number of distinct rows = ">
1235 aload 67
1237 getfield #1150 <Field int a>
1240 bipush 10
1242 invokestatic #1341 <Method java.lang.String toString(int, int)>
1245 bipush 45
1247 bipush 126
1249 invokevirtual #1245 <Method java.lang.String replace(char, char)>
1252 invokevirtual #1235 <Method java.lang.String concat(java.lang.String)>
1255 invokestatic #1208 <Method void i(java.io.BufferedOutputStream, java.lang.String)>
1258 aload_2
1259 invokevirtual #1335 <Method void flush()>
1262 aload 4
1264 aload 67
1266 getfield #1150 <Field int a>
1269 aload 9
1271 getfield #1150 <Field int a>
1274 imul
1275 istore 71
1277 getfield #1150 <Field int a>
1280 ifne 3411
1283 bipush 8
1285 istore 72
1287 aload_2
1288 ldc #143 <String "
Approx. memory size of trans. table = ">
1290 iload 71
1292 iload 72
1294 imul
1295 bipush 10
1297 invokestatic #1341 <Method java.lang.String toString(int, int)>
1300 bipush 45
1302 bipush 126
1304 invokevirtual #1245 <Method java.lang.String replace(char, char)>
1307 invokevirtual #1235 <Method java.lang.String concat(java.lang.String)>
1310 invokestatic #1208 <Method void i(java.io.BufferedOutputStream, java.lang.String)>
1313 aload_2
1314 invokevirtual #1335 <Method void flush()>
1317 aload_2
1318 ldc #145 <String " bytes
">
1320 invokestatic #1208 <Method void i(java.io.BufferedOutputStream, java.lang.String)>
1323 aload_2
1324 invokevirtual #1335 <Method void flush()>
1327 aload 7
1329 aload 15
1331 aload 15
1333 aload 15
1335 aload 15
1337 aload 15
1339 aload 15
1341 aload 15
1343 aload 15
1345 aload 22
1347 aload 15
1349 aload 15
1351 aload 15
1353 getfield #1109 <Field java.io.BufferedOutputStream a>
1356 ldc #147 <String "structure StartStates =
	struct
">
1358 invokestatic #1208 <Method void i(java.io.BufferedOutputStream, java.lang.String)>
1361 getfield #1109 <Field java.io.BufferedOutputStream a>
1364 ldc #149 <String "	datatype yystartstate = STARTSTATE of int
">
1366 invokestatic #1208 <Method void i(java.io.BufferedOutputStream, java.lang.String)>
1369 getfield #1109 <Field java.io.BufferedOutputStream a>
1372 ldc #150 <String "
(* start state definitions *)

">
1374 invokestatic #1208 <Method void i(java.io.BufferedOutputStream, java.lang.String)>
1377 getfield #1121 <Field Rm a>
1380 getfield #1123 <Field Rf b>
1383 aconst_null
1384 invokestatic #1380 <Method Rf aW(Rf, Rf)>
1387 invokestatic #1218 <Method void aV(Rq, Rf)>
1390 getfield #1109 <Field java.io.BufferedOutputStream a>
1393 ldc #152 <String "
end
">
1395 invokestatic #1208 <Method void i(java.io.BufferedOutputStream, java.lang.String)>
1398 getfield #1109 <Field java.io.BufferedOutputStream a>
1401 ldc #155 <String "type result = UserDeclarations.lexresult
">
1403 invokestatic #1208 <Method void i(java.io.BufferedOutputStream, java.lang.String)>
1406 getfield #1109 <Field java.io.BufferedOutputStream a>
1409 ldc #156 <String "	exception LexerError (* raised if illegal leaf ">
1411 invokestatic #1208 <Method void i(java.io.BufferedOutputStream, java.lang.String)>
1414 getfield #1109 <Field java.io.BufferedOutputStream a>
1417 ldc #99 <String "action tried *)
">
1419 invokestatic #1208 <Method void i(java.io.BufferedOutputStream, java.lang.String)>
1422 getfield #1109 <Field java.io.BufferedOutputStream a>
1425 ldc #157 <String "end

">
1427 invokestatic #1208 <Method void i(java.io.BufferedOutputStream, java.lang.String)>
1430 getfield #1109 <Field java.io.BufferedOutputStream a>
1433 ldc #158 <String "fun makeLexer yyinput = 
">
1435 invokestatic #1208 <Method void i(java.io.BufferedOutputStream, java.lang.String)>
1438 getfield #1109 <Field java.io.BufferedOutputStream a>
1441 ldc #159 <String "let 
">
1443 invokestatic #1208 <Method void i(java.io.BufferedOutputStream, java.lang.String)>
1446 getfield #1150 <Field int a>
1449 ifeq 1462
1452 aload 15
1454 getfield #1109 <Field java.io.BufferedOutputStream a>
1457 ldc #160 <String "	val yylineno = ref 0

">
1459 invokestatic #1208 <Method void i(java.io.BufferedOutputStream, java.lang.String)>
1462 aload 13
1464 aload 15
1466 getfield #1109 <Field java.io.BufferedOutputStream a>
1469 ldc #161 <String "	val yyb = ref "\n" 		(* buffer *)
	val yybl = ref 1		(*buffer length *)
	val yybufpos = ref 1		(* location of next character to use *)
	val yygone = ref 1		(* position in file of beginning of buffer *)
	val yydone = ref false		(* eof found yet? *)
	val yybegin = ref 1		(*Current 'start state' for lexer *)

	val YYBEGIN = fn (Internal.StartStates.STARTSTATE x) =>
		 yybegin := x

">
1471 invokestatic #1208 <Method void i(java.io.BufferedOutputStream, java.lang.String)>
1474 getfield #1094 <Field java.lang.String a>
1477 dup
1478 astore 75
1480 ifnonnull 1590
1483 aload 15
1485 aload 15
1487 aload 15
1489 aload 15
1491 getfield #1109 <Field java.io.BufferedOutputStream a>
1494 ldc #162 <String "fun lex () : Internal.result =">
1496 invokestatic #1208 <Method void i(java.io.BufferedOutputStream, java.lang.String)>
1499 getfield #1109 <Field java.io.BufferedOutputStream a>
1502 ldc #11 <String "
">
1504 invokestatic #1208 <Method void i(java.io.BufferedOutputStream, java.lang.String)>
1507 getfield #1109 <Field java.io.BufferedOutputStream a>
1510 ldc #163 <String "let fun continue() = lex() in">
1512 invokestatic #1208 <Method void i(java.io.BufferedOutputStream, java.lang.String)>
1515 getfield #1109 <Field java.io.BufferedOutputStream a>
1518 ldc #11 <String "
">
1520 invokestatic #1208 <Method void i(java.io.BufferedOutputStream, java.lang.String)>
1523 goto 1660
1526 astore 69
1528 new #835 <Class Eb>
1531 dup
1532 aload 69
1534 ldc #164 <String "flushOut">
1536 ldc #98 <String "java.io.BufferedOutputStream">
1538 invokespecial #1259 <Method Eb(java.lang.Exception,java.lang.String,java.lang.String)>
1541 athrow
1542 astore 70
1544 new #835 <Class Eb>
1547 dup
1548 aload 70
1550 ldc #164 <String "flushOut">
1552 ldc #98 <String "java.io.BufferedOutputStream">
1554 invokespecial #1259 <Method Eb(java.lang.Exception,java.lang.String,java.lang.String)>
1557 athrow
1558 astore 73
1560 new #835 <Class Eb>
1563 dup
1564 aload 73
1566 ldc #164 <String "flushOut">
1568 ldc #98 <String "java.io.BufferedOutputStream">
1570 invokespecial #1259 <Method Eb(java.lang.Exception,java.lang.String,java.lang.String)>
1573 athrow
1574 astore 74
1576 new #835 <Class Eb>
1579 dup
1580 aload 74
1582 ldc #164 <String "flushOut">
1584 ldc #98 <String "java.io.BufferedOutputStream">
1586 invokespecial #1259 <Method Eb(java.lang.Exception,java.lang.String,java.lang.String)>
1589 athrow
1590 aload 15
1592 aload 15
1594 aload 15
1596 aload 15
1598 aload 15
1600 aload 15
1602 aload 15
1604 getfield #1109 <Field java.io.BufferedOutputStream a>
1607 ldc #165 <String "fun lex ">
1609 invokestatic #1208 <Method void i(java.io.BufferedOutputStream, java.lang.String)>
1612 getfield #1109 <Field java.io.BufferedOutputStream a>
1615 ldc #167 <String "(yyarg as (">
1617 invokestatic #1208 <Method void i(java.io.BufferedOutputStream, java.lang.String)>
1620 getfield #1109 <Field java.io.BufferedOutputStream a>
1623 aload 75
1625 invokestatic #1208 <Method void i(java.io.BufferedOutputStream, java.lang.String)>
1628 getfield #1109 <Field java.io.BufferedOutputStream a>
1631 ldc #168 <String ")) =">
1633 invokestatic #1208 <Method void i(java.io.BufferedOutputStream, java.lang.String)>
1636 getfield #1109 <Field java.io.BufferedOutputStream a>
1639 ldc #11 <String "
">
1641 invokestatic #1208 <Method void i(java.io.BufferedOutputStream, java.lang.String)>
1644 getfield #1109 <Field java.io.BufferedOutputStream a>
1647 ldc #169 <String "let fun continue() : Internal.result = ">
1649 invokestatic #1208 <Method void i(java.io.BufferedOutputStream, java.lang.String)>
1652 getfield #1109 <Field java.io.BufferedOutputStream a>
1655 ldc #11 <String "
">
1657 invokestatic #1208 <Method void i(java.io.BufferedOutputStream, java.lang.String)>
1660 aload 5
1662 aload 15
1664 aload 15
1666 aload 15
1668 getfield #1109 <Field java.io.BufferedOutputStream a>
1671 ldc #170 <String "  let fun scan (s,AcceptingLeaves : Internal.yyfinstate">
1673 invokestatic #1208 <Method void i(java.io.BufferedOutputStream, java.lang.String)>
1676 getfield #1109 <Field java.io.BufferedOutputStream a>
1679 ldc #171 <String " list list,l,i0) =">
1681 invokestatic #1208 <Method void i(java.io.BufferedOutputStream, java.lang.String)>
1684 getfield #1109 <Field java.io.BufferedOutputStream a>
1687 ldc #11 <String "
">
1689 invokestatic #1208 <Method void i(java.io.BufferedOutputStream, java.lang.String)>
1692 getfield #1150 <Field int a>
1695 ifne 1711
1698 aload 15
1700 getfield #1109 <Field java.io.BufferedOutputStream a>
1703 ldc #172 <String "	let fun action (i,nil)">
1705 invokestatic #1208 <Method void i(java.io.BufferedOutputStream, java.lang.String)>
1708 goto 1721
1711 aload 15
1713 getfield #1109 <Field java.io.BufferedOutputStream a>
1716 ldc #173 <String "	let fun action (i,nil,rs)">
1718 invokestatic #1208 <Method void i(java.io.BufferedOutputStream, java.lang.String)>
1721 aload 5
1723 aload 15
1725 aload 15
1727 getfield #1109 <Field java.io.BufferedOutputStream a>
1730 ldc #175 <String " = raise LexError">
1732 invokestatic #1208 <Method void i(java.io.BufferedOutputStream, java.lang.String)>
1735 getfield #1109 <Field java.io.BufferedOutputStream a>
1738 ldc #11 <String "
">
1740 invokestatic #1208 <Method void i(java.io.BufferedOutputStream, java.lang.String)>
1743 getfield #1150 <Field int a>
1746 ifne 1772
1749 aload 15
1751 aload 15
1753 getfield #1109 <Field java.io.BufferedOutputStream a>
1756 ldc #177 <String "	| action (i,nil::l) = action (i-1,l)">
1758 invokestatic #1208 <Method void i(java.io.BufferedOutputStream, java.lang.String)>
1761 getfield #1109 <Field java.io.BufferedOutputStream a>
1764 ldc #11 <String "
">
1766 invokestatic #1208 <Method void i(java.io.BufferedOutputStream, java.lang.String)>
1769 goto 1792
1772 aload 15
1774 aload 15
1776 getfield #1109 <Field java.io.BufferedOutputStream a>
1779 ldc #178 <String "	| action (i,nil::l,rs) = action(i-1,l,rs)">
1781 invokestatic #1208 <Method void i(java.io.BufferedOutputStream, java.lang.String)>
1784 getfield #1109 <Field java.io.BufferedOutputStream a>
1787 ldc #11 <String "
">
1789 invokestatic #1208 <Method void i(java.io.BufferedOutputStream, java.lang.String)>
1792 aload 5
1794 getfield #1150 <Field int a>
1797 ifne 1823
1800 aload 15
1802 aload 15
1804 getfield #1109 <Field java.io.BufferedOutputStream a>
1807 ldc #179 <String "	| action (i,(node::acts)::l) =">
1809 invokestatic #1208 <Method void i(java.io.BufferedOutputStream, java.lang.String)>
1812 getfield #1109 <Field java.io.BufferedOutputStream a>
1815 ldc #11 <String "
">
1817 invokestatic #1208 <Method void i(java.io.BufferedOutputStream, java.lang.String)>
1820 goto 1843
1823 aload 15
1825 aload 15
1827 getfield #1109 <Field java.io.BufferedOutputStream a>
1830 ldc #180 <String "	| action (i,(node::acts)::l,rs) =">
1832 invokestatic #1208 <Method void i(java.io.BufferedOutputStream, java.lang.String)>
1835 getfield #1109 <Field java.io.BufferedOutputStream a>
1838 ldc #11 <String "
">
1840 invokestatic #1208 <Method void i(java.io.BufferedOutputStream, java.lang.String)>
1843 aload 7
1845 aload 15
1847 aload 15
1849 aload 15
1851 aload 15
1853 aload 15
1855 aload 15
1857 getfield #1109 <Field java.io.BufferedOutputStream a>
1860 ldc #181 <String "		case node of">
1862 invokestatic #1208 <Method void i(java.io.BufferedOutputStream, java.lang.String)>
1865 getfield #1109 <Field java.io.BufferedOutputStream a>
1868 ldc #11 <String "
">
1870 invokestatic #1208 <Method void i(java.io.BufferedOutputStream, java.lang.String)>
1873 getfield #1109 <Field java.io.BufferedOutputStream a>
1876 ldc #183 <String "		    Internal.N yyk => ">
1878 invokestatic #1208 <Method void i(java.io.BufferedOutputStream, java.lang.String)>
1881 getfield #1109 <Field java.io.BufferedOutputStream a>
1884 ldc #11 <String "
">
1886 invokestatic #1208 <Method void i(java.io.BufferedOutputStream, java.lang.String)>
1889 getfield #1109 <Field java.io.BufferedOutputStream a>
1892 ldc #3 <String "			(let val yytext = substring(!yyb,i0,i-i0)
			     val yypos = i0+ !yygone">
1894 invokestatic #1208 <Method void i(java.io.BufferedOutputStream, java.lang.String)>
1897 getfield #1109 <Field java.io.BufferedOutputStream a>
1900 ldc #11 <String "
">
1902 invokestatic #1208 <Method void i(java.io.BufferedOutputStream, java.lang.String)>
1905 getfield #1150 <Field int a>
1908 ifeq 1951
1911 aload 15
1913 aload 15
1915 aload 15
1917 aload 15
1919 getfield #1109 <Field java.io.BufferedOutputStream a>
1922 ldc #5 <String "			val _ = yylineno := CharVector.foldl">
1924 invokestatic #1208 <Method void i(java.io.BufferedOutputStream, java.lang.String)>
1927 getfield #1109 <Field java.io.BufferedOutputStream a>
1930 ldc #11 <String "
">
1932 invokestatic #1208 <Method void i(java.io.BufferedOutputStream, java.lang.String)>
1935 getfield #1109 <Field java.io.BufferedOutputStream a>
1938 ldc #6 <String "				(fn (#"\n", n) => n+1 | (_, n) => n) (!yylineno) yytext">
1940 invokestatic #1208 <Method void i(java.io.BufferedOutputStream, java.lang.String)>
1943 getfield #1109 <Field java.io.BufferedOutputStream a>
1946 ldc #11 <String "
">
1948 invokestatic #1208 <Method void i(java.io.BufferedOutputStream, java.lang.String)>
1951 aload 8
1953 getfield #1150 <Field int a>
1956 ifeq 2020
1959 aload 5
1961 aload 15
1963 getfield #1109 <Field java.io.BufferedOutputStream a>
1966 ldc #7 <String "			fun REJECT() = action(i,acts::l">
1968 invokestatic #1208 <Method void i(java.io.BufferedOutputStream, java.lang.String)>
1971 getfield #1150 <Field int a>
1974 ifne 2000
1977 aload 15
1979 aload 15
1981 getfield #1109 <Field java.io.BufferedOutputStream a>
1984 ldc #10 <String ")">
1986 invokestatic #1208 <Method void i(java.io.BufferedOutputStream, java.lang.String)>
1989 getfield #1109 <Field java.io.BufferedOutputStream a>
1992 ldc #11 <String "
">
1994 invokestatic #1208 <Method void i(java.io.BufferedOutputStream, java.lang.String)>
1997 goto 2020
2000 aload 15
2002 aload 15
2004 getfield #1109 <Field java.io.BufferedOutputStream a>
2007 ldc #12 <String ",rs)">
2009 invokestatic #1208 <Method void i(java.io.BufferedOutputStream, java.lang.String)>
2012 getfield #1109 <Field java.io.BufferedOutputStream a>
2015 ldc #11 <String "
">
2017 invokestatic #1208 <Method void i(java.io.BufferedOutputStream, java.lang.String)>
2020 aload 5
2022 aload 15
2024 aload 15
2026 aload 15
2028 aload 56
2030 aload 15
2032 aload 15
2034 aload 15
2036 aload 15
2038 aload 15
2040 aload 15
2042 aload 15
2044 aload 15
2046 getfield #1109 <Field java.io.BufferedOutputStream a>
2049 ldc #13 <String "			open UserDeclarations Internal.StartStates">
2051 invokestatic #1208 <Method void i(java.io.BufferedOutputStream, java.lang.String)>
2054 getfield #1109 <Field java.io.BufferedOutputStream a>
2057 ldc #11 <String "
">
2059 invokestatic #1208 <Method void i(java.io.BufferedOutputStream, java.lang.String)>
2062 getfield #1109 <Field java.io.BufferedOutputStream a>
2065 ldc #14 <String " in (yybufpos := i; case yyk of ">
2067 invokestatic #1208 <Method void i(java.io.BufferedOutputStream, java.lang.String)>
2070 getfield #1109 <Field java.io.BufferedOutputStream a>
2073 ldc #11 <String "
">
2075 invokestatic #1208 <Method void i(java.io.BufferedOutputStream, java.lang.String)>
2078 getfield #1109 <Field java.io.BufferedOutputStream a>
2081 ldc #129 <String "">
2083 invokestatic #1208 <Method void i(java.io.BufferedOutputStream, java.lang.String)>
2086 getfield #1109 <Field java.io.BufferedOutputStream a>
2089 ldc #11 <String "
">
2091 invokestatic #1208 <Method void i(java.io.BufferedOutputStream, java.lang.String)>
2094 getfield #1109 <Field java.io.BufferedOutputStream a>
2097 ldc #15 <String "			(* Application actions *)
">
2099 invokestatic #1208 <Method void i(java.io.BufferedOutputStream, java.lang.String)>
2102 getfield #1109 <Field java.io.BufferedOutputStream a>
2105 ldc #11 <String "
">
2107 invokestatic #1208 <Method void i(java.io.BufferedOutputStream, java.lang.String)>
2110 getfield #1193 <Field Rh b>
2113 aconst_null
2114 invokestatic #1303 <Method Rh aY(Rh, Rh)>
2117 iconst_1
2118 invokestatic #1325 <Method void aX(Rq, Rh, int)>
2121 getfield #1109 <Field java.io.BufferedOutputStream a>
2124 ldc #18 <String "
		) end ">
2126 invokestatic #1208 <Method void i(java.io.BufferedOutputStream, java.lang.String)>
2129 getfield #1109 <Field java.io.BufferedOutputStream a>
2132 ldc #20 <String ")

">
2134 invokestatic #1208 <Method void i(java.io.BufferedOutputStream, java.lang.String)>
2137 getfield #1150 <Field int a>
2140 ifeq 2153
2143 aload 15
2145 getfield #1109 <Field java.io.BufferedOutputStream a>
2148 ldc #21 <String "                       | Internal.D k => action (i,(acts::l),k::rs)
                       | Internal.T k =>
                         let fun f (a::b,r) =
                              if a=k
                                then action(i,(((Internal.N a)::acts)::l),(b@r))
                                else f (b,a::r)
                               | f (nil,r) = action(i,(acts::l),rs)
                          in f (rs,nil)
                          end
">
2150 invokestatic #1208 <Method void i(java.io.BufferedOutputStream, java.lang.String)>
2153 aload 5
2155 aload 15
2157 aload 15
2159 aload 15
2161 aload 15
2163 aload 15
2165 aload 15
2167 aload 15
2169 aload 15
2171 aload 15
2173 aload 15
2175 getfield #1109 <Field java.io.BufferedOutputStream a>
2178 ldc #22 <String "	val {fin,trans} = Vector.sub(Internal.tab, s)">
2180 invokestatic #1208 <Method void i(java.io.BufferedOutputStream, java.lang.String)>
2183 getfield #1109 <Field java.io.BufferedOutputStream a>
2186 ldc #11 <String "
">
2188 invokestatic #1208 <Method void i(java.io.BufferedOutputStream, java.lang.String)>
2191 getfield #1109 <Field java.io.BufferedOutputStream a>
2194 ldc #23 <String "	val NewAcceptingLeaves = fin::AcceptingLeaves">
2196 invokestatic #1208 <Method void i(java.io.BufferedOutputStream, java.lang.String)>
2199 getfield #1109 <Field java.io.BufferedOutputStream a>
2202 ldc #11 <String "
">
2204 invokestatic #1208 <Method void i(java.io.BufferedOutputStream, java.lang.String)>
2207 getfield #1109 <Field java.io.BufferedOutputStream a>
2210 ldc #24 <String "	in if l = !yybl then">
2212 invokestatic #1208 <Method void i(java.io.BufferedOutputStream, java.lang.String)>
2215 getfield #1109 <Field java.io.BufferedOutputStream a>
2218 ldc #11 <String "
">
2220 invokestatic #1208 <Method void i(java.io.BufferedOutputStream, java.lang.String)>
2223 getfield #1109 <Field java.io.BufferedOutputStream a>
2226 ldc #25 <String "	     if trans = #trans(Vector.sub(Internal.tab,0))">
2228 invokestatic #1208 <Method void i(java.io.BufferedOutputStream, java.lang.String)>
2231 getfield #1109 <Field java.io.BufferedOutputStream a>
2234 ldc #11 <String "
">
2236 invokestatic #1208 <Method void i(java.io.BufferedOutputStream, java.lang.String)>
2239 getfield #1109 <Field java.io.BufferedOutputStream a>
2242 ldc #26 <String "	       then action(l,NewAcceptingLeaves">
2244 invokestatic #1208 <Method void i(java.io.BufferedOutputStream, java.lang.String)>
2247 getfield #1109 <Field java.io.BufferedOutputStream a>
2250 ldc #11 <String "
">
2252 invokestatic #1208 <Method void i(java.io.BufferedOutputStream, java.lang.String)>
2255 getfield #1150 <Field int a>
2258 ifeq 2271
2261 aload 15
2263 getfield #1109 <Field java.io.BufferedOutputStream a>
2266 ldc #27 <String ",nil">
2268 invokestatic #1208 <Method void i(java.io.BufferedOutputStream, java.lang.String)>
2271 aload 13
2273 aload 15
2275 aload 15
2277 aload 15
2279 aload 15
2281 aload 15
2283 aload 15
2285 aload 15
2287 aload 15
2289 getfield #1109 <Field java.io.BufferedOutputStream a>
2292 ldc #28 <String ") else">
2294 invokestatic #1208 <Method void i(java.io.BufferedOutputStream, java.lang.String)>
2297 getfield #1109 <Field java.io.BufferedOutputStream a>
2300 ldc #29 <String "	    let val newchars= if !yydone then "" else yyinput 1024">
2302 invokestatic #1208 <Method void i(java.io.BufferedOutputStream, java.lang.String)>
2305 getfield #1109 <Field java.io.BufferedOutputStream a>
2308 ldc #11 <String "
">
2310 invokestatic #1208 <Method void i(java.io.BufferedOutputStream, java.lang.String)>
2313 getfield #1109 <Field java.io.BufferedOutputStream a>
2316 ldc #31 <String "	    in if (size newchars)=0">
2318 invokestatic #1208 <Method void i(java.io.BufferedOutputStream, java.lang.String)>
2321 getfield #1109 <Field java.io.BufferedOutputStream a>
2324 ldc #11 <String "
">
2326 invokestatic #1208 <Method void i(java.io.BufferedOutputStream, java.lang.String)>
2329 getfield #1109 <Field java.io.BufferedOutputStream a>
2332 ldc #34 <String "		  then (yydone := true;">
2334 invokestatic #1208 <Method void i(java.io.BufferedOutputStream, java.lang.String)>
2337 getfield #1109 <Field java.io.BufferedOutputStream a>
2340 ldc #11 <String "
">
2342 invokestatic #1208 <Method void i(java.io.BufferedOutputStream, java.lang.String)>
2345 getfield #1109 <Field java.io.BufferedOutputStream a>
2348 ldc #35 <String "		        if (l=i0) then UserDeclarations.eof ">
2350 invokestatic #1208 <Method void i(java.io.BufferedOutputStream, java.lang.String)>
2353 getfield #1094 <Field java.lang.String a>
2356 ifnonnull 3417
2359 ldc #36 <String "()">
2361 astore 76
2363 aload 5
2365 aload 15
2367 aload 15
2369 aload 15
2371 getfield #1109 <Field java.io.BufferedOutputStream a>
2374 aload 76
2376 invokestatic #1208 <Method void i(java.io.BufferedOutputStream, java.lang.String)>
2379 getfield #1109 <Field java.io.BufferedOutputStream a>
2382 ldc #11 <String "
">
2384 invokestatic #1208 <Method void i(java.io.BufferedOutputStream, java.lang.String)>
2387 getfield #1109 <Field java.io.BufferedOutputStream a>
2390 ldc #37 <String "		                  else action(l,NewAcceptingLeaves">
2392 invokestatic #1208 <Method void i(java.io.BufferedOutputStream, java.lang.String)>
2395 getfield #1150 <Field int a>
2398 ifne 2424
2401 aload 15
2403 aload 15
2405 getfield #1109 <Field java.io.BufferedOutputStream a>
2408 ldc #38 <String "))">
2410 invokestatic #1208 <Method void i(java.io.BufferedOutputStream, java.lang.String)>
2413 getfield #1109 <Field java.io.BufferedOutputStream a>
2416 ldc #11 <String "
">
2418 invokestatic #1208 <Method void i(java.io.BufferedOutputStream, java.lang.String)>
2421 goto 2444
2424 aload 15
2426 aload 15
2428 getfield #1109 <Field java.io.BufferedOutputStream a>
2431 ldc #39 <String ",nil))">
2433 invokestatic #1208 <Method void i(java.io.BufferedOutputStream, java.lang.String)>
2436 getfield #1109 <Field java.io.BufferedOutputStream a>
2439 ldc #11 <String "
">
2441 invokestatic #1208 <Method void i(java.io.BufferedOutputStream, java.lang.String)>
2444 aload 9
2446 aload 4
2448 aload 15
2450 aload 15
2452 aload 15
2454 aload 15
2456 aload 15
2458 aload 15
2460 aload 15
2462 aload 15
2464 aload 15
2466 aload 15
2468 aload 15
2470 aload 15
2472 aload 15
2474 aload 15
2476 aload 15
2478 getfield #1109 <Field java.io.BufferedOutputStream a>
2481 ldc #41 <String "		  else (if i0=l then yyb := newchars">
2483 invokestatic #1208 <Method void i(java.io.BufferedOutputStream, java.lang.String)>
2486 getfield #1109 <Field java.io.BufferedOutputStream a>
2489 ldc #11 <String "
">
2491 invokestatic #1208 <Method void i(java.io.BufferedOutputStream, java.lang.String)>
2494 getfield #1109 <Field java.io.BufferedOutputStream a>
2497 ldc #42 <String "		     else yyb := substring(!yyb,i0,l-i0)^newchars;">
2499 invokestatic #1208 <Method void i(java.io.BufferedOutputStream, java.lang.String)>
2502 getfield #1109 <Field java.io.BufferedOutputStream a>
2505 ldc #11 <String "
">
2507 invokestatic #1208 <Method void i(java.io.BufferedOutputStream, java.lang.String)>
2510 getfield #1109 <Field java.io.BufferedOutputStream a>
2513 ldc #43 <String "		     yygone := !yygone+i0;">
2515 invokestatic #1208 <Method void i(java.io.BufferedOutputStream, java.lang.String)>
2518 getfield #1109 <Field java.io.BufferedOutputStream a>
2521 ldc #11 <String "
">
2523 invokestatic #1208 <Method void i(java.io.BufferedOutputStream, java.lang.String)>
2526 getfield #1109 <Field java.io.BufferedOutputStream a>
2529 ldc #45 <String "		     yybl := size (!yyb);">
2531 invokestatic #1208 <Method void i(java.io.BufferedOutputStream, java.lang.String)>
2534 getfield #1109 <Field java.io.BufferedOutputStream a>
2537 ldc #11 <String "
">
2539 invokestatic #1208 <Method void i(java.io.BufferedOutputStream, java.lang.String)>
2542 getfield #1109 <Field java.io.BufferedOutputStream a>
2545 ldc #47 <String "		     scan (s,AcceptingLeaves,l-i0,0))">
2547 invokestatic #1208 <Method void i(java.io.BufferedOutputStream, java.lang.String)>
2550 getfield #1109 <Field java.io.BufferedOutputStream a>
2553 ldc #11 <String "
">
2555 invokestatic #1208 <Method void i(java.io.BufferedOutputStream, java.lang.String)>
2558 getfield #1109 <Field java.io.BufferedOutputStream a>
2561 ldc #48 <String "	    end">
2563 invokestatic #1208 <Method void i(java.io.BufferedOutputStream, java.lang.String)>
2566 getfield #1109 <Field java.io.BufferedOutputStream a>
2569 ldc #11 <String "
">
2571 invokestatic #1208 <Method void i(java.io.BufferedOutputStream, java.lang.String)>
2574 getfield #1109 <Field java.io.BufferedOutputStream a>
2577 ldc #50 <String "	  else let val NewChar = Char.ord(String.sub(!yyb,l))">
2579 invokestatic #1208 <Method void i(java.io.BufferedOutputStream, java.lang.String)>
2582 getfield #1109 <Field java.io.BufferedOutputStream a>
2585 ldc #11 <String "
">
2587 invokestatic #1208 <Method void i(java.io.BufferedOutputStream, java.lang.String)>
2590 getfield #1109 <Field java.io.BufferedOutputStream a>
2593 ldc #51 <String "		val NewState = ">
2595 invokestatic #1208 <Method void i(java.io.BufferedOutputStream, java.lang.String)>
2598 getfield #1150 <Field int a>
2601 istore 77
2603 getfield #1150 <Field int a>
2606 lookupswitch 2: default=2632
	  129: 3138
	  256: 2640
2632 new #817 <Class Eh>
2635 dup
2636 invokespecial #1240 <Method Eh()>
2639 athrow
2640 iload 77
2642 ifne 2668
2645 aload 15
2647 aload 15
2649 getfield #1109 <Field java.io.BufferedOutputStream a>
2652 ldc #52 <String "Vector.sub(trans, NewChar)">
2654 invokestatic #1208 <Method void i(java.io.BufferedOutputStream, java.lang.String)>
2657 getfield #1109 <Field java.io.BufferedOutputStream a>
2660 ldc #11 <String "
">
2662 invokestatic #1208 <Method void i(java.io.BufferedOutputStream, java.lang.String)>
2665 goto 2688
2668 aload 15
2670 aload 15
2672 getfield #1109 <Field java.io.BufferedOutputStream a>
2675 ldc #53 <String "Char.ord(String.sub(trans,NewChar))">
2677 invokestatic #1208 <Method void i(java.io.BufferedOutputStream, java.lang.String)>
2680 getfield #1109 <Field java.io.BufferedOutputStream a>
2683 ldc #11 <String "
">
2685 invokestatic #1208 <Method void i(java.io.BufferedOutputStream, java.lang.String)>
2688 aload 5
2690 aload 15
2692 getfield #1109 <Field java.io.BufferedOutputStream a>
2695 ldc #54 <String "		in if NewState=0 then action(l,NewAcceptingLeaves">
2697 invokestatic #1208 <Method void i(java.io.BufferedOutputStream, java.lang.String)>
2700 getfield #1150 <Field int a>
2703 ifne 2729
2706 aload 15
2708 aload 15
2710 getfield #1109 <Field java.io.BufferedOutputStream a>
2713 ldc #10 <String ")">
2715 invokestatic #1208 <Method void i(java.io.BufferedOutputStream, java.lang.String)>
2718 getfield #1109 <Field java.io.BufferedOutputStream a>
2721 ldc #11 <String "
">
2723 invokestatic #1208 <Method void i(java.io.BufferedOutputStream, java.lang.String)>
2726 goto 2749
2729 aload 15
2731 aload 15
2733 getfield #1109 <Field java.io.BufferedOutputStream a>
2736 ldc #55 <String ",nil)">
2738 invokestatic #1208 <Method void i(java.io.BufferedOutputStream, java.lang.String)>
2741 getfield #1109 <Field java.io.BufferedOutputStream a>
2744 ldc #11 <String "
">
2746 invokestatic #1208 <Method void i(java.io.BufferedOutputStream, java.lang.String)>
2749 aload 6
2751 aload 15
2753 aload 15
2755 aload 15
2757 aload 15
2759 aload 15
2761 aload 15
2763 getfield #1109 <Field java.io.BufferedOutputStream a>
2766 ldc #56 <String "		else scan(NewState,NewAcceptingLeaves,l+1,i0)">
2768 invokestatic #1208 <Method void i(java.io.BufferedOutputStream, java.lang.String)>
2771 getfield #1109 <Field java.io.BufferedOutputStream a>
2774 ldc #11 <String "
">
2776 invokestatic #1208 <Method void i(java.io.BufferedOutputStream, java.lang.String)>
2779 getfield #1109 <Field java.io.BufferedOutputStream a>
2782 ldc #57 <String "	end">
2784 invokestatic #1208 <Method void i(java.io.BufferedOutputStream, java.lang.String)>
2787 getfield #1109 <Field java.io.BufferedOutputStream a>
2790 ldc #11 <String "
">
2792 invokestatic #1208 <Method void i(java.io.BufferedOutputStream, java.lang.String)>
2795 getfield #1109 <Field java.io.BufferedOutputStream a>
2798 ldc #57 <String "	end">
2800 invokestatic #1208 <Method void i(java.io.BufferedOutputStream, java.lang.String)>
2803 getfield #1109 <Field java.io.BufferedOutputStream a>
2806 ldc #11 <String "
">
2808 invokestatic #1208 <Method void i(java.io.BufferedOutputStream, java.lang.String)>
2811 getfield #1150 <Field int a>
2814 ifne 2837
2817 aload 15
2819 aload 15
2821 getfield #1109 <Field java.io.BufferedOutputStream a>
2824 ldc #59 <String "(*">
2826 invokestatic #1208 <Method void i(java.io.BufferedOutputStream, java.lang.String)>
2829 getfield #1109 <Field java.io.BufferedOutputStream a>
2832 ldc #11 <String "
">
2834 invokestatic #1208 <Method void i(java.io.BufferedOutputStream, java.lang.String)>
2837 aload 6
2839 aload 15
2841 aload 15
2843 aload 15
2845 aload 15
2847 getfield #1109 <Field java.io.BufferedOutputStream a>
2850 ldc #60 <String "	val start= if substring(!yyb,!yybufpos-1,1)="\n"">
2852 invokestatic #1208 <Method void i(java.io.BufferedOutputStream, java.lang.String)>
2855 getfield #1109 <Field java.io.BufferedOutputStream a>
2858 ldc #11 <String "
">
2860 invokestatic #1208 <Method void i(java.io.BufferedOutputStream, java.lang.String)>
2863 getfield #1109 <Field java.io.BufferedOutputStream a>
2866 ldc #61 <String "then !yybegin+1 else !yybegin">
2868 invokestatic #1208 <Method void i(java.io.BufferedOutputStream, java.lang.String)>
2871 getfield #1109 <Field java.io.BufferedOutputStream a>
2874 ldc #11 <String "
">
2876 invokestatic #1208 <Method void i(java.io.BufferedOutputStream, java.lang.String)>
2879 getfield #1150 <Field int a>
2882 ifne 2905
2885 aload 15
2887 aload 15
2889 getfield #1109 <Field java.io.BufferedOutputStream a>
2892 ldc #64 <String "*)">
2894 invokestatic #1208 <Method void i(java.io.BufferedOutputStream, java.lang.String)>
2897 getfield #1109 <Field java.io.BufferedOutputStream a>
2900 ldc #11 <String "
">
2902 invokestatic #1208 <Method void i(java.io.BufferedOutputStream, java.lang.String)>
2905 aload 6
2907 aload 15
2909 getfield #1109 <Field java.io.BufferedOutputStream a>
2912 ldc #65 <String "	in scan(">
2914 invokestatic #1208 <Method void i(java.io.BufferedOutputStream, java.lang.String)>
2917 getfield #1150 <Field int a>
2920 ifne 2936
2923 aload 15
2925 getfield #1109 <Field java.io.BufferedOutputStream a>
2928 ldc #67 <String "!yybegin (* start *)">
2930 invokestatic #1208 <Method void i(java.io.BufferedOutputStream, java.lang.String)>
2933 goto 2946
2936 aload 15
2938 getfield #1109 <Field java.io.BufferedOutputStream a>
2941 ldc #69 <String "start">
2943 invokestatic #1208 <Method void i(java.io.BufferedOutputStream, java.lang.String)>
2946 aload 13
2948 aload 15
2950 aload 15
2952 aload 15
2954 aload 15
2956 getfield #1109 <Field java.io.BufferedOutputStream a>
2959 ldc #71 <String ",nil,!yybufpos,!yybufpos)">
2961 invokestatic #1208 <Method void i(java.io.BufferedOutputStream, java.lang.String)>
2964 getfield #1109 <Field java.io.BufferedOutputStream a>
2967 ldc #11 <String "
">
2969 invokestatic #1208 <Method void i(java.io.BufferedOutputStream, java.lang.String)>
2972 getfield #1109 <Field java.io.BufferedOutputStream a>
2975 ldc #73 <String "    end">
2977 invokestatic #1208 <Method void i(java.io.BufferedOutputStream, java.lang.String)>
2980 getfield #1109 <Field java.io.BufferedOutputStream a>
2983 ldc #11 <String "
">
2985 invokestatic #1208 <Method void i(java.io.BufferedOutputStream, java.lang.String)>
2988 getfield #1094 <Field java.lang.String a>
2991 ifnonnull 3424
2994 ldc #77 <String "end">
2996 astore 78
2998 aload 17
3000 aload 15
3002 aload 15
3004 aload 15
3006 aload 15
3008 aload 15
3010 aload 15
3012 aload 15
3014 aload 15
3016 getfield #1109 <Field java.io.BufferedOutputStream a>
3019 aload 78
3021 invokestatic #1208 <Method void i(java.io.BufferedOutputStream, java.lang.String)>
3024 getfield #1109 <Field java.io.BufferedOutputStream a>
3027 ldc #11 <String "
">
3029 invokestatic #1208 <Method void i(java.io.BufferedOutputStream, java.lang.String)>
3032 getfield #1109 <Field java.io.BufferedOutputStream a>
3035 ldc #81 <String "  in lex">
3037 invokestatic #1208 <Method void i(java.io.BufferedOutputStream, java.lang.String)>
3040 getfield #1109 <Field java.io.BufferedOutputStream a>
3043 ldc #11 <String "
">
3045 invokestatic #1208 <Method void i(java.io.BufferedOutputStream, java.lang.String)>
3048 getfield #1109 <Field java.io.BufferedOutputStream a>
3051 ldc #84 <String "  end">
3053 invokestatic #1208 <Method void i(java.io.BufferedOutputStream, java.lang.String)>
3056 getfield #1109 <Field java.io.BufferedOutputStream a>
3059 ldc #11 <String "
">
3061 invokestatic #1208 <Method void i(java.io.BufferedOutputStream, java.lang.String)>
3064 getfield #1109 <Field java.io.BufferedOutputStream a>
3067 ldc #77 <String "end">
3069 invokestatic #1208 <Method void i(java.io.BufferedOutputStream, java.lang.String)>
3072 getfield #1109 <Field java.io.BufferedOutputStream a>
3075 ldc #11 <String "
">
3077 invokestatic #1208 <Method void i(java.io.BufferedOutputStream, java.lang.String)>
3080 getfield #1164 <Field Rw a>
3083 getfield #1135 <Field java.io.BufferedInputStream a>
3086 astore 79
3088 aload 79
3090 invokevirtual #1234 <Method void close()>
3093 aload 15
3095 getfield #1109 <Field java.io.BufferedOutputStream a>
3098 astore 81
3100 aload 81
3102 invokevirtual #1237 <Method void close()>
3105 return
3106 astore 80
3108 new #835 <Class Eb>
3111 dup
3112 aload 80
3114 ldc #82 <String "closeIn">
3116 ldc #176 <String "java.io.BufferedInputStream">
3118 invokespecial #1259 <Method Eb(java.lang.Exception,java.lang.String,java.lang.String)>
3121 athrow
3122 astore 82
3124 new #835 <Class Eb>
3127 dup
3128 aload 82
3130 ldc #85 <String "closeOut">
3132 ldc #98 <String "java.io.BufferedOutputStream">
3134 invokespecial #1259 <Method Eb(java.lang.Exception,java.lang.String,java.lang.String)>
3137 athrow
3138 iload 77
3140 ifne 3166
3143 aload 15
3145 aload 15
3147 getfield #1109 <Field java.io.BufferedOutputStream a>
3150 ldc #87 <String "if NewChar<128 then Vector.sub(trans, NewChar) else Vector.sub(trans, 128)">
3152 invokestatic #1208 <Method void i(java.io.BufferedOutputStream, java.lang.String)>
3155 getfield #1109 <Field java.io.BufferedOutputStream a>
3158 ldc #11 <String "
">
3160 invokestatic #1208 <Method void i(java.io.BufferedOutputStream, java.lang.String)>
3163 goto 2688
3166 aload 15
3168 aload 15
3170 getfield #1109 <Field java.io.BufferedOutputStream a>
3173 ldc #90 <String "if NewChar<128 then Char.ord(String.sub(trans,NewChar)) else Char.ord(String.sub(trans,128))">
3175 invokestatic #1208 <Method void i(java.io.BufferedOutputStream, java.lang.String)>
3178 getfield #1109 <Field java.io.BufferedOutputStream a>
3181 ldc #11 <String "
">
3183 invokestatic #1208 <Method void i(java.io.BufferedOutputStream, java.lang.String)>
3186 goto 2688
3189 astore 85
3191 aload 85
3193 instanceof #829 <Class Eg>
3196 ifeq 3267
3199 aload_3
3200 aload 16
3202 ldc #129 <String "">
3204 invokestatic #1220 <Method Rv B(java.io.BufferedOutputStream, Ro, java.lang.String)>
3207 astore 90
3209 aload 90
3211 getfield #1122 <Field java.lang.String a>
3214 astore 84
3216 aload 90
3218 getfield #1089 <Field Rt b>
3221 astore 42
3223 aload 90
3225 getfield #1108 <Field Ru c>
3228 astore 56
3230 goto 433
3233 astore 87
3235 new #835 <Class Eb>
3238 dup
3239 aload 87
3241 ldc #82 <String "closeIn">
3243 ldc #176 <String "java.io.BufferedInputStream">
3245 invokespecial #1259 <Method Eb(java.lang.Exception,java.lang.String,java.lang.String)>
3248 athrow
3249 astore 89
3251 new #835 <Class Eb>
3254 dup
3255 aload 89
3257 ldc #85 <String "closeOut">
3259 ldc #98 <String "java.io.BufferedOutputStream">
3261 invokespecial #1259 <Method Eb(java.lang.Exception,java.lang.String,java.lang.String)>
3264 athrow
3265 astore 85
3267 aload 17
3269 getfield #1164 <Field Rw a>
3272 getfield #1135 <Field java.io.BufferedInputStream a>
3275 astore 86
3277 aload 86
3279 invokevirtual #1234 <Method void close()>
3282 aload 15
3284 getfield #1109 <Field java.io.BufferedOutputStream a>
3287 astore 88
3289 aload 88
3291 invokevirtual #1237 <Method void close()>
3294 aload 85
3296 athrow
3297 astore 91
3299 aload 91
3301 instanceof #829 <Class Eg>
3304 ifeq 3375
3307 aload_3
3308 aload 16
3310 ldc #129 <String "">
3312 invokestatic #1220 <Method Rv B(java.io.BufferedOutputStream, Ro, java.lang.String)>
3315 astore 96
3317 aload 96
3319 getfield #1122 <Field java.lang.String a>
3322 astore 84
3324 aload 96
3326 getfield #1089 <Field Rt b>
3329 astore 42
3331 aload 96
3333 getfield #1108 <Field Ru c>
3336 astore 56
3338 goto 433
3341 astore 93
3343 new #835 <Class Eb>
3346 dup
3347 aload 93
3349 ldc #82 <String "closeIn">
3351 ldc #176 <String "java.io.BufferedInputStream">
3353 invokespecial #1259 <Method Eb(java.lang.Exception,java.lang.String,java.lang.String)>
3356 athrow
3357 astore 95
3359 new #835 <Class Eb>
3362 dup
3363 aload 95
3365 ldc #85 <String "closeOut">
3367 ldc #98 <String "java.io.BufferedOutputStream">
3369 invokespecial #1259 <Method Eb(java.lang.Exception,java.lang.String,java.lang.String)>
3372 athrow
3373 astore 91
3375 aload 17
3377 getfield #1164 <Field Rw a>
3380 getfield #1135 <Field java.io.BufferedInputStream a>
3383 astore 92
3385 aload 92
3387 invokevirtual #1234 <Method void close()>
3390 aload 15
3392 getfield #1109 <Field java.io.BufferedOutputStream a>
3395 astore 94
3397 aload 94
3399 invokevirtual #1237 <Method void close()>
3402 aload 91
3404 athrow
3405 iconst_1
3406 istore 66
3408 goto 989
3411 iconst_1
3412 istore 72
3414 goto 1287
3417 ldc #92 <String "yyarg">
3419 astore 76
3421 goto 2363
3424 ldc #96 <String "in continue end">
3426 astore 78
3428 goto 2998
Exception table:
   from   to  target type
  3397  3402  3357   <Class java.io.IOException>
  3385  3390  3341   <Class java.io.IOException>
  3307  3317  3373   <Class java.lang.Exception>
  3289  3294  3249   <Class java.io.IOException>
  3277  3282  3233   <Class java.io.IOException>
  3199  3209  3265   <Class java.lang.Exception>
  3100  3105  3122   <Class java.io.IOException>
  3088  3093  3106   <Class java.io.IOException>
  1323  1327  1574   <Class java.io.IOException>
  1313  1317  1558   <Class java.io.IOException>
  1258  1262  1542   <Class java.io.IOException>
  1228  1232  1526   <Class java.io.IOException>
   837   842   797   <Class java.io.IOException>
   825   830   781   <Class java.io.IOException>
   735   740   861   <Class java.io.IOException>
   723   728   845   <Class java.io.IOException>
   402   412   813   <Class java.lang.Exception>
   285   318  3297   <Class java.lang.Exception>
   247   285  3189   <Class java.lang.Exception>
   237   247   392   <Class java.lang.Exception>
   163   174   376   <Class java.io.IOException>
   152   163   360   <Class java.io.IOException>
    84    95   344   <Class java.io.IOException>
    73    84   328   <Class java.io.IOException>

Method Rt ae(java.io.BufferedOutputStream, Ro, Ro, Ro, Ro, Rx, Ro, Ry, Ro, R3, R4, Ro, Ro, R5, Rt)
   0 goto 276
   3 bipush 25
   5 aload 7
   7 getfield #1115 <Field S a>
  10 dup
  11 astore 15
  13 getfield #1147 <Field int $>
  16 if_icmpeq 387
  19 aload 11
  21 iconst_1
  22 aconst_null
  23 invokestatic #1225 <Method Rc ag(Ro, int, Rc)>
  26 astore 16
  28 bipush 6
  30 aload 7
  32 getfield #1115 <Field S a>
  35 getfield #1147 <Field int $>
  38 if_icmpeq 351
  41 aload 16
  43 invokestatic #1290 <Method Rc ai(Rc)>
  46 astore 17
  48 iconst_2
  49 aload 7
  51 aload 12
  53 new #811 <Class Sa>
  56 dup
  57 aload_0
  58 aload_1
  59 aload_3
  60 aload 4
  62 aload 5
  64 aload 6
  66 aload 7
  68 aload 8
  70 aload 9
  72 invokestatic #1212 <Method S U(java.io.BufferedOutputStream, Ro, Ro, Ro, Rx, Ro, Ry, Ro, R3)>
  75 new #816 <Class Sb>
  78 dup
  79 iconst_0
  80 iconst_4
  81 invokespecial #1329 <Method Sb(int,int)>
  84 iconst_1
  85 invokespecial #1360 <Method Sa(S,S,int)>
  88 invokestatic #1271 <Method S aj(Ro, S)>
  91 astore 20
  93 getfield #1115 <Field S a>
  96 getfield #1147 <Field int $>
  99 if_icmpne 433
 102 iconst_1
 103 istore 18
 105 iload 18
 107 ifeq 439
 110 aload 7
 112 aload_0
 113 aload_3
 114 aload 4
 116 aload 5
 118 aload 6
 120 aload 7
 122 aload 8
 124 aload 6
 126 iconst_2
 127 putfield #1150 <Field int a>
 130 invokestatic #1347 <Method void C(java.io.BufferedOutputStream, Ro, Ro, Rx, Ro, Ry, Ro)>
 133 getfield #1115 <Field S a>
 136 dup
 137 astore 19
 139 aload_0
 140 aload_3
 141 aload 4
 143 aload 5
 145 aload 6
 147 aload 7
 149 aload 8
 151 invokestatic #1347 <Method void C(java.io.BufferedOutputStream, Ro, Ro, Rx, Ro, Ry, Ro)>
 154 getfield #1147 <Field int $>
 157 ifne 343
 160 bipush 22
 162 aload 7
 164 getfield #1115 <Field S a>
 167 getfield #1147 <Field int $>
 170 aload 19
 172 checkcast #798 <Class Sf>
 175 getfield #1104 <Field java.lang.String a>
 178 astore 21
 180 if_icmpne 519
 183 iconst_1
 184 istore 22
 186 iload 22
 188 ifeq 525
 191 new #778 <Class Rt>
 194 dup
 195 new #782 <Class Rs>
 198 dup
 199 aload 17
 201 aload 20
 203 aload 13
 205 new #784 <Class Ru>
 208 dup
 209 aload 13
 211 getfield #1184 <Field Ru a>
 214 dup
 215 astore 23
 217 getfield #1113 <Field F a>
 220 dup
 221 new #771 <Class Rg>
 224 dup
 225 aload 12
 227 getfield #1150 <Field int a>
 230 bipush 10
 232 invokestatic #1341 <Method java.lang.String toString(int, int)>
 235 bipush 45
 237 bipush 126
 239 invokevirtual #1245 <Method java.lang.String replace(char, char)>
 242 dup
 243 astore 25
 245 aload 21
 247 invokespecial #1294 <Method Rg(java.lang.String,java.lang.String)>
 250 aload 25
 252 aload 23
 254 getfield #1193 <Field Rh b>
 257 invokestatic #1285 <Method Rh ak(F, Rg, java.lang.String, Rh)>
 260 invokespecial #1310 <Method Ru(F,Rh)>
 263 putfield #1184 <Field Ru a>
 266 invokespecial #1372 <Method Rs(Rc,S)>
 269 aload 14
 271 invokespecial #1243 <Method Rt(Rs,Rt)>
 274 astore 14
 276 aload 7
 278 aload_0
 279 aload_3
 280 aload 4
 282 aload 5
 284 aload 6
 286 aload 7
 288 aload 8
 290 aload 6
 292 iconst_1
 293 putfield #1150 <Field int a>
 296 invokestatic #1347 <Method void C(java.io.BufferedOutputStream, Ro, Ro, Rx, Ro, Ry, Ro)>
 299 getfield #1115 <Field S a>
 302 getfield #1147 <Field int $>
 305 tableswitch 10 to 14: default=3
	   10: 430
	   11: 3
	   12: 3
	   13: 3
	   14: 340
 340 aload 14
 342 areturn
 343 new #829 <Class Eg>
 346 dup
 347 invokespecial #1365 <Method Eg()>
 350 athrow
 351 aload 16
 353 aload_2
 354 iconst_1
 355 aload_0
 356 aload_3
 357 aload 4
 359 aload 5
 361 aload 6
 363 aload 7
 365 aload 8
 367 aload 6
 369 iconst_1
 370 putfield #1150 <Field int a>
 373 invokestatic #1347 <Method void C(java.io.BufferedOutputStream, Ro, Ro, Rx, Ro, Ry, Ro)>
 376 putfield #1150 <Field int a>
 379 invokestatic #1302 <Method Rc ah(Rc)>
 382 astore 17
 384 goto 48
 387 aload_0
 388 aload 4
 390 aload 10
 392 aload 15
 394 checkcast #792 <Class Sg>
 397 getfield #1137 <Field Rk a>
 400 aconst_null
 401 aload 6
 403 iconst_1
 404 aload_0
 405 aload_3
 406 aload 4
 408 aload 5
 410 aload 6
 412 aload 7
 414 aload 8
 416 invokestatic #1347 <Method void C(java.io.BufferedOutputStream, Ro, Ro, Rx, Ro, Ry, Ro)>
 419 putfield #1150 <Field int a>
 422 invokestatic #1246 <Method Rc af(java.io.BufferedOutputStream, Ro, R4, Rk, Rc)>
 425 astore 16
 427 goto 28
 430 aload 14
 432 areturn
 433 iconst_0
 434 istore 18
 436 goto 105
 439 ldc #131 <String "expected '=>'">
 441 astore 26
 443 new #833 <Class Ee>
 446 dup
 447 aload_0
 448 new #815 <Class Rk>
 451 dup
 452 ldc #17 <String "ml-lex: syntax error, line ">
 454 new #815 <Class Rk>
 457 dup
 458 aload 4
 460 getfield #1150 <Field int a>
 463 bipush 10
 465 invokestatic #1341 <Method java.lang.String toString(int, int)>
 468 bipush 45
 470 bipush 126
 472 invokevirtual #1245 <Method java.lang.String replace(char, char)>
 475 new #815 <Class Rk>
 478 dup
 479 ldc #9 <String ": ">
 481 new #815 <Class Rk>
 484 dup
 485 aload 26
 487 new #815 <Class Rk>
 490 dup
 491 ldc #11 <String "
">
 493 aconst_null
 494 invokespecial #1331 <Method Rk(java.lang.String,Rk)>
 497 invokespecial #1331 <Method Rk(java.lang.String,Rk)>
 500 invokespecial #1331 <Method Rk(java.lang.String,Rk)>
 503 invokespecial #1331 <Method Rk(java.lang.String,Rk)>
 506 invokespecial #1331 <Method Rk(java.lang.String,Rk)>
 509 invokestatic #1286 <Method java.lang.String g(Rk)>
 512 invokestatic #1208 <Method void i(java.io.BufferedOutputStream, java.lang.String)>
 515 invokespecial #1371 <Method Ee()>
 518 athrow
 519 iconst_0
 520 istore 22
 522 goto 186
 525 ldc #133 <String "expected ';'">
 527 astore 26
 529 goto 443

Method Rc af(java.io.BufferedOutputStream, Ro, R4, Rk, Rc)
   0 goto 63
   3 aload_2
   4 getfield #1121 <Field Rm a>
   7 dup
   8 astore 6
  10 getfield #1091 <Field F a>
  13 astore 7
  15 aload 6
  17 getfield #1123 <Field Rf b>
  20 astore 8
  22 aload 5
  24 getfield #1129 <Field Rk b>
  27 astore_3
  28 aload 5
  30 getfield #1142 <Field java.lang.String a>
  33 astore 9
  35 aload 7
  37 aload 8
  39 aload 9
  41 invokestatic #1338 <Method int l(F, Rf, java.lang.String)>
  44 istore 10
  46 new #797 <Class Rc>
  49 dup
  50 iload 10
  52 aconst_null
  53 invokespecial #1256 <Method Rc(int,Rc)>
  56 aload 4
  58 invokestatic #1366 <Method Rc s(Rc, Rc)>
  61 astore 4
  63 aload_3
  64 ifnull 158
  67 aload_3
  68 astore 5
  70 goto 3
  73 pop
  74 new #833 <Class Ee>
  77 dup
  78 aload_0
  79 new #815 <Class Rk>
  82 dup
  83 ldc #182 <String "ml-lex: error, line ">
  85 new #815 <Class Rk>
  88 dup
  89 aload_1
  90 ldc #137 <String "bad state name: ">
  92 aload 9
  94 invokevirtual #1235 <Method java.lang.String concat(java.lang.String)>
  97 astore 12
  99 getfield #1150 <Field int a>
 102 bipush 10
 104 invokestatic #1341 <Method java.lang.String toString(int, int)>
 107 bipush 45
 109 bipush 126
 111 invokevirtual #1245 <Method java.lang.String replace(char, char)>
 114 new #815 <Class Rk>
 117 dup
 118 ldc #9 <String ": ">
 120 new #815 <Class Rk>
 123 dup
 124 aload 12
 126 new #815 <Class Rk>
 129 dup
 130 ldc #11 <String "
">
 132 aconst_null
 133 invokespecial #1331 <Method Rk(java.lang.String,Rk)>
 136 invokespecial #1331 <Method Rk(java.lang.String,Rk)>
 139 invokespecial #1331 <Method Rk(java.lang.String,Rk)>
 142 invokespecial #1331 <Method Rk(java.lang.String,Rk)>
 145 invokespecial #1331 <Method Rk(java.lang.String,Rk)>
 148 invokestatic #1286 <Method java.lang.String g(Rk)>
 151 invokestatic #1208 <Method void i(java.io.BufferedOutputStream, java.lang.String)>
 154 invokespecial #1371 <Method Ee()>
 157 athrow
 158 aload 4
 160 areturn
Exception table:
   from   to  target type
    35    46    73   <Class Ec>

Method Rc ag(Ro, int, Rc)
   0 goto 29
   3 aload_2
   4 areturn
   5 iconst_0
   6 istore_3
   7 iload_3
   8 ifeq 3
  11 new #797 <Class Rc>
  14 dup
  15 iload_1
  16 aconst_null
  17 invokespecial #1256 <Method Rc(int,Rc)>
  20 aload_2
  21 invokestatic #1366 <Method Rc s(Rc, Rc)>
  24 astore_2
  25 iload_1
  26 iconst_2
  27 iadd
  28 istore_1
  29 iload_1
  30 aload_0
  31 getfield #1150 <Field int a>
  34 if_icmpgt 5
  37 iconst_1
  38 istore_3
  39 goto 7

Method Rc ah(Rc)
   0 aload_0
   1 ifnonnull 6
   4 aconst_null
   5 areturn
   6 new #797 <Class Rc>
   9 dup
  10 aload_0
  11 getfield #1189 <Field int a>
  14 iconst_1
  15 iadd
  16 aload_0
  17 getfield #1127 <Field Rc b>
  20 invokestatic #1302 <Method Rc ah(Rc)>
  23 invokespecial #1256 <Method Rc(int,Rc)>
  26 areturn

Method Rc ai(Rc)
   0 aload_0
   1 ifnonnull 6
   4 aconst_null
   5 areturn
   6 new #797 <Class Rc>
   9 dup
  10 aload_0
  11 getfield #1189 <Field int a>
  14 dup
  15 istore_1
  16 new #797 <Class Rc>
  19 dup
  20 iload_1
  21 iconst_1
  22 iadd
  23 aload_0
  24 getfield #1127 <Field Rc b>
  27 invokestatic #1290 <Method Rc ai(Rc)>
  30 invokespecial #1256 <Method Rc(int,Rc)>
  33 invokespecial #1256 <Method Rc(int,Rc)>
  36 areturn

Method S aj(Ro, S)
   0 aload_1
   1 getfield #1147 <Field int $>
   4 tableswitch 0 to 5: default=44
	    0: 180
	    1: 150
	    2: 120
	    3: 100
	    4: 77
	    5: 68
  44 new #816 <Class Sb>
  47 dup
  48 aload_0
  49 aload_0
  50 aload_0
  51 getfield #1150 <Field int a>
  54 iconst_1
  55 iadd
  56 putfield #1150 <Field int a>
  59 getfield #1150 <Field int a>
  62 bipush 6
  64 invokespecial #1329 <Method Sb(int,int)>
  67 areturn
  68 new #770 <Class S>
  71 dup
  72 iconst_5
  73 invokespecial #1362 <Method S(int)>
  76 areturn
  77 new #816 <Class Sb>
  80 dup
  81 aload_0
  82 aload_0
  83 aload_0
  84 getfield #1150 <Field int a>
  87 iconst_1
  88 iadd
  89 putfield #1150 <Field int a>
  92 getfield #1150 <Field int a>
  95 iconst_4
  96 invokespecial #1329 <Method Sb(int,int)>
  99 areturn
 100 new #820 <Class Sd>
 103 dup
 104 aload_0
 105 aload_1
 106 checkcast #820 <Class Sd>
 109 getfield #1178 <Field S a>
 112 invokestatic #1271 <Method S aj(Ro, S)>
 115 iconst_3
 116 invokespecial #1301 <Method Sd(S,int)>
 119 areturn
 120 new #825 <Class Sc>
 123 dup
 124 aload_1
 125 checkcast #825 <Class Sc>
 128 getfield #1096 <Field int a[]>
 131 aload_0
 132 aload_0
 133 aload_0
 134 getfield #1150 <Field int a>
 137 iconst_1
 138 iadd
 139 putfield #1150 <Field int a>
 142 getfield #1150 <Field int a>
 145 iconst_2
 146 invokespecial #1351 <Method Sc(int[],int,int)>
 149 areturn
 150 new #811 <Class Sa>
 153 dup
 154 aload_0
 155 aload_1
 156 checkcast #811 <Class Sa>
 159 dup
 160 astore_2
 161 getfield #1168 <Field S a>
 164 invokestatic #1271 <Method S aj(Ro, S)>
 167 aload_0
 168 aload_2
 169 getfield #1120 <Field S b>
 172 invokestatic #1271 <Method S aj(Ro, S)>
 175 iconst_1
 176 invokespecial #1360 <Method Sa(S,S,int)>
 179 areturn
 180 new #811 <Class Sa>
 183 dup
 184 aload_0
 185 aload_1
 186 checkcast #811 <Class Sa>
 189 dup
 190 astore_3
 191 getfield #1168 <Field S a>
 194 invokestatic #1271 <Method S aj(Ro, S)>
 197 aload_0
 198 aload_3
 199 getfield #1120 <Field S b>
 202 invokestatic #1271 <Method S aj(Ro, S)>
 205 iconst_0
 206 invokespecial #1360 <Method Sa(S,S,int)>
 209 areturn

Method Rh ak(F, Rg, java.lang.String, Rh)
   0 aload_3
   1 ifnonnull 14
   4 new #802 <Class Rh>
   7 dup
   8 aload_1
   9 aconst_null
  10 invokespecial #1239 <Method Rh(Rg,Rh)>
  13 areturn
  14 aload_0
  15 new #771 <Class Rg>
  18 dup
  19 aload_2
  20 aload_3
  21 getfield #1099 <Field Rg a>
  24 dup
  25 astore 5
  27 getfield #1194 <Field java.lang.String a>
  30 dup
  31 astore 6
  33 invokespecial #1294 <Method Rg(java.lang.String,java.lang.String)>
  36 invokevirtual #1266 <Method int d(Rg)>
  39 aload_3
  40 getfield #1105 <Field Rh b>
  43 astore 4
  45 ifne 54
  48 iconst_0
  49 istore 7
  51 goto 70
  54 aload_0
  55 new #771 <Class Rg>
  58 dup
  59 aload 6
  61 aload_2
  62 invokespecial #1294 <Method Rg(java.lang.String,java.lang.String)>
  65 invokevirtual #1266 <Method int d(Rg)>
  68 istore 7
  70 iload 7
  72 ifne 118
  75 aload_0
  76 new #771 <Class Rg>
  79 dup
  80 aload 6
  82 aload_2
  83 invokespecial #1294 <Method Rg(java.lang.String,java.lang.String)>
  86 invokevirtual #1266 <Method int d(Rg)>
  89 ifne 149
  92 iconst_1
  93 istore 8
  95 iload 8
  97 ifne 129
 100 new #802 <Class Rh>
 103 dup
 104 aload 5
 106 aload_0
 107 aload_1
 108 aload_2
 109 aload 4
 111 invokestatic #1285 <Method Rh ak(F, Rg, java.lang.String, Rh)>
 114 invokespecial #1239 <Method Rh(Rg,Rh)>
 117 areturn
 118 new #802 <Class Rh>
 121 dup
 122 aload_1
 123 aload 4
 125 invokespecial #1239 <Method Rh(Rg,Rh)>
 128 areturn
 129 new #802 <Class Rh>
 132 dup
 133 aload_1
 134 new #802 <Class Rh>
 137 dup
 138 aload 5
 140 aload 4
 142 invokespecial #1239 <Method Rh(Rg,Rh)>
 145 invokespecial #1239 <Method Rh(Rg,Rh)>
 148 areturn
 149 iconst_0
 150 istore 8
 152 goto 95

Method void al(java.io.BufferedOutputStream, Ro, Ro, Ro, Ro, Rp, Rp, Ro, Rp, Ro, Ro, Rx, Ro, Ry, Ro, R3, R4, Ro)
   0 goto 43
   3 bipush 13
   5 aload 13
   7 aload_0
   8 aload 4
  10 aload 10
  12 aload 11
  14 aload 12
  16 aload 13
  18 aload 14
  20 invokestatic #1347 <Method void C(java.io.BufferedOutputStream, Ro, Ro, Rx, Ro, Ry, Ro)>
  23 getfield #1115 <Field S a>
  26 dup
  27 astore 19
  29 getfield #1147 <Field int $>
  32 if_icmpeq 204
  35 aload_0
  36 aload 10
  38 ldc #144 <String "expected ID">
  40 invokestatic #1299 <Method void z(java.io.BufferedOutputStream, Ro, java.lang.String)>
  43 aload 13
  45 aload_0
  46 aload 4
  48 aload 10
  50 aload 11
  52 aload 12
  54 aload 13
  56 aload 14
  58 aload 12
  60 iconst_0
  61 putfield #1150 <Field int a>
  64 invokestatic #1347 <Method void C(java.io.BufferedOutputStream, Ro, Ro, Rx, Ro, Ry, Ro)>
  67 getfield #1115 <Field S a>
  70 dup
  71 astore 18
  73 getfield #1147 <Field int $>
  76 tableswitch 1 to 26: default=262
	    1: 707
	    2: 262
	    3: 262
	    4: 262
	    5: 262
	    6: 262
	    7: 262
	    8: 699
	    9: 262
	   10: 262
	   11: 688
	   12: 562
	   13: 400
	   14: 399
	   15: 270
	   16: 262
	   17: 262
	   18: 262
	   19: 196
	   20: 262
	   21: 262
	   22: 262
	   23: 262
	   24: 262
	   25: 262
	   26: 3
 196 aload_3
 197 iconst_1
 198 putfield #1150 <Field int a>
 201 goto 43
 204 aload 7
 206 getfield #1150 <Field int a>
 209 aload 19
 211 checkcast #798 <Class Sf>
 214 astore 20
 216 ifeq 230
 219 aload_0
 220 aload 10
 222 ldc #146 <String "cannot have both %s and %header declarations">
 224 invokestatic #1299 <Method void z(java.io.BufferedOutputStream, Ro, java.lang.String)>
 227 goto 43
 230 aload 9
 232 getfield #1150 <Field int a>
 235 ifeq 249
 238 aload_0
 239 aload 10
 241 ldc #148 <String "duplicate %s declarations">
 243 invokestatic #1299 <Method void z(java.io.BufferedOutputStream, Ro, java.lang.String)>
 246 goto 43
 249 aload 5
 251 aload 20
 253 getfield #1104 <Field java.lang.String a>
 256 putfield #1094 <Field java.lang.String a>
 259 goto 43
 262 new #829 <Class Eg>
 265 dup
 266 invokespecial #1365 <Method Eg()>
 269 athrow
 270 bipush 22
 272 aload 13
 274 aload_0
 275 aload 4
 277 aload 10
 279 aload 11
 281 aload 12
 283 aload 13
 285 aload 14
 287 aload 16
 289 aload 17
 291 aload_0
 292 aload 4
 294 aload 10
 296 aload 11
 298 aload 12
 300 aload 13
 302 aload 14
 304 invokestatic #1347 <Method void C(java.io.BufferedOutputStream, Ro, Ro, Rx, Ro, Ry, Ro)>
 307 invokestatic #1354 <Method void an(java.io.BufferedOutputStream, Ro, Ro, Rx, Ro, Ry, Ro, R4, Ro)>
 310 getfield #1115 <Field S a>
 313 getfield #1147 <Field int $>
 316 if_icmpeq 43
 319 ldc #133 <String "expected ';'">
 321 astore 21
 323 new #833 <Class Ee>
 326 dup
 327 aload_0
 328 new #815 <Class Rk>
 331 dup
 332 ldc #17 <String "ml-lex: syntax error, line ">
 334 new #815 <Class Rk>
 337 dup
 338 aload 10
 340 getfield #1150 <Field int a>
 343 bipush 10
 345 invokestatic #1341 <Method java.lang.String toString(int, int)>
 348 bipush 45
 350 bipush 126
 352 invokevirtual #1245 <Method java.lang.String replace(char, char)>
 355 new #815 <Class Rk>
 358 dup
 359 ldc #9 <String ": ">
 361 new #815 <Class Rk>
 364 dup
 365 aload 21
 367 new #815 <Class Rk>
 370 dup
 371 ldc #11 <String "
">
 373 aconst_null
 374 invokespecial #1331 <Method Rk(java.lang.String,Rk)>
 377 invokespecial #1331 <Method Rk(java.lang.String,Rk)>
 380 invokespecial #1331 <Method Rk(java.lang.String,Rk)>
 383 invokespecial #1331 <Method Rk(java.lang.String,Rk)>
 386 invokespecial #1331 <Method Rk(java.lang.String,Rk)>
 389 invokestatic #1286 <Method java.lang.String g(Rk)>
 392 invokestatic #1208 <Method void i(java.io.BufferedOutputStream, java.lang.String)>
 395 invokespecial #1371 <Method Ee()>
 398 athrow
 399 return
 400 iconst_3
 401 aload 13
 403 aload_0
 404 aload 4
 406 aload 10
 408 aload 11
 410 aload 12
 412 aload 13
 414 aload 14
 416 aload 12
 418 iconst_1
 419 putfield #1150 <Field int a>
 422 invokestatic #1347 <Method void C(java.io.BufferedOutputStream, Ro, Ro, Rx, Ro, Ry, Ro)>
 425 getfield #1115 <Field S a>
 428 aload_0
 429 aload 4
 431 aload 10
 433 aload 11
 435 aload 12
 437 aload 13
 439 aload 14
 441 invokestatic #1347 <Method void C(java.io.BufferedOutputStream, Ro, Ro, Rx, Ro, Ry, Ro)>
 444 getfield #1147 <Field int $>
 447 aload 18
 449 checkcast #798 <Class Sf>
 452 getfield #1104 <Field java.lang.String a>
 455 astore 22
 457 if_icmpne 818
 460 iconst_1
 461 istore 23
 463 iload 23
 465 ifeq 554
 468 bipush 22
 470 aload 13
 472 aload 15
 474 new #766 <Class R2>
 477 dup
 478 aload 15
 480 getfield #1159 <Field R2 a>
 483 dup
 484 astore 24
 486 getfield #1102 <Field F a>
 489 dup
 490 astore 25
 492 aload 22
 494 aload 25
 496 new #819 <Class R0>
 499 dup
 500 aload 22
 502 aload_0
 503 aload_1
 504 aload 4
 506 aload 10
 508 aload 11
 510 aload 12
 512 aload 13
 514 aload 14
 516 aload 15
 518 invokestatic #1212 <Method S U(java.io.BufferedOutputStream, Ro, Ro, Ro, Rx, Ro, Ry, Ro, R3)>
 521 invokespecial #1292 <Method R0(java.lang.String,S)>
 524 aload 24
 526 getfield #1192 <Field R1 b>
 529 invokestatic #1254 <Method R1 am(java.lang.String, F, R0, R1)>
 532 invokespecial #1353 <Method R2(F,R1)>
 535 putfield #1159 <Field R2 a>
 538 getfield #1115 <Field S a>
 541 getfield #1147 <Field int $>
 544 if_icmpeq 43
 547 ldc #133 <String "expected ';'">
 549 astore 21
 551 goto 323
 554 new #829 <Class Eg>
 557 dup
 558 invokespecial #1365 <Method Eg()>
 561 athrow
 562 aload 13
 564 aload_0
 565 aload 4
 567 aload 10
 569 aload 11
 571 aload 12
 573 aload 13
 575 aload 14
 577 aload 12
 579 iconst_2
 580 putfield #1150 <Field int a>
 583 invokestatic #1347 <Method void C(java.io.BufferedOutputStream, Ro, Ro, Rx, Ro, Ry, Ro)>
 586 getfield #1115 <Field S a>
 589 dup
 590 astore 26
 592 aload_0
 593 aload 4
 595 aload 10
 597 aload 11
 599 aload 12
 601 aload 13
 603 aload 14
 605 invokestatic #1347 <Method void C(java.io.BufferedOutputStream, Ro, Ro, Rx, Ro, Ry, Ro)>
 608 getfield #1147 <Field int $>
 611 ifne 662
 614 aload 9
 616 getfield #1150 <Field int a>
 619 aload 26
 621 checkcast #798 <Class Sf>
 624 astore 27
 626 ifne 670
 629 aload 7
 631 getfield #1150 <Field int a>
 634 ifne 679
 637 aload 7
 639 iconst_1
 640 aload 12
 642 iconst_0
 643 aload 6
 645 aload 27
 647 getfield #1104 <Field java.lang.String a>
 650 putfield #1094 <Field java.lang.String a>
 653 putfield #1150 <Field int a>
 656 putfield #1150 <Field int a>
 659 goto 43
 662 new #829 <Class Eg>
 665 dup
 666 invokespecial #1365 <Method Eg()>
 669 athrow
 670 aload_0
 671 aload 10
 673 ldc #146 <String "cannot have both %s and %header declarations">
 675 invokestatic #1299 <Method void z(java.io.BufferedOutputStream, Ro, java.lang.String)>
 678 return
 679 aload_0
 680 aload 10
 682 ldc #151 <String "duplicate %header declarations">
 684 invokestatic #1299 <Method void z(java.io.BufferedOutputStream, Ro, java.lang.String)>
 687 return
 688 aload 4
 690 sipush 256
 693 putfield #1150 <Field int a>
 696 goto 43
 699 aload_2
 700 iconst_1
 701 putfield #1150 <Field int a>
 704 goto 43
 707 aload 13
 709 aload_0
 710 aload 4
 712 aload 10
 714 aload 11
 716 aload 12
 718 aload 13
 720 aload 14
 722 aload 12
 724 iconst_2
 725 putfield #1150 <Field int a>
 728 invokestatic #1347 <Method void C(java.io.BufferedOutputStream, Ro, Ro, Rx, Ro, Ry, Ro)>
 731 getfield #1115 <Field S a>
 734 dup
 735 astore 28
 737 aload_0
 738 aload 4
 740 aload 10
 742 aload 11
 744 aload 12
 746 aload 13
 748 aload 14
 750 invokestatic #1347 <Method void C(java.io.BufferedOutputStream, Ro, Ro, Rx, Ro, Ry, Ro)>
 753 getfield #1147 <Field int $>
 756 ifne 791
 759 aload 8
 761 getfield #1094 <Field java.lang.String a>
 764 aload 28
 766 checkcast #798 <Class Sf>
 769 astore 29
 771 ifnull 799
 774 aload 12
 776 iconst_0
 777 aload_0
 778 aload 10
 780 ldc #154 <String "duplicate %arg declarations">
 782 invokestatic #1299 <Method void z(java.io.BufferedOutputStream, Ro, java.lang.String)>
 785 putfield #1150 <Field int a>
 788 goto 43
 791 new #829 <Class Eg>
 794 dup
 795 invokespecial #1365 <Method Eg()>
 798 athrow
 799 aload 12
 801 iconst_0
 802 aload 8
 804 aload 29
 806 getfield #1104 <Field java.lang.String a>
 809 putfield #1094 <Field java.lang.String a>
 812 putfield #1150 <Field int a>
 815 goto 43
 818 iconst_0
 819 istore 23
 821 goto 463

Method R1 am(java.lang.String, F, R0, R1)
   0 aload_3
   1 ifnonnull 14
   4 new #814 <Class R1>
   7 dup
   8 aload_2
   9 aconst_null
  10 invokespecial #1222 <Method R1(R0,R1)>
  13 areturn
  14 aload_1
  15 new #771 <Class Rg>
  18 dup
  19 aload_0
  20 aload_3
  21 getfield #1172 <Field R0 a>
  24 dup
  25 astore 5
  27 getfield #1146 <Field java.lang.String a>
  30 dup
  31 astore 6
  33 invokespecial #1294 <Method Rg(java.lang.String,java.lang.String)>
  36 invokevirtual #1266 <Method int d(Rg)>
  39 aload_3
  40 getfield #1144 <Field R1 b>
  43 astore 4
  45 ifne 54
  48 iconst_0
  49 istore 7
  51 goto 70
  54 aload_1
  55 new #771 <Class Rg>
  58 dup
  59 aload 6
  61 aload_0
  62 invokespecial #1294 <Method Rg(java.lang.String,java.lang.String)>
  65 invokevirtual #1266 <Method int d(Rg)>
  68 istore 7
  70 iload 7
  72 ifne 118
  75 aload_1
  76 new #771 <Class Rg>
  79 dup
  80 aload 6
  82 aload_0
  83 invokespecial #1294 <Method Rg(java.lang.String,java.lang.String)>
  86 invokevirtual #1266 <Method int d(Rg)>
  89 ifne 149
  92 iconst_1
  93 istore 8
  95 iload 8
  97 ifne 129
 100 new #814 <Class R1>
 103 dup
 104 aload 5
 106 aload_0
 107 aload_1
 108 aload_2
 109 aload 4
 111 invokestatic #1254 <Method R1 am(java.lang.String, F, R0, R1)>
 114 invokespecial #1222 <Method R1(R0,R1)>
 117 areturn
 118 new #814 <Class R1>
 121 dup
 122 aload_2
 123 aload 4
 125 invokespecial #1222 <Method R1(R0,R1)>
 128 areturn
 129 new #814 <Class R1>
 132 dup
 133 aload_2
 134 new #814 <Class R1>
 137 dup
 138 aload 5
 140 aload 4
 142 invokespecial #1222 <Method R1(R0,R1)>
 145 invokespecial #1222 <Method R1(R0,R1)>
 148 areturn
 149 iconst_0
 150 istore 8
 152 goto 95

Method void an(java.io.BufferedOutputStream, Ro, Ro, Rx, Ro, Ry, Ro, R4, Ro)
   0 goto 90
   3 aload_0
   4 aload_1
   5 aload_2
   6 aload_3
   7 aload 4
   9 aload 5
  11 aload 6
  13 aload 8
  15 aload 8
  17 aload 8
  19 aload 7
  21 aload 7
  23 getfield #1121 <Field Rm a>
  26 dup
  27 astore 10
  29 getfield #1091 <Field F a>
  32 aload 10
  34 getfield #1123 <Field Rf b>
  37 new #783 <Class Re>
  40 dup
  41 aload 9
  43 checkcast #798 <Class Sf>
  46 getfield #1104 <Field java.lang.String a>
  49 aload 8
  51 aload 8
  53 aload 8
  55 getfield #1150 <Field int a>
  58 iconst_1
  59 iadd
  60 putfield #1150 <Field int a>
  63 getfield #1150 <Field int a>
  66 invokespecial #1296 <Method Re(java.lang.String,int)>
  69 invokestatic #1260 <Method Rm o(F, Rf, Re)>
  72 putfield #1121 <Field Rm a>
  75 getfield #1150 <Field int a>
  78 iconst_1
  79 iadd
  80 putfield #1150 <Field int a>
  83 getfield #1150 <Field int a>
  86 pop
  87 invokestatic #1347 <Method void C(java.io.BufferedOutputStream, Ro, Ro, Rx, Ro, Ry, Ro)>
  90 bipush 13
  92 aload 5
  94 getfield #1115 <Field S a>
  97 dup
  98 astore 9
 100 getfield #1147 <Field int $>
 103 if_icmpeq 3
 106 return

Method java.lang.String ao(Ro, Rx, Ri)
   0 goto 14
   3 new #801 <Class Ri>
   6 dup
   7 iload 4
   9 aload_2
  10 invokespecial #1238 <Method Ri(char,Ri)>
  13 astore_2
  14 bipush 37
  16 aload_0
  17 aload_1
  18 getfield #1164 <Field Rw a>
  21 dup
  22 astore_3
  23 getfield #1135 <Field java.io.BufferedInputStream a>
  26 aload_3
  27 getfield #1101 <Field Rr b>
  30 invokestatic #1219 <Method char w(Ro, java.io.BufferedInputStream, Rr)>
  33 dup
  34 istore 4
  36 if_icmpne 3
  39 aload_0
  40 aload_1
  41 getfield #1164 <Field Rw a>
  44 dup
  45 astore 5
  47 getfield #1135 <Field java.io.BufferedInputStream a>
  50 aload 5
  52 getfield #1101 <Field Rr b>
  55 invokestatic #1219 <Method char w(Ro, java.io.BufferedInputStream, Rr)>
  58 dup
  59 istore 6
  61 bipush 37
  63 if_icmpne 106
  66 iconst_1
  67 istore 7
  69 iload 7
  71 ifne 97
  74 new #801 <Class Ri>
  77 dup
  78 iload 6
  80 new #801 <Class Ri>
  83 dup
  84 bipush 37
  86 aload_2
  87 invokespecial #1238 <Method Ri(char,Ri)>
  90 invokespecial #1238 <Method Ri(char,Ri)>
  93 astore_2
  94 goto 14
  97 aload_2
  98 aconst_null
  99 invokestatic #1274 <Method Ri c(Ri, Ri)>
 102 invokestatic #1199 <Method java.lang.String h(Ri)>
 105 areturn
 106 iconst_0
 107 istore 7
 109 goto 69

Method S ap(int, S, S[], int)[]
   0 goto 26
   3 aload_2
   4 areturn
   5 iconst_0
   6 istore 4
   8 iload 4
  10 ifne 3
  13 iload_3
  14 istore 5
  16 iload 5
  18 iconst_1
  19 iadd
  20 istore_3
  21 aload_2
  22 iload 5
  24 aload_1
  25 aastore
  26 iload_3
  27 iload_0
  28 if_icmpne 5
  31 iconst_1
  32 istore 4
  34 goto 8

Method void aq(Rc[], S[], R8, Ro, S)
   0 goto 294
   3 aload_3
   4 aload_1
   5 aload 4
   7 checkcast #816 <Class Sb>
  10 getfield #1118 <Field int a>
  13 dup
  14 istore 5
  16 new #816 <Class Sb>
  19 dup
  20 iload 5
  22 bipush 6
  24 invokespecial #1329 <Method Sb(int,int)>
  27 aastore
  28 getfield #1150 <Field int a>
  31 iconst_m1
  32 if_icmpne 42
  35 aload_3
  36 iload 5
  38 putfield #1150 <Field int a>
  41 return
  42 return
  43 aload_3
  44 aload_1
  45 aload 4
  47 checkcast #816 <Class Sb>
  50 getfield #1118 <Field int a>
  53 dup
  54 istore 6
  56 new #816 <Class Sb>
  59 dup
  60 iload 6
  62 iconst_4
  63 invokespecial #1329 <Method Sb(int,int)>
  66 aastore
  67 getfield #1150 <Field int a>
  70 iconst_m1
  71 if_icmpne 341
  74 iconst_0
  75 istore 7
  77 iload 7
  79 ifne 83
  82 return
  83 aload_3
  84 iconst_m1
  85 aload_2
  86 new #821 <Class R7>
  89 dup
  90 new #791 <Class Ra>
  93 dup
  94 aload_3
  95 getfield #1150 <Field int a>
  98 iload 6
 100 invokespecial #1201 <Method Ra(int,int)>
 103 aload_2
 104 getfield #1136 <Field R7 a>
 107 invokespecial #1314 <Method R7(Ra,R7)>
 110 putfield #1136 <Field R7 a>
 113 putfield #1150 <Field int a>
 116 return
 117 aload 4
 119 checkcast #820 <Class Sd>
 122 getfield #1178 <Field S a>
 125 dup
 126 astore 8
 128 aload 8
 130 aload_0
 131 aload_1
 132 aload_2
 133 aload_3
 134 aload 8
 136 invokestatic #1367 <Method void aq(Rc[], S[], R8, Ro, S)>
 139 invokestatic #1251 <Method Rc u(S)>
 142 astore 9
 144 invokestatic #1352 <Method Rc v(S)>
 147 astore 10
 149 goto 178
 152 aload_0
 153 aload 9
 155 getfield #1189 <Field int a>
 158 dup
 159 istore 11
 161 aload_0
 162 iload 11
 164 aaload
 165 aload 10
 167 invokestatic #1366 <Method Rc s(Rc, Rc)>
 170 aastore
 171 aload 9
 173 getfield #1127 <Field Rc b>
 176 astore 9
 178 aload 9
 180 ifnonnull 152
 183 return
 184 aload_1
 185 aload 4
 187 checkcast #825 <Class Sc>
 190 dup
 191 astore 12
 193 getfield #1112 <Field int b>
 196 dup
 197 istore 13
 199 new #825 <Class Sc>
 202 dup
 203 aload 12
 205 getfield #1096 <Field int a[]>
 208 iload 13
 210 iconst_2
 211 invokespecial #1351 <Method Sc(int[],int,int)>
 214 aastore
 215 return
 216 aload 4
 218 checkcast #811 <Class Sa>
 221 dup
 222 astore 14
 224 getfield #1120 <Field S b>
 227 dup
 228 astore 15
 230 aload 14
 232 getfield #1168 <Field S a>
 235 dup
 236 astore 16
 238 aload_0
 239 aload_1
 240 aload_2
 241 aload_3
 242 aload 15
 244 aload_0
 245 aload_1
 246 aload_2
 247 aload_3
 248 aload 16
 250 invokestatic #1367 <Method void aq(Rc[], S[], R8, Ro, S)>
 253 invokestatic #1367 <Method void aq(Rc[], S[], R8, Ro, S)>
 256 invokestatic #1251 <Method Rc u(S)>
 259 astore 9
 261 invokestatic #1352 <Method Rc v(S)>
 264 astore 10
 266 goto 178
 269 aload_0
 270 aload_1
 271 aload_2
 272 aload_3
 273 aload 4
 275 checkcast #811 <Class Sa>
 278 dup
 279 astore 17
 281 getfield #1168 <Field S a>
 284 invokestatic #1367 <Method void aq(Rc[], S[], R8, Ro, S)>
 287 aload 17
 289 getfield #1120 <Field S b>
 292 astore 4
 294 aload 4
 296 getfield #1147 <Field int $>
 299 tableswitch 0 to 6: default=340
	    0: 269
	    1: 216
	    2: 184
	    3: 117
	    4: 43
	    5: 340
	    6: 3
 340 return
 341 iconst_1
 342 istore 7
 344 goto 77

Method void ar(Rc[], S[], R8, Ro, Rt)
   0 goto 25
   3 aload_0
   4 aload_1
   5 aload_2
   6 aload_3
   7 aload 4
   9 getfield #1149 <Field Rs a>
  12 getfield #1180 <Field S b>
  15 invokestatic #1367 <Method void aq(Rc[], S[], R8, Ro, S)>
  18 aload 4
  20 getfield #1166 <Field Rt b>
  23 astore 4
  25 aload 4
  27 ifnonnull 3
  30 return

Method java.lang.String as(Rc)
   0 ldc #129 <String "">
   2 astore_1
   3 goto 37
   6 aload_1
   7 ldc #166 <String " ">
   9 invokevirtual #1235 <Method java.lang.String concat(java.lang.String)>
  12 aload_0
  13 getfield #1189 <Field int a>
  16 bipush 10
  18 invokestatic #1341 <Method java.lang.String toString(int, int)>
  21 bipush 45
  23 bipush 126
  25 invokevirtual #1245 <Method java.lang.String replace(char, char)>
  28 invokevirtual #1235 <Method java.lang.String concat(java.lang.String)>
  31 astore_1
  32 aload_0
  33 getfield #1127 <Field Rc b>
  36 astore_0
  37 aload_0
  38 ifnonnull 6
  41 aload_1
  42 areturn

Method void at(Ro, Ro, R4, R6, R6, R6, Rc[], S[], Rc, int)
   0 aload 4
   2 aload 4
   4 aload 5
   6 aload 5
   8 aload_3
   9 aload_3
  10 aload_0
  11 aload_1
  12 aload_2
  13 aload_3
  14 aload 4
  16 aload 5
  18 aload 6
  20 aload 7
  22 aload 8
  24 invokestatic #1317 <Method Rc av(Ro, Ro, R4, R6, R6, R6, Rc[], S[], Rc)>
  27 astore 10
  29 getfield #1190 <Field Rl a>
  32 dup
  33 astore 11
  35 getfield #1130 <Field F a>
  38 aload 11
  40 getfield #1140 <Field Rd b>
  43 new #797 <Class Rc>
  46 dup
  47 iload 9
  49 aload 7
  51 aload 8
  53 aconst_null
  54 invokestatic #1348 <Method Rc aw(S[], Rc, Rc)>
  57 invokespecial #1256 <Method Rc(int,Rc)>
  60 invokestatic #1264 <Method Rl m(F, Rd, Rc)>
  63 putfield #1190 <Field Rl a>
  66 getfield #1190 <Field Rl a>
  69 dup
  70 astore 12
  72 getfield #1130 <Field F a>
  75 aload 12
  77 getfield #1140 <Field Rd b>
  80 new #797 <Class Rc>
  83 dup
  84 iload 9
  86 aload 7
  88 aload 8
  90 aconst_null
  91 invokestatic #1328 <Method Rc ax(S[], Rc, Rc)>
  94 invokespecial #1256 <Method Rc(int,Rc)>
  97 invokestatic #1264 <Method Rl m(F, Rd, Rc)>
 100 putfield #1190 <Field Rl a>
 103 getfield #1190 <Field Rl a>
 106 dup
 107 astore 13
 109 getfield #1130 <Field F a>
 112 aload 13
 114 getfield #1140 <Field Rd b>
 117 new #797 <Class Rc>
 120 dup
 121 iload 9
 123 aload 10
 125 invokespecial #1256 <Method Rc(int,Rc)>
 128 invokestatic #1264 <Method Rl m(F, Rd, Rc)>
 131 putfield #1190 <Field Rl a>
 134 return

Method int au(Ro, Ro, R4, R6, R6, R6, Rc[], S[], Rc)
   0 aload_2
   1 getfield #1121 <Field Rm a>
   4 dup
   5 astore 9
   7 getfield #1091 <Field F a>
  10 astore 10
  12 aload 9
  14 getfield #1123 <Field Rf b>
  17 astore 11
  19 aload 8
  21 invokestatic #1361 <Method java.lang.String as(Rc)>
  24 astore 15
  26 aload 10
  28 aload 11
  30 aload 15
  32 invokestatic #1338 <Method int l(F, Rf, java.lang.String)>
  35 istore 16
  37 iload 16
  39 ireturn
  40 astore 12
  42 aload 12
  44 instanceof #790 <Class Ec>
  47 ifne 53
  50 aload 12
  52 athrow
  53 aload_1
  54 aload_1
  55 aload_1
  56 getfield #1150 <Field int a>
  59 iconst_1
  60 iadd
  61 putfield #1150 <Field int a>
  64 getfield #1150 <Field int a>
  67 dup
  68 istore 13
  70 aload_0
  71 aload_1
  72 aload_2
  73 aload_3
  74 aload 4
  76 aload 5
  78 aload 6
  80 aload 7
  82 aload 8
  84 iload 13
  86 aload_2
  87 aload_2
  88 getfield #1121 <Field Rm a>
  91 dup
  92 astore 14
  94 getfield #1091 <Field F a>
  97 aload 14
  99 getfield #1123 <Field Rf b>
 102 new #783 <Class Re>
 105 dup
 106 aload 8
 108 invokestatic #1361 <Method java.lang.String as(Rc)>
 111 iload 13
 113 invokespecial #1296 <Method Re(java.lang.String,int)>
 116 invokestatic #1260 <Method Rm o(F, Rf, Re)>
 119 putfield #1121 <Field Rm a>
 122 invokestatic #1273 <Method void at(Ro, Ro, R4, R6, R6, R6, Rc[], S[], Rc, int)>
 125 ireturn
 126 astore 12
 128 goto 42
Exception table:
   from   to  target type
    26    37   126   <Class java.lang.Exception>
    19    26    40   <Class java.lang.Exception>

Method Rc av(Ro, Ro, R4, R6, R6, R6, Rc[], S[], Rc)
   0 aload_0
   1 getfield #1150 <Field int a>
   4 iconst_m1
   5 iadd
   6 istore 9
   8 aconst_null
   9 astore 10
  11 goto 74
  14 new #797 <Class Rc>
  17 dup
  18 aload_0
  19 aload_1
  20 aload_2
  21 aload_3
  22 aload 4
  24 aload 5
  26 aload 6
  28 aload 7
  30 aload 12
  32 invokestatic #1197 <Method int au(Ro, Ro, R4, R6, R6, R6, Rc[], S[], Rc)>
  35 aload 10
  37 invokespecial #1256 <Method Rc(int,Rc)>
  40 astore 10
  42 goto 74
  45 aload 10
  47 areturn
  48 iconst_0
  49 istore 11
  51 goto 82
  54 iconst_0
  55 istore 13
  57 iload 13
  59 ifeq 14
  62 new #797 <Class Rc>
  65 dup
  66 iconst_0
  67 aload 10
  69 invokespecial #1256 <Method Rc(int,Rc)>
  72 astore 10
  74 iload 9
  76 iflt 48
  79 iconst_1
  80 istore 11
  82 iload 11
  84 ifeq 45
  87 aload 6
  89 aload 7
  91 iload 9
  93 aload 8
  95 aconst_null
  96 invokestatic #1226 <Method Rc ay(Rc[], S[], int, Rc, Rc)>
  99 dup
 100 astore 12
 102 iload 9
 104 iconst_m1
 105 iadd
 106 istore 9
 108 ifnonnull 54
 111 iconst_1
 112 istore 13
 114 goto 57

Method Rc aw(S[], Rc, Rc)
   0 goto 13
   3 new #797 <Class Rc>
   6 dup
   7 iload_3
   8 aload_2
   9 invokespecial #1256 <Method Rc(int,Rc)>
  12 astore_2
  13 aload_1
  14 ifnull 40
  17 iconst_4
  18 aload_0
  19 aload_1
  20 getfield #1189 <Field int a>
  23 dup
  24 istore_3
  25 aaload
  26 getfield #1147 <Field int $>
  29 aload_1
  30 getfield #1127 <Field Rc b>
  33 astore_1
  34 if_icmpeq 3
  37 goto 13
  40 aload_2
  41 areturn

Method Rc ax(S[], Rc, Rc)
   0 goto 13
   3 new #797 <Class Rc>
   6 dup
   7 iload_3
   8 aload_2
   9 invokespecial #1256 <Method Rc(int,Rc)>
  12 astore_2
  13 aload_1
  14 ifnull 41
  17 bipush 6
  19 aload_0
  20 aload_1
  21 getfield #1189 <Field int a>
  24 dup
  25 istore_3
  26 aaload
  27 getfield #1147 <Field int $>
  30 aload_1
  31 getfield #1127 <Field Rc b>
  34 astore_1
  35 if_icmpeq 3
  38 goto 13
  41 aload_2
  42 areturn

Method Rc ay(Rc[], S[], int, Rc, Rc)
   0 goto 27
   3 aload 5
   5 checkcast #825 <Class Sc>
   8 getfield #1096 <Field int a[]>
  11 iload_2
  12 iaload
  13 ifeq 58
  16 aload 4
  18 aload_0
  19 iload 6
  21 aaload
  22 invokestatic #1366 <Method Rc s(Rc, Rc)>
  25 astore 4
  27 aload_3
  28 ifnull 83
  31 iconst_2
  32 aload_1
  33 aload_3
  34 getfield #1189 <Field int a>
  37 dup
  38 istore 6
  40 aaload
  41 dup
  42 astore 5
  44 getfield #1147 <Field int $>
  47 aload_3
  48 getfield #1127 <Field Rc b>
  51 astore_3
  52 if_icmpeq 3
  55 goto 27
  58 aload_0
  59 aload_1
  60 iload_2
  61 aload_3
  62 aload 4
  64 invokestatic #1226 <Method Rc ay(Rc[], S[], int, Rc, Rc)>
  67 astore 7
  69 aload 7
  71 areturn
  72 pop
  73 aload_0
  74 aload_1
  75 iload_2
  76 aload_3
  77 aload 4
  79 invokestatic #1226 <Method Rc ay(Rc[], S[], int, Rc, Rc)>
  82 areturn
  83 aload 4
  85 areturn
Exception table:
   from   to  target type
    58    69    72   <Class java.lang.IndexOutOfBoundsException>

Method void az(Rc[], Rc, Rc)
   0 goto 23
   3 aload_0
   4 aload_1
   5 getfield #1189 <Field int a>
   8 dup
   9 istore_3
  10 aload_2
  11 aload_0
  12 iload_3
  13 aaload
  14 invokestatic #1366 <Method Rc s(Rc, Rc)>
  17 aastore
  18 aload_1
  19 getfield #1127 <Field Rc b>
  22 astore_1
  23 aload_1
  24 ifnonnull 3
  27 return

Method void aA(Rc[], Rt)
   0 goto 28
   3 aload_0
   4 aload_1
   5 getfield #1149 <Field Rs a>
   8 dup
   9 astore_2
  10 getfield #1185 <Field Rc a>
  13 aload_2
  14 getfield #1180 <Field S b>
  17 invokestatic #1352 <Method Rc v(S)>
  20 invokestatic #1315 <Method void az(Rc[], Rc, Rc)>
  23 aload_1
  24 getfield #1166 <Field Rt b>
  27 astore_1
  28 aload_1
  29 ifnonnull 3
  32 return

Method R9 aB(Rc[], int, R9)
   0 goto 27
   3 aload_2
   4 areturn
   5 iconst_0
   6 istore_3
   7 iload_3
   8 ifeq 3
  11 new #767 <Class R9>
  14 dup
  15 aload_0
  16 iload_1
  17 aaload
  18 aload_2
  19 invokespecial #1215 <Method R9(Rc,R9)>
  22 astore_2
  23 iload_1
  24 iconst_m1
  25 iadd
  26 istore_1
  27 iload_1
  28 iflt 5
  31 iconst_1
  32 istore_3
  33 goto 7

Method void aC(Ro, Ro, R4, R6, R6, R6, Rc[], S[], R9, int)
   0 goto 38
   3 iload 10
   5 iconst_1
   6 iadd
   7 istore 9
   9 aload_0
  10 aload_1
  11 aload_2
  12 aload_3
  13 aload 4
  15 aload 5
  17 aload 6
  19 aload 7
  21 aload 8
  23 getfield #1176 <Field Rc a>
  26 iload 10
  28 invokestatic #1273 <Method void at(Ro, Ro, R4, R6, R6, R6, Rc[], S[], Rc, int)>
  31 aload 8
  33 getfield #1134 <Field R9 b>
  36 astore 8
  38 aload 8
  40 ifnull 50
  43 iload 9
  45 istore 10
  47 goto 3
  50 return

Method int aD(Rd, int)
   0 goto 12
   3 iload_1
   4 iconst_1
   5 iadd
   6 istore_1
   7 aload_0
   8 getfield #1145 <Field Rd b>
  11 astore_0
  12 aload_0
  13 ifnonnull 3
  16 iload_1
  17 ireturn

Method S aE(R7, int)
   0 iload_1
   1 aload_0
   2 invokestatic #1270 <Method int aF(int, R7)>
   5 ifne 18
   8 new #816 <Class Sb>
  11 dup
  12 iload_1
  13 iconst_1
  14 invokespecial #1329 <Method Sb(int,int)>
  17 areturn
  18 new #816 <Class Sb>
  21 dup
  22 iload_1
  23 iconst_0
  24 invokespecial #1329 <Method Sb(int,int)>
  27 areturn

Method int aF(int, R7)
   0 goto 8
   3 aload_1
   4 getfield #1155 <Field R7 b>
   7 astore_1
   8 aload_1
   9 ifnull 25
  12 aload_1
  13 getfield #1124 <Field Ra a>
  16 getfield #1170 <Field int b>
  19 iload_0
  20 if_icmpne 3
  23 iconst_1
  24 ireturn
  25 iconst_0
  26 ireturn

Method Rj aG(R7, Rc, Rc)
   0 aload_2
   1 ifnonnull 10
   4 aload_1
   5 ifnonnull 143
   8 aconst_null
   9 areturn
  10 aload_1
  11 ifnonnull 43
  14 new #805 <Class Rj>
  17 dup
  18 new #816 <Class Sb>
  21 dup
  22 aload_2
  23 getfield #1189 <Field int a>
  26 iconst_2
  27 invokespecial #1329 <Method Sb(int,int)>
  30 aload_0
  31 aload_2
  32 getfield #1127 <Field Rc b>
  35 aconst_null
  36 invokestatic #1284 <Method Rj aG(R7, Rc, Rc)>
  39 invokespecial #1322 <Method Rj(S,Rj)>
  42 areturn
  43 aload_1
  44 getfield #1189 <Field int a>
  47 dup
  48 istore_3
  49 aload_2
  50 getfield #1189 <Field int a>
  53 dup
  54 istore 4
  56 aload_2
  57 getfield #1127 <Field Rc b>
  60 astore 5
  62 aload_1
  63 getfield #1127 <Field Rc b>
  66 astore 6
  68 if_icmpgt 168
  71 iconst_1
  72 istore 7
  74 iload 7
  76 ifne 113
  79 new #805 <Class Rj>
  82 dup
  83 new #816 <Class Sb>
  86 dup
  87 iload 4
  89 iconst_2
  90 invokespecial #1329 <Method Sb(int,int)>
  93 aload_0
  94 new #797 <Class Rc>
  97 dup
  98 iload_3
  99 aload 6
 101 invokespecial #1256 <Method Rc(int,Rc)>
 104 aload 5
 106 invokestatic #1284 <Method Rj aG(R7, Rc, Rc)>
 109 invokespecial #1322 <Method Rj(S,Rj)>
 112 areturn
 113 new #805 <Class Rj>
 116 dup
 117 aload_0
 118 iload_3
 119 invokestatic #1207 <Method S aE(R7, int)>
 122 aload_0
 123 aload 6
 125 new #797 <Class Rc>
 128 dup
 129 iload 4
 131 aload 5
 133 invokespecial #1256 <Method Rc(int,Rc)>
 136 invokestatic #1284 <Method Rj aG(R7, Rc, Rc)>
 139 invokespecial #1322 <Method Rj(S,Rj)>
 142 areturn
 143 new #805 <Class Rj>
 146 dup
 147 aload_0
 148 aload_1
 149 getfield #1189 <Field int a>
 152 invokestatic #1207 <Method S aE(R7, int)>
 155 aload_0
 156 aload_1
 157 getfield #1127 <Field Rc b>
 160 aconst_null
 161 invokestatic #1284 <Method Rj aG(R7, Rc, Rc)>
 164 invokespecial #1322 <Method Rj(S,Rj)>
 167 areturn
 168 iconst_0
 169 istore 7
 171 goto 74

Method Raa aH(R7, Rd, Raa, Rd)
   0 goto 64
   3 new #793 <Class Raa>
   6 dup
   7 aload_0
   8 aload_3
   9 getfield #1093 <Field Rc a>
  12 dup
  13 astore 4
  15 getfield #1127 <Field Rc b>
  18 new #834 <Class Fa>
  21 dup
  22 aload_0
  23 aconst_null
  24 aload 4
  26 getfield #1189 <Field int a>
  29 aload_1
  30 invokestatic #1340 <Method Rc aI(int, Rd)>
  33 invokestatic #1373 <Method Rc aJ(R7, Rc, Rc)>
  36 astore 5
  38 invokespecial #1268 <Method Fa()>
  41 aconst_null
  42 aload 5
  44 invokestatic #1319 <Method Rc e(F, Rc, Rc)>
  47 invokestatic #1284 <Method Rj aG(R7, Rc, Rc)>
  50 aconst_null
  51 invokestatic #1279 <Method Rj d(Rj, Rj)>
  54 aload_2
  55 invokespecial #1275 <Method Raa(Rj,Raa)>
  58 astore_2
  59 aload_3
  60 getfield #1145 <Field Rd b>
  63 astore_3
  64 aload_3
  65 ifnonnull 3
  68 aconst_null
  69 astore 6
  71 goto 87
  74 aload 6
  76 aload 7
  78 aload 6
  80 getfield #1152 <Field Raa b>
  83 astore_2
  84 putfield #1152 <Field Raa b>
  87 aload_2
  88 ifnull 101
  91 aload_2
  92 aload 6
  94 astore 7
  96 astore 6
  98 goto 74
 101 aload 6
 103 areturn

Method Rc aI(int, Rd)
   0 goto 8
   3 aload_1
   4 getfield #1145 <Field Rd b>
   7 astore_1
   8 aload_1
   9 ifnull 30
  12 iload_0
  13 aload_1
  14 getfield #1093 <Field Rc a>
  17 dup
  18 astore_2
  19 getfield #1189 <Field int a>
  22 if_icmpne 3
  25 aload_2
  26 getfield #1127 <Field Rc b>
  29 areturn
  30 aconst_null
  31 areturn

Method Rc aJ(R7, Rc, Rc)
   0 goto 25
   3 new #797 <Class Rc>
   6 dup
   7 aload_2
   8 getfield #1189 <Field int a>
  11 aload_0
  12 invokestatic #1298 <Method int aK(int, R7)>
  15 aload_1
  16 invokespecial #1256 <Method Rc(int,Rc)>
  19 astore_1
  20 aload_2
  21 getfield #1127 <Field Rc b>
  24 astore_2
  25 aload_2
  26 ifnonnull 3
  29 aconst_null
  30 astore_3
  31 goto 45
  34 aload_3
  35 aload 4
  37 aload_3
  38 getfield #1127 <Field Rc b>
  41 astore_1
  42 putfield #1127 <Field Rc b>
  45 aload_1
  46 ifnull 57
  49 aload_1
  50 aload_3
  51 astore 4
  53 astore_3
  54 goto 34
  57 aload_3
  58 areturn

Method int aK(int, R7)
   0 goto 8
   3 aload_1
   4 getfield #1155 <Field R7 b>
   7 astore_1
   8 aload_1
   9 ifnull 30
  12 aload_1
  13 getfield #1124 <Field Ra a>
  16 dup
  17 astore_2
  18 getfield #1182 <Field int a>
  21 iload_0
  22 if_icmpne 3
  25 aload_2
  26 getfield #1170 <Field int b>
  29 ireturn
  30 new #817 <Class Eh>
  33 dup
  34 invokespecial #1240 <Method Eh()>
  37 athrow

Method Rc aL(int, Rc)
   0 aload_1
   1 ifnonnull 14
   4 new #797 <Class Rc>
   7 dup
   8 iload_0
   9 aconst_null
  10 invokespecial #1256 <Method Rc(int,Rc)>
  13 areturn
  14 iload_0
  15 aload_1
  16 getfield #1189 <Field int a>
  19 dup
  20 istore_2
  21 aload_1
  22 getfield #1127 <Field Rc b>
  25 astore_3
  26 if_icmpgt 69
  29 iconst_1
  30 istore 4
  32 iload 4
  34 ifne 51
  37 new #797 <Class Rc>
  40 dup
  41 iload_2
  42 iload_0
  43 aload_3
  44 invokestatic #1320 <Method Rc aL(int, Rc)>
  47 invokespecial #1256 <Method Rc(int,Rc)>
  50 areturn
  51 new #797 <Class Rc>
  54 dup
  55 iload_0
  56 new #797 <Class Rc>
  59 dup
  60 iload_2
  61 aload_3
  62 invokespecial #1256 <Method Rc(int,Rc)>
  65 invokespecial #1256 <Method Rc(int,Rc)>
  68 areturn
  69 iconst_0
  70 istore 4
  72 goto 32

Method Rk aM(Ro, Rq, Ro, Rd, Rk, Rab)
   0 goto 206
   3 astore 11
   5 aload 11
   7 instanceof #806 <Class Ei>
  10 ifeq 307
  13 aload_0
  14 new #807 <Class Fc>
  17 dup
  18 new #808 <Class Fb>
  21 dup
  22 aload_1
  23 aload_1
  24 aload_2
  25 aload_2
  26 getfield #1150 <Field int a>
  29 iconst_1
  30 iadd
  31 putfield #1150 <Field int a>
  34 getfield #1109 <Field java.io.BufferedOutputStream a>
  37 ldc #40 <String "val ">
  39 invokestatic #1208 <Method void i(java.io.BufferedOutputStream, java.lang.String)>
  42 getfield #1109 <Field java.io.BufferedOutputStream a>
  45 aload 10
  47 invokestatic #1208 <Method void i(java.io.BufferedOutputStream, java.lang.String)>
  50 invokespecial #1233 <Method Fb()>
  53 dup
  54 astore 12
  56 aload_1
  57 putfield #1092 <Field Rq a>
  60 invokespecial #1230 <Method Fc()>
  63 dup
  64 astore 13
  66 aload 12
  68 putfield #1151 <Field F a>
  71 getfield #1150 <Field int a>
  74 ifeq 446
  77 aload_1
  78 aload 9
  80 aload 12
  82 iconst_0
  83 aload_1
  84 getfield #1109 <Field java.io.BufferedOutputStream a>
  87 ldc #44 <String " =
"">
  89 invokestatic #1208 <Method void i(java.io.BufferedOutputStream, java.lang.String)>
  92 invokestatic #1307 <Method void aP(Rc, F, int)>
  95 getfield #1109 <Field java.io.BufferedOutputStream a>
  98 ldc #49 <String ""
">
 100 invokestatic #1208 <Method void i(java.io.BufferedOutputStream, java.lang.String)>
 103 new #810 <Class Rn>
 106 dup
 107 aload 9
 109 aload 10
 111 new #815 <Class Rk>
 114 dup
 115 aload 10
 117 aload 4
 119 invokespecial #1331 <Method Rk(java.lang.String,Rk)>
 122 astore 4
 124 invokespecial #1343 <Method Rn(Rc,java.lang.String)>
 127 aload 5
 129 invokestatic #1318 <Method Rab aQ(Rn, Rab)>
 132 dup
 133 astore 5
 135 ifnull 206
 138 aload 5
 140 getfield #1177 <Field Rab c>
 143 dup
 144 astore 14
 146 ifnull 395
 149 iconst_1
 150 aload 14
 152 getfield #1106 <Field int b>
 155 if_icmpeq 310
 158 aload 5
 160 getfield #1148 <Field Rab d>
 163 dup
 164 astore 15
 166 ifnull 206
 169 iconst_1
 170 aload 15
 172 getfield #1106 <Field int b>
 175 if_icmpne 206
 178 iconst_1
 179 aload 5
 181 getfield #1106 <Field int b>
 184 if_icmpne 206
 187 new #822 <Class Rab>
 190 dup
 191 aload 5
 193 getfield #1114 <Field Rn a>
 196 iconst_0
 197 aload 14
 199 aload 15
 201 invokespecial #1287 <Method Rab(Rn,int,Rab,Rab)>
 204 astore 5
 206 aload_3
 207 ifnull 549
 210 new #810 <Class Rn>
 213 dup
 214 aload_3
 215 getfield #1093 <Field Rc a>
 218 dup
 219 astore 6
 221 getfield #1127 <Field Rc b>
 224 dup
 225 astore 9
 227 ldc #62 <String "s">
 229 aload 6
 231 getfield #1189 <Field int a>
 234 bipush 10
 236 invokestatic #1341 <Method java.lang.String toString(int, int)>
 239 bipush 45
 241 bipush 126
 243 invokevirtual #1245 <Method java.lang.String replace(char, char)>
 246 invokevirtual #1235 <Method java.lang.String concat(java.lang.String)>
 249 dup
 250 astore 10
 252 invokespecial #1343 <Method Rn(Rc,java.lang.String)>
 255 astore 7
 257 aload_3
 258 getfield #1145 <Field Rd b>
 261 astore_3
 262 aload 9
 264 aload 10
 266 aload 7
 268 aload 5
 270 invokestatic #1350 <Method Rn aN(Rc, java.lang.String, Rn, Rab)>
 273 astore 8
 275 new #815 <Class Rk>
 278 dup
 279 aload 8
 281 getfield #1111 <Field java.lang.String b>
 284 aload 4
 286 invokespecial #1331 <Method Rk(java.lang.String,Rk)>
 289 astore 20
 291 aload_0
 292 aload_1
 293 aload_2
 294 aload_3
 295 aload 20
 297 aload 5
 299 invokestatic #1311 <Method Rk aM(Ro, Rq, Ro, Rd, Rk, Rab)>
 302 astore 21
 304 aload 21
 306 areturn
 307 aload 11
 309 athrow
 310 iconst_1
 311 aload 5
 313 getfield #1106 <Field int b>
 316 dup
 317 istore 16
 319 if_icmpeq 370
 322 aload 5
 324 getfield #1148 <Field Rab d>
 327 dup
 328 astore 17
 330 ifnull 206
 333 iconst_1
 334 aload 17
 336 getfield #1106 <Field int b>
 339 if_icmpne 206
 342 iconst_1
 343 iload 16
 345 if_icmpne 206
 348 new #822 <Class Rab>
 351 dup
 352 aload 5
 354 getfield #1114 <Field Rn a>
 357 iconst_0
 358 aload 14
 360 aload 17
 362 invokespecial #1287 <Method Rab(Rn,int,Rab,Rab)>
 365 astore 5
 367 goto 206
 370 new #822 <Class Rab>
 373 dup
 374 aload 5
 376 getfield #1114 <Field Rn a>
 379 iconst_0
 380 aload 14
 382 aload 5
 384 getfield #1148 <Field Rab d>
 387 invokespecial #1287 <Method Rab(Rn,int,Rab,Rab)>
 390 astore 5
 392 goto 206
 395 aload 5
 397 getfield #1148 <Field Rab d>
 400 dup
 401 astore 18
 403 ifnull 206
 406 iconst_1
 407 aload 18
 409 getfield #1106 <Field int b>
 412 if_icmpne 206
 415 iconst_1
 416 aload 5
 418 getfield #1106 <Field int b>
 421 if_icmpne 206
 424 new #822 <Class Rab>
 427 dup
 428 aload 5
 430 getfield #1114 <Field Rn a>
 433 iconst_0
 434 aload 14
 436 aload 18
 438 invokespecial #1287 <Method Rab(Rn,int,Rab,Rab)>
 441 astore 5
 443 goto 206
 446 aload_1
 447 aload 9
 449 aload 13
 451 iconst_0
 452 aload_1
 453 aload_1
 454 aload 9
 456 iconst_0
 457 aload_1
 458 getfield #1109 <Field java.io.BufferedOutputStream a>
 461 ldc #66 <String " = Vector.tabulate(">
 463 invokestatic #1208 <Method void i(java.io.BufferedOutputStream, java.lang.String)>
 466 invokestatic #1214 <Method int aR(Rc, int)>
 469 bipush 10
 471 invokestatic #1341 <Method java.lang.String toString(int, int)>
 474 bipush 45
 476 bipush 126
 478 invokevirtual #1245 <Method java.lang.String replace(char, char)>
 481 astore 19
 483 getfield #1109 <Field java.io.BufferedOutputStream a>
 486 aload 19
 488 invokestatic #1208 <Method void i(java.io.BufferedOutputStream, java.lang.String)>
 491 getfield #1109 <Field java.io.BufferedOutputStream a>
 494 ldc #72 <String ", decode
"">
 496 invokestatic #1208 <Method void i(java.io.BufferedOutputStream, java.lang.String)>
 499 invokestatic #1307 <Method void aP(Rc, F, int)>
 502 getfield #1109 <Field java.io.BufferedOutputStream a>
 505 ldc #75 <String "")
">
 507 invokestatic #1208 <Method void i(java.io.BufferedOutputStream, java.lang.String)>
 510 goto 103
 513 astore 11
 515 goto 5
 518 new #815 <Class Rk>
 521 dup
 522 aload 4
 524 getfield #1142 <Field java.lang.String a>
 527 aload 22
 529 invokespecial #1331 <Method Rk(java.lang.String,Rk)>
 532 astore 22
 534 aload 4
 536 getfield #1129 <Field Rk b>
 539 astore 4
 541 aload 4
 543 ifnonnull 518
 546 aload 22
 548 areturn
 549 aconst_null
 550 astore 22
 552 goto 541
Exception table:
   from   to  target type
   291   304   513   <Class java.lang.Exception>
   262   275     3   <Class java.lang.Exception>

Method Rn aN(Rc, java.lang.String, Rn, Rab)
   0 goto 8
   3 aload_3
   4 getfield #1177 <Field Rab c>
   7 astore_3
   8 aload_3
   9 ifnull 46
  12 aload_3
  13 getfield #1114 <Field Rn a>
  16 dup
  17 astore 4
  19 aload_2
  20 invokestatic #1346 <Method int r(Rn, Rn)>
  23 ifne 3
  26 aload_2
  27 aload 4
  29 invokestatic #1346 <Method int r(Rn, Rn)>
  32 ifeq 43
  35 aload_3
  36 getfield #1148 <Field Rab d>
  39 astore_3
  40 goto 8
  43 aload 4
  45 areturn
  46 new #806 <Class Ei>
  49 dup
  50 aload_0
  51 aload_1
  52 invokespecial #1242 <Method Ei(Rc,java.lang.String)>
  55 athrow

Method java.lang.String aO(java.lang.StringBuffer, java.lang.String, int)
   0 goto 14
   3 iload_2
   4 iconst_m1
   5 iadd
   6 istore_2
   7 aload_0
   8 bipush 48
  10 invokevirtual #1376 <Method java.lang.StringBuffer append(char)>
  13 pop
  14 iload_2
  15 ifne 3
  18 aload_0
  19 aload_0
  20 aload_1
  21 invokevirtual #1332 <Method java.lang.StringBuffer append(java.lang.String)>
  24 pop
  25 invokevirtual #1363 <Method java.lang.String toString()>
  28 areturn

Method void aP(Rc, F, int)
   0 goto 25
   3 aload_1
   4 new #791 <Class Ra>
   7 dup
   8 aload_0
   9 getfield #1189 <Field int a>
  12 iload_2
  13 invokespecial #1201 <Method Ra(int,int)>
  16 invokevirtual #1349 <Method int a(Ra)>
  19 istore_2
  20 aload_0
  21 getfield #1127 <Field Rc b>
  24 astore_0
  25 aload_0
  26 ifnonnull 3
  29 return

Method Rab aQ(Rn, Rab)
   0 aload_1
   1 ifnonnull 16
   4 new #822 <Class Rab>
   7 dup
   8 aload_0
   9 iconst_1
  10 aconst_null
  11 aconst_null
  12 invokespecial #1287 <Method Rab(Rn,int,Rab,Rab)>
  15 areturn
  16 aload_1
  17 getfield #1106 <Field int b>
  20 ifne 72
  23 aload_0
  24 aload_1
  25 getfield #1114 <Field Rn a>
  28 dup
  29 astore 5
  31 invokestatic #1346 <Method int r(Rn, Rn)>
  34 aload_1
  35 getfield #1148 <Field Rab d>
  38 astore 6
  40 aload_1
  41 getfield #1177 <Field Rab c>
  44 astore 7
  46 ifne 151
  49 aload 5
  51 aload_0
  52 invokestatic #1346 <Method int r(Rn, Rn)>
  55 ifne 973
  58 new #822 <Class Rab>
  61 dup
  62 aload_0
  63 iconst_0
  64 aload 7
  66 aload 6
  68 invokespecial #1287 <Method Rab(Rn,int,Rab,Rab)>
  71 areturn
  72 aload_0
  73 aload_1
  74 getfield #1114 <Field Rn a>
  77 dup
  78 astore_2
  79 invokestatic #1346 <Method int r(Rn, Rn)>
  82 aload_1
  83 getfield #1148 <Field Rab d>
  86 astore_3
  87 aload_1
  88 getfield #1177 <Field Rab c>
  91 astore 4
  93 ifne 117
  96 aload_2
  97 aload_0
  98 invokestatic #1346 <Method int r(Rn, Rn)>
 101 ifne 134
 104 new #822 <Class Rab>
 107 dup
 108 aload_0
 109 iconst_1
 110 aload 4
 112 aload_3
 113 invokespecial #1287 <Method Rab(Rn,int,Rab,Rab)>
 116 areturn
 117 new #822 <Class Rab>
 120 dup
 121 aload_2
 122 iconst_1
 123 aload 4
 125 aload_0
 126 aload_3
 127 invokestatic #1318 <Method Rab aQ(Rn, Rab)>
 130 invokespecial #1287 <Method Rab(Rn,int,Rab,Rab)>
 133 areturn
 134 new #822 <Class Rab>
 137 dup
 138 aload_2
 139 iconst_1
 140 aload_0
 141 aload 4
 143 invokestatic #1318 <Method Rab aQ(Rn, Rab)>
 146 aload_3
 147 invokespecial #1287 <Method Rab(Rn,int,Rab,Rab)>
 150 areturn
 151 aload_0
 152 aload 6
 154 invokestatic #1318 <Method Rab aQ(Rn, Rab)>
 157 dup
 158 astore 8
 160 ifnonnull 178
 163 new #822 <Class Rab>
 166 dup
 167 aload 5
 169 iconst_0
 170 aload 7
 172 aload 8
 174 invokespecial #1287 <Method Rab(Rn,int,Rab,Rab)>
 177 areturn
 178 aload 8
 180 getfield #1177 <Field Rab c>
 183 dup
 184 astore 9
 186 ifnonnull 215
 189 aload 8
 191 getfield #1148 <Field Rab d>
 194 dup
 195 astore 20
 197 ifnonnull 802
 200 new #822 <Class Rab>
 203 dup
 204 aload 5
 206 iconst_0
 207 aload 7
 209 aload 8
 211 invokespecial #1287 <Method Rab(Rn,int,Rab,Rab)>
 214 areturn
 215 iconst_1
 216 aload 9
 218 getfield #1106 <Field int b>
 221 if_icmpne 315
 224 iconst_1
 225 aload 8
 227 getfield #1106 <Field int b>
 230 dup
 231 istore 12
 233 if_icmpne 512
 236 aload 7
 238 aload 8
 240 getfield #1148 <Field Rab d>
 243 astore 15
 245 aload 9
 247 getfield #1148 <Field Rab d>
 250 astore 16
 252 aload 9
 254 getfield #1177 <Field Rab c>
 257 astore 17
 259 aload 9
 261 getfield #1114 <Field Rn a>
 264 astore 18
 266 aload 8
 268 getfield #1114 <Field Rn a>
 271 astore 19
 273 ifnonnull 706
 276 new #822 <Class Rab>
 279 dup
 280 aload 18
 282 iconst_0
 283 new #822 <Class Rab>
 286 dup
 287 aload 5
 289 iconst_1
 290 aload 7
 292 aload 17
 294 invokespecial #1287 <Method Rab(Rn,int,Rab,Rab)>
 297 new #822 <Class Rab>
 300 dup
 301 aload 19
 303 iconst_1
 304 aload 16
 306 aload 15
 308 invokespecial #1287 <Method Rab(Rn,int,Rab,Rab)>
 311 invokespecial #1287 <Method Rab(Rn,int,Rab,Rab)>
 314 areturn
 315 aload 8
 317 getfield #1148 <Field Rab d>
 320 dup
 321 astore 10
 323 ifnonnull 341
 326 new #822 <Class Rab>
 329 dup
 330 aload 5
 332 iconst_0
 333 aload 7
 335 aload 8
 337 invokespecial #1287 <Method Rab(Rn,int,Rab,Rab)>
 340 areturn
 341 iconst_1
 342 aload 10
 344 getfield #1106 <Field int b>
 347 if_icmpne 398
 350 iconst_1
 351 aload 8
 353 getfield #1106 <Field int b>
 356 if_icmpne 413
 359 aload 7
 361 aload 8
 363 getfield #1114 <Field Rn a>
 366 astore 11
 368 ifnonnull 428
 371 new #822 <Class Rab>
 374 dup
 375 aload 11
 377 iconst_0
 378 new #822 <Class Rab>
 381 dup
 382 aload 5
 384 iconst_1
 385 aload 7
 387 aload 9
 389 invokespecial #1287 <Method Rab(Rn,int,Rab,Rab)>
 392 aload 10
 394 invokespecial #1287 <Method Rab(Rn,int,Rab,Rab)>
 397 areturn
 398 new #822 <Class Rab>
 401 dup
 402 aload 5
 404 iconst_0
 405 aload 7
 407 aload 8
 409 invokespecial #1287 <Method Rab(Rn,int,Rab,Rab)>
 412 areturn
 413 new #822 <Class Rab>
 416 dup
 417 aload 5
 419 iconst_0
 420 aload 7
 422 aload 8
 424 invokespecial #1287 <Method Rab(Rn,int,Rab,Rab)>
 427 areturn
 428 iconst_1
 429 aload 7
 431 getfield #1106 <Field int b>
 434 if_icmpne 485
 437 new #822 <Class Rab>
 440 dup
 441 aload 5
 443 iconst_1
 444 new #822 <Class Rab>
 447 dup
 448 aload 7
 450 getfield #1114 <Field Rn a>
 453 iconst_0
 454 aload 7
 456 getfield #1177 <Field Rab c>
 459 aload 7
 461 getfield #1148 <Field Rab d>
 464 invokespecial #1287 <Method Rab(Rn,int,Rab,Rab)>
 467 new #822 <Class Rab>
 470 dup
 471 aload 11
 473 iconst_0
 474 aload 9
 476 aload 10
 478 invokespecial #1287 <Method Rab(Rn,int,Rab,Rab)>
 481 invokespecial #1287 <Method Rab(Rn,int,Rab,Rab)>
 484 areturn
 485 new #822 <Class Rab>
 488 dup
 489 aload 11
 491 iconst_0
 492 new #822 <Class Rab>
 495 dup
 496 aload 5
 498 iconst_1
 499 aload 7
 501 aload 9
 503 invokespecial #1287 <Method Rab(Rn,int,Rab,Rab)>
 506 aload 10
 508 invokespecial #1287 <Method Rab(Rn,int,Rab,Rab)>
 511 areturn
 512 aload 8
 514 getfield #1148 <Field Rab d>
 517 dup
 518 astore 13
 520 ifnonnull 538
 523 new #822 <Class Rab>
 526 dup
 527 aload 5
 529 iconst_0
 530 aload 7
 532 aload 8
 534 invokespecial #1287 <Method Rab(Rn,int,Rab,Rab)>
 537 areturn
 538 iconst_1
 539 aload 13
 541 getfield #1106 <Field int b>
 544 if_icmpne 592
 547 iconst_1
 548 iload 12
 550 if_icmpne 607
 553 aload 7
 555 aload 8
 557 getfield #1114 <Field Rn a>
 560 astore 14
 562 ifnonnull 622
 565 new #822 <Class Rab>
 568 dup
 569 aload 14
 571 iconst_0
 572 new #822 <Class Rab>
 575 dup
 576 aload 5
 578 iconst_1
 579 aload 7
 581 aload 9
 583 invokespecial #1287 <Method Rab(Rn,int,Rab,Rab)>
 586 aload 13
 588 invokespecial #1287 <Method Rab(Rn,int,Rab,Rab)>
 591 areturn
 592 new #822 <Class Rab>
 595 dup
 596 aload 5
 598 iconst_0
 599 aload 7
 601 aload 8
 603 invokespecial #1287 <Method Rab(Rn,int,Rab,Rab)>
 606 areturn
 607 new #822 <Class Rab>
 610 dup
 611 aload 5
 613 iconst_0
 614 aload 7
 616 aload 8
 618 invokespecial #1287 <Method Rab(Rn,int,Rab,Rab)>
 621 areturn
 622 iconst_1
 623 aload 7
 625 getfield #1106 <Field int b>
 628 if_icmpne 679
 631 new #822 <Class Rab>
 634 dup
 635 aload 5
 637 iconst_1
 638 new #822 <Class Rab>
 641 dup
 642 aload 7
 644 getfield #1114 <Field Rn a>
 647 iconst_0
 648 aload 7
 650 getfield #1177 <Field Rab c>
 653 aload 7
 655 getfield #1148 <Field Rab d>
 658 invokespecial #1287 <Method Rab(Rn,int,Rab,Rab)>
 661 new #822 <Class Rab>
 664 dup
 665 aload 14
 667 iconst_0
 668 aload 9
 670 aload 13
 672 invokespecial #1287 <Method Rab(Rn,int,Rab,Rab)>
 675 invokespecial #1287 <Method Rab(Rn,int,Rab,Rab)>
 678 areturn
 679 new #822 <Class Rab>
 682 dup
 683 aload 14
 685 iconst_0
 686 new #822 <Class Rab>
 689 dup
 690 aload 5
 692 iconst_1
 693 aload 7
 695 aload 9
 697 invokespecial #1287 <Method Rab(Rn,int,Rab,Rab)>
 700 aload 13
 702 invokespecial #1287 <Method Rab(Rn,int,Rab,Rab)>
 705 areturn
 706 iconst_1
 707 aload 7
 709 getfield #1106 <Field int b>
 712 if_icmpne 763
 715 new #822 <Class Rab>
 718 dup
 719 aload 5
 721 iconst_1
 722 new #822 <Class Rab>
 725 dup
 726 aload 7
 728 getfield #1114 <Field Rn a>
 731 iconst_0
 732 aload 7
 734 getfield #1177 <Field Rab c>
 737 aload 7
 739 getfield #1148 <Field Rab d>
 742 invokespecial #1287 <Method Rab(Rn,int,Rab,Rab)>
 745 new #822 <Class Rab>
 748 dup
 749 aload 19
 751 iconst_0
 752 aload 9
 754 aload 15
 756 invokespecial #1287 <Method Rab(Rn,int,Rab,Rab)>
 759 invokespecial #1287 <Method Rab(Rn,int,Rab,Rab)>
 762 areturn
 763 new #822 <Class Rab>
 766 dup
 767 aload 18
 769 iconst_0
 770 new #822 <Class Rab>
 773 dup
 774 aload 5
 776 iconst_1
 777 aload 7
 779 aload 17
 781 invokespecial #1287 <Method Rab(Rn,int,Rab,Rab)>
 784 new #822 <Class Rab>
 787 dup
 788 aload 19
 790 iconst_1
 791 aload 16
 793 aload 15
 795 invokespecial #1287 <Method Rab(Rn,int,Rab,Rab)>
 798 invokespecial #1287 <Method Rab(Rn,int,Rab,Rab)>
 801 areturn
 802 iconst_1
 803 aload 20
 805 getfield #1106 <Field int b>
 808 if_icmpne 859
 811 iconst_1
 812 aload 8
 814 getfield #1106 <Field int b>
 817 if_icmpne 874
 820 aload 7
 822 aload 8
 824 getfield #1114 <Field Rn a>
 827 astore 21
 829 ifnonnull 889
 832 new #822 <Class Rab>
 835 dup
 836 aload 21
 838 iconst_0
 839 new #822 <Class Rab>
 842 dup
 843 aload 5
 845 iconst_1
 846 aload 7
 848 aload 9
 850 invokespecial #1287 <Method Rab(Rn,int,Rab,Rab)>
 853 aload 20
 855 invokespecial #1287 <Method Rab(Rn,int,Rab,Rab)>
 858 areturn
 859 new #822 <Class Rab>
 862 dup
 863 aload 5
 865 iconst_0
 866 aload 7
 868 aload 8
 870 invokespecial #1287 <Method Rab(Rn,int,Rab,Rab)>
 873 areturn
 874 new #822 <Class Rab>
 877 dup
 878 aload 5
 880 iconst_0
 881 aload 7
 883 aload 8
 885 invokespecial #1287 <Method Rab(Rn,int,Rab,Rab)>
 888 areturn
 889 iconst_1
 890 aload 7
 892 getfield #1106 <Field int b>
 895 if_icmpne 946
 898 new #822 <Class Rab>
 901 dup
 902 aload 5
 904 iconst_1
 905 new #822 <Class Rab>
 908 dup
 909 aload 7
 911 getfield #1114 <Field Rn a>
 914 iconst_0
 915 aload 7
 917 getfield #1177 <Field Rab c>
 920 aload 7
 922 getfield #1148 <Field Rab d>
 925 invokespecial #1287 <Method Rab(Rn,int,Rab,Rab)>
 928 new #822 <Class Rab>
 931 dup
 932 aload 21
 934 iconst_0
 935 aload 9
 937 aload 20
 939 invokespecial #1287 <Method Rab(Rn,int,Rab,Rab)>
 942 invokespecial #1287 <Method Rab(Rn,int,Rab,Rab)>
 945 areturn
 946 new #822 <Class Rab>
 949 dup
 950 aload 21
 952 iconst_0
 953 new #822 <Class Rab>
 956 dup
 957 aload 5
 959 iconst_1
 960 aload 7
 962 aload 9
 964 invokespecial #1287 <Method Rab(Rn,int,Rab,Rab)>
 967 aload 20
 969 invokespecial #1287 <Method Rab(Rn,int,Rab,Rab)>
 972 areturn
 973 aload_0
 974 aload 7
 976 invokestatic #1318 <Method Rab aQ(Rn, Rab)>
 979 dup
 980 astore 22
 982 ifnonnull 1000
 985 new #822 <Class Rab>
 988 dup
 989 aload 5
 991 iconst_0
 992 aload 22
 994 aload 6
 996 invokespecial #1287 <Method Rab(Rn,int,Rab,Rab)>
 999 areturn
1000 aload 22
1002 getfield #1177 <Field Rab c>
1005 dup
1006 astore 23
1008 ifnonnull 1037
1011 aload 22
1013 getfield #1148 <Field Rab d>
1016 dup
1017 astore 43
1019 ifnonnull 2102
1022 new #822 <Class Rab>
1025 dup
1026 aload 5
1028 iconst_0
1029 aload 22
1031 aload 6
1033 invokespecial #1287 <Method Rab(Rn,int,Rab,Rab)>
1036 areturn
1037 iconst_1
1038 aload 23
1040 getfield #1106 <Field int b>
1043 if_icmpne 1108
1046 iconst_1
1047 aload 22
1049 getfield #1106 <Field int b>
1052 dup
1053 istore 29
1055 if_icmpne 1350
1058 aload 22
1060 getfield #1148 <Field Rab d>
1063 dup
1064 astore 35
1066 ifnonnull 1589
1069 aload 6
1071 aload 22
1073 getfield #1114 <Field Rn a>
1076 astore 42
1078 ifnonnull 2018
1081 new #822 <Class Rab>
1084 dup
1085 aload 42
1087 iconst_0
1088 aload 23
1090 new #822 <Class Rab>
1093 dup
1094 aload 5
1096 iconst_1
1097 aload 35
1099 aload 6
1101 invokespecial #1287 <Method Rab(Rn,int,Rab,Rab)>
1104 invokespecial #1287 <Method Rab(Rn,int,Rab,Rab)>
1107 areturn
1108 aload 22
1110 getfield #1148 <Field Rab d>
1113 dup
1114 astore 24
1116 ifnonnull 1134
1119 new #822 <Class Rab>
1122 dup
1123 aload 5
1125 iconst_0
1126 aload 22
1128 aload 6
1130 invokespecial #1287 <Method Rab(Rn,int,Rab,Rab)>
1133 areturn
1134 iconst_1
1135 aload 24
1137 getfield #1106 <Field int b>
1140 if_icmpne 1224
1143 iconst_1
1144 aload 22
1146 getfield #1106 <Field int b>
1149 if_icmpne 1239
1152 aload 6
1154 aload 24
1156 getfield #1148 <Field Rab d>
1159 astore 25
1161 aload 24
1163 getfield #1177 <Field Rab c>
1166 astore 26
1168 aload 24
1170 getfield #1114 <Field Rn a>
1173 astore 27
1175 aload 22
1177 getfield #1114 <Field Rn a>
1180 astore 28
1182 ifnonnull 1254
1185 new #822 <Class Rab>
1188 dup
1189 aload 27
1191 iconst_0
1192 new #822 <Class Rab>
1195 dup
1196 aload 28
1198 iconst_1
1199 aload 23
1201 aload 26
1203 invokespecial #1287 <Method Rab(Rn,int,Rab,Rab)>
1206 new #822 <Class Rab>
1209 dup
1210 aload 5
1212 iconst_1
1213 aload 25
1215 aload 6
1217 invokespecial #1287 <Method Rab(Rn,int,Rab,Rab)>
1220 invokespecial #1287 <Method Rab(Rn,int,Rab,Rab)>
1223 areturn
1224 new #822 <Class Rab>
1227 dup
1228 aload 5
1230 iconst_0
1231 aload 22
1233 aload 6
1235 invokespecial #1287 <Method Rab(Rn,int,Rab,Rab)>
1238 areturn
1239 new #822 <Class Rab>
1242 dup
1243 aload 5
1245 iconst_0
1246 aload 22
1248 aload 6
1250 invokespecial #1287 <Method Rab(Rn,int,Rab,Rab)>
1253 areturn
1254 iconst_1
1255 aload 6
1257 getfield #1106 <Field int b>
1260 if_icmpne 1311
1263 new #822 <Class Rab>
1266 dup
1267 aload 5
1269 iconst_1
1270 new #822 <Class Rab>
1273 dup
1274 aload 28
1276 iconst_0
1277 aload 23
1279 aload 24
1281 invokespecial #1287 <Method Rab(Rn,int,Rab,Rab)>
1284 new #822 <Class Rab>
1287 dup
1288 aload 6
1290 getfield #1114 <Field Rn a>
1293 iconst_0
1294 aload 6
1296 getfield #1177 <Field Rab c>
1299 aload 6
1301 getfield #1148 <Field Rab d>
1304 invokespecial #1287 <Method Rab(Rn,int,Rab,Rab)>
1307 invokespecial #1287 <Method Rab(Rn,int,Rab,Rab)>
1310 areturn
1311 new #822 <Class Rab>
1314 dup
1315 aload 27
1317 iconst_0
1318 new #822 <Class Rab>
1321 dup
1322 aload 28
1324 iconst_1
1325 aload 23
1327 aload 26
1329 invokespecial #1287 <Method Rab(Rn,int,Rab,Rab)>
1332 new #822 <Class Rab>
1335 dup
1336 aload 5
1338 iconst_1
1339 aload 25
1341 aload 6
1343 invokespecial #1287 <Method Rab(Rn,int,Rab,Rab)>
1346 invokespecial #1287 <Method Rab(Rn,int,Rab,Rab)>
1349 areturn
1350 aload 22
1352 getfield #1148 <Field Rab d>
1355 dup
1356 astore 30
1358 ifnonnull 1376
1361 new #822 <Class Rab>
1364 dup
1365 aload 5
1367 iconst_0
1368 aload 22
1370 aload 6
1372 invokespecial #1287 <Method Rab(Rn,int,Rab,Rab)>
1375 areturn
1376 iconst_1
1377 aload 30
1379 getfield #1106 <Field int b>
1382 if_icmpne 1463
1385 iconst_1
1386 iload 29
1388 if_icmpne 1478
1391 aload 6
1393 aload 30
1395 getfield #1148 <Field Rab d>
1398 astore 31
1400 aload 30
1402 getfield #1177 <Field Rab c>
1405 astore 32
1407 aload 30
1409 getfield #1114 <Field Rn a>
1412 astore 33
1414 aload 22
1416 getfield #1114 <Field Rn a>
1419 astore 34
1421 ifnonnull 1493
1424 new #822 <Class Rab>
1427 dup
1428 aload 33
1430 iconst_0
1431 new #822 <Class Rab>
1434 dup
1435 aload 34
1437 iconst_1
1438 aload 23
1440 aload 32
1442 invokespecial #1287 <Method Rab(Rn,int,Rab,Rab)>
1445 new #822 <Class Rab>
1448 dup
1449 aload 5
1451 iconst_1
1452 aload 31
1454 aload 6
1456 invokespecial #1287 <Method Rab(Rn,int,Rab,Rab)>
1459 invokespecial #1287 <Method Rab(Rn,int,Rab,Rab)>
1462 areturn
1463 new #822 <Class Rab>
1466 dup
1467 aload 5
1469 iconst_0
1470 aload 22
1472 aload 6
1474 invokespecial #1287 <Method Rab(Rn,int,Rab,Rab)>
1477 areturn
1478 new #822 <Class Rab>
1481 dup
1482 aload 5
1484 iconst_0
1485 aload 22
1487 aload 6
1489 invokespecial #1287 <Method Rab(Rn,int,Rab,Rab)>
1492 areturn
1493 iconst_1
1494 aload 6
1496 getfield #1106 <Field int b>
1499 if_icmpne 1550
1502 new #822 <Class Rab>
1505 dup
1506 aload 5
1508 iconst_1
1509 new #822 <Class Rab>
1512 dup
1513 aload 34
1515 iconst_0
1516 aload 23
1518 aload 30
1520 invokespecial #1287 <Method Rab(Rn,int,Rab,Rab)>
1523 new #822 <Class Rab>
1526 dup
1527 aload 6
1529 getfield #1114 <Field Rn a>
1532 iconst_0
1533 aload 6
1535 getfield #1177 <Field Rab c>
1538 aload 6
1540 getfield #1148 <Field Rab d>
1543 invokespecial #1287 <Method Rab(Rn,int,Rab,Rab)>
1546 invokespecial #1287 <Method Rab(Rn,int,Rab,Rab)>
1549 areturn
1550 new #822 <Class Rab>
1553 dup
1554 aload 33
1556 iconst_0
1557 new #822 <Class Rab>
1560 dup
1561 aload 34
1563 iconst_1
1564 aload 23
1566 aload 32
1568 invokespecial #1287 <Method Rab(Rn,int,Rab,Rab)>
1571 new #822 <Class Rab>
1574 dup
1575 aload 5
1577 iconst_1
1578 aload 31
1580 aload 6
1582 invokespecial #1287 <Method Rab(Rn,int,Rab,Rab)>
1585 invokespecial #1287 <Method Rab(Rn,int,Rab,Rab)>
1588 areturn
1589 iconst_1
1590 aload 35
1592 getfield #1106 <Field int b>
1595 if_icmpne 1676
1598 iconst_1
1599 iload 29
1601 if_icmpne 1799
1604 aload 6
1606 aload 35
1608 getfield #1148 <Field Rab d>
1611 astore 38
1613 aload 35
1615 getfield #1177 <Field Rab c>
1618 astore 39
1620 aload 35
1622 getfield #1114 <Field Rn a>
1625 astore 40
1627 aload 22
1629 getfield #1114 <Field Rn a>
1632 astore 41
1634 ifnonnull 1922
1637 new #822 <Class Rab>
1640 dup
1641 aload 40
1643 iconst_0
1644 new #822 <Class Rab>
1647 dup
1648 aload 41
1650 iconst_1
1651 aload 23
1653 aload 39
1655 invokespecial #1287 <Method Rab(Rn,int,Rab,Rab)>
1658 new #822 <Class Rab>
1661 dup
1662 aload 5
1664 iconst_1
1665 aload 38
1667 aload 6
1669 invokespecial #1287 <Method Rab(Rn,int,Rab,Rab)>
1672 invokespecial #1287 <Method Rab(Rn,int,Rab,Rab)>
1675 areturn
1676 aload 6
1678 aload 22
1680 getfield #1114 <Field Rn a>
1683 astore 36
1685 ifnonnull 1715
1688 new #822 <Class Rab>
1691 dup
1692 aload 36
1694 iconst_0
1695 aload 23
1697 new #822 <Class Rab>
1700 dup
1701 aload 5
1703 iconst_1
1704 aload 35
1706 aload 6
1708 invokespecial #1287 <Method Rab(Rn,int,Rab,Rab)>
1711 invokespecial #1287 <Method Rab(Rn,int,Rab,Rab)>
1714 areturn
1715 iconst_1
1716 aload 6
1718 getfield #1106 <Field int b>
1721 if_icmpne 1772
1724 new #822 <Class Rab>
1727 dup
1728 aload 5
1730 iconst_1
1731 new #822 <Class Rab>
1734 dup
1735 aload 36
1737 iconst_0
1738 aload 23
1740 aload 35
1742 invokespecial #1287 <Method Rab(Rn,int,Rab,Rab)>
1745 new #822 <Class Rab>
1748 dup
1749 aload 6
1751 getfield #1114 <Field Rn a>
1754 iconst_0
1755 aload 6
1757 getfield #1177 <Field Rab c>
1760 aload 6
1762 getfield #1148 <Field Rab d>
1765 invokespecial #1287 <Method Rab(Rn,int,Rab,Rab)>
1768 invokespecial #1287 <Method Rab(Rn,int,Rab,Rab)>
1771 areturn
1772 new #822 <Class Rab>
1775 dup
1776 aload 36
1778 iconst_0
1779 aload 23
1781 new #822 <Class Rab>
1784 dup
1785 aload 5
1787 iconst_1
1788 aload 35
1790 aload 6
1792 invokespecial #1287 <Method Rab(Rn,int,Rab,Rab)>
1795 invokespecial #1287 <Method Rab(Rn,int,Rab,Rab)>
1798 areturn
1799 aload 6
1801 aload 22
1803 getfield #1114 <Field Rn a>
1806 astore 37
1808 ifnonnull 1838
1811 new #822 <Class Rab>
1814 dup
1815 aload 37
1817 iconst_0
1818 aload 23
1820 new #822 <Class Rab>
1823 dup
1824 aload 5
1826 iconst_1
1827 aload 35
1829 aload 6
1831 invokespecial #1287 <Method Rab(Rn,int,Rab,Rab)>
1834 invokespecial #1287 <Method Rab(Rn,int,Rab,Rab)>
1837 areturn
1838 iconst_1
1839 aload 6
1841 getfield #1106 <Field int b>
1844 if_icmpne 1895
1847 new #822 <Class Rab>
1850 dup
1851 aload 5
1853 iconst_1
1854 new #822 <Class Rab>
1857 dup
1858 aload 37
1860 iconst_0
1861 aload 23
1863 aload 35
1865 invokespecial #1287 <Method Rab(Rn,int,Rab,Rab)>
1868 new #822 <Class Rab>
1871 dup
1872 aload 6
1874 getfield #1114 <Field Rn a>
1877 iconst_0
1878 aload 6
1880 getfield #1177 <Field Rab c>
1883 aload 6
1885 getfield #1148 <Field Rab d>
1888 invokespecial #1287 <Method Rab(Rn,int,Rab,Rab)>
1891 invokespecial #1287 <Method Rab(Rn,int,Rab,Rab)>
1894 areturn
1895 new #822 <Class Rab>
1898 dup
1899 aload 37
1901 iconst_0
1902 aload 23
1904 new #822 <Class Rab>
1907 dup
1908 aload 5
1910 iconst_1
1911 aload 35
1913 aload 6
1915 invokespecial #1287 <Method Rab(Rn,int,Rab,Rab)>
1918 invokespecial #1287 <Method Rab(Rn,int,Rab,Rab)>
1921 areturn
1922 iconst_1
1923 aload 6
1925 getfield #1106 <Field int b>
1928 if_icmpne 1979
1931 new #822 <Class Rab>
1934 dup
1935 aload 5
1937 iconst_1
1938 new #822 <Class Rab>
1941 dup
1942 aload 41
1944 iconst_0
1945 aload 23
1947 aload 35
1949 invokespecial #1287 <Method Rab(Rn,int,Rab,Rab)>
1952 new #822 <Class Rab>
1955 dup
1956 aload 6
1958 getfield #1114 <Field Rn a>
1961 iconst_0
1962 aload 6
1964 getfield #1177 <Field Rab c>
1967 aload 6
1969 getfield #1148 <Field Rab d>
1972 invokespecial #1287 <Method Rab(Rn,int,Rab,Rab)>
1975 invokespecial #1287 <Method Rab(Rn,int,Rab,Rab)>
1978 areturn
1979 new #822 <Class Rab>
1982 dup
1983 aload 40
1985 iconst_0
1986 new #822 <Class Rab>
1989 dup
1990 aload 41
1992 iconst_1
1993 aload 23
1995 aload 39
1997 invokespecial #1287 <Method Rab(Rn,int,Rab,Rab)>
2000 new #822 <Class Rab>
2003 dup
2004 aload 5
2006 iconst_1
2007 aload 38
2009 aload 6
2011 invokespecial #1287 <Method Rab(Rn,int,Rab,Rab)>
2014 invokespecial #1287 <Method Rab(Rn,int,Rab,Rab)>
2017 areturn
2018 iconst_1
2019 aload 6
2021 getfield #1106 <Field int b>
2024 if_icmpne 2075
2027 new #822 <Class Rab>
2030 dup
2031 aload 5
2033 iconst_1
2034 new #822 <Class Rab>
2037 dup
2038 aload 42
2040 iconst_0
2041 aload 23
2043 aload 35
2045 invokespecial #1287 <Method Rab(Rn,int,Rab,Rab)>
2048 new #822 <Class Rab>
2051 dup
2052 aload 6
2054 getfield #1114 <Field Rn a>
2057 iconst_0
2058 aload 6
2060 getfield #1177 <Field Rab c>
2063 aload 6
2065 getfield #1148 <Field Rab d>
2068 invokespecial #1287 <Method Rab(Rn,int,Rab,Rab)>
2071 invokespecial #1287 <Method Rab(Rn,int,Rab,Rab)>
2074 areturn
2075 new #822 <Class Rab>
2078 dup
2079 aload 42
2081 iconst_0
2082 aload 23
2084 new #822 <Class Rab>
2087 dup
2088 aload 5
2090 iconst_1
2091 aload 35
2093 aload 6
2095 invokespecial #1287 <Method Rab(Rn,int,Rab,Rab)>
2098 invokespecial #1287 <Method Rab(Rn,int,Rab,Rab)>
2101 areturn
2102 iconst_1
2103 aload 43
2105 getfield #1106 <Field int b>
2108 if_icmpne 2192
2111 iconst_1
2112 aload 22
2114 getfield #1106 <Field int b>
2117 if_icmpne 2207
2120 aload 6
2122 aload 43
2124 getfield #1148 <Field Rab d>
2127 astore 44
2129 aload 43
2131 getfield #1177 <Field Rab c>
2134 astore 45
2136 aload 43
2138 getfield #1114 <Field Rn a>
2141 astore 46
2143 aload 22
2145 getfield #1114 <Field Rn a>
2148 astore 47
2150 ifnonnull 2222
2153 new #822 <Class Rab>
2156 dup
2157 aload 46
2159 iconst_0
2160 new #822 <Class Rab>
2163 dup
2164 aload 47
2166 iconst_1
2167 aload 23
2169 aload 45
2171 invokespecial #1287 <Method Rab(Rn,int,Rab,Rab)>
2174 new #822 <Class Rab>
2177 dup
2178 aload 5
2180 iconst_1
2181 aload 44
2183 aload 6
2185 invokespecial #1287 <Method Rab(Rn,int,Rab,Rab)>
2188 invokespecial #1287 <Method Rab(Rn,int,Rab,Rab)>
2191 areturn
2192 new #822 <Class Rab>
2195 dup
2196 aload 5
2198 iconst_0
2199 aload 22
2201 aload 6
2203 invokespecial #1287 <Method Rab(Rn,int,Rab,Rab)>
2206 areturn
2207 new #822 <Class Rab>
2210 dup
2211 aload 5
2213 iconst_0
2214 aload 22
2216 aload 6
2218 invokespecial #1287 <Method Rab(Rn,int,Rab,Rab)>
2221 areturn
2222 iconst_1
2223 aload 6
2225 getfield #1106 <Field int b>
2228 if_icmpne 2279
2231 new #822 <Class Rab>
2234 dup
2235 aload 5
2237 iconst_1
2238 new #822 <Class Rab>
2241 dup
2242 aload 47
2244 iconst_0
2245 aload 23
2247 aload 43
2249 invokespecial #1287 <Method Rab(Rn,int,Rab,Rab)>
2252 new #822 <Class Rab>
2255 dup
2256 aload 6
2258 getfield #1114 <Field Rn a>
2261 iconst_0
2262 aload 6
2264 getfield #1177 <Field Rab c>
2267 aload 6
2269 getfield #1148 <Field Rab d>
2272 invokespecial #1287 <Method Rab(Rn,int,Rab,Rab)>
2275 invokespecial #1287 <Method Rab(Rn,int,Rab,Rab)>
2278 areturn
2279 new #822 <Class Rab>
2282 dup
2283 aload 46
2285 iconst_0
2286 new #822 <Class Rab>
2289 dup
2290 aload 47
2292 iconst_1
2293 aload 23
2295 aload 45
2297 invokespecial #1287 <Method Rab(Rn,int,Rab,Rab)>
2300 new #822 <Class Rab>
2303 dup
2304 aload 5
2306 iconst_1
2307 aload 44
2309 aload 6
2311 invokespecial #1287 <Method Rab(Rn,int,Rab,Rab)>
2314 invokespecial #1287 <Method Rab(Rn,int,Rab,Rab)>
2317 areturn

Method int aR(Rc, int)
   0 goto 12
   3 iload_1
   4 iconst_1
   5 iadd
   6 istore_1
   7 aload_0
   8 getfield #1127 <Field Rc b>
  11 astore_0
  12 aload_0
  13 ifnonnull 3
  16 iload_1
  17 ireturn

Method void aS(Rq, Rk, Raa)
   0 goto 42
   3 return
   4 new #817 <Class Eh>
   7 dup
   8 invokespecial #1240 <Method Eh()>
  11 athrow
  12 aload_1
  13 ifnonnull 17
  16 return
  17 new #817 <Class Eh>
  20 dup
  21 invokespecial #1240 <Method Eh()>
  24 athrow
  25 iconst_0
  26 istore 4
  28 iload 4
  30 ifne 3
  33 aload_0
  34 getfield #1109 <Field java.io.BufferedOutputStream a>
  37 ldc #88 <String ",
">
  39 invokestatic #1208 <Method void i(java.io.BufferedOutputStream, java.lang.String)>
  42 aload_2
  43 ifnull 12
  46 aload_1
  47 ifnull 4
  50 aload_1
  51 astore_3
  52 aload_3
  53 getfield #1129 <Field Rk b>
  56 dup
  57 astore_1
  58 aload_0
  59 aload_0
  60 aload_0
  61 aload_0
  62 aload_2
  63 getfield #1174 <Field Rj a>
  66 aload_0
  67 getfield #1109 <Field java.io.BufferedOutputStream a>
  70 ldc #93 <String "{fin = [">
  72 invokestatic #1208 <Method void i(java.io.BufferedOutputStream, java.lang.String)>
  75 invokestatic #1196 <Method void aT(Rq, Rj)>
  78 getfield #1109 <Field java.io.BufferedOutputStream a>
  81 ldc #100 <String "], trans = ">
  83 invokestatic #1208 <Method void i(java.io.BufferedOutputStream, java.lang.String)>
  86 getfield #1109 <Field java.io.BufferedOutputStream a>
  89 aload_3
  90 getfield #1142 <Field java.lang.String a>
  93 invokestatic #1208 <Method void i(java.io.BufferedOutputStream, java.lang.String)>
  96 getfield #1109 <Field java.io.BufferedOutputStream a>
  99 ldc #102 <String "}">
 101 invokestatic #1208 <Method void i(java.io.BufferedOutputStream, java.lang.String)>
 104 aload_2
 105 getfield #1152 <Field Raa b>
 108 astore_2
 109 ifnonnull 25
 112 iconst_1
 113 istore 4
 115 goto 28

Method void aT(Rq, Rj)
   0 goto 78
   3 aload_2
   4 checkcast #816 <Class Sb>
   7 getfield #1118 <Field int a>
  10 istore_3
  11 ldc #104 <String "(N ">
  13 astore 4
  15 aload_1
  16 aload_0
  17 aload_0
  18 iload_3
  19 bipush 10
  21 aload_0
  22 getfield #1109 <Field java.io.BufferedOutputStream a>
  25 aload 4
  27 invokestatic #1208 <Method void i(java.io.BufferedOutputStream, java.lang.String)>
  30 invokestatic #1341 <Method java.lang.String toString(int, int)>
  33 bipush 45
  35 bipush 126
  37 invokevirtual #1245 <Method java.lang.String replace(char, char)>
  40 astore 5
  42 getfield #1109 <Field java.io.BufferedOutputStream a>
  45 aload 5
  47 invokestatic #1208 <Method void i(java.io.BufferedOutputStream, java.lang.String)>
  50 getfield #1109 <Field java.io.BufferedOutputStream a>
  53 ldc #10 <String ")">
  55 invokestatic #1208 <Method void i(java.io.BufferedOutputStream, java.lang.String)>
  58 ifnonnull 152
  61 iconst_1
  62 istore 6
  64 iload 6
  66 ifne 135
  69 aload_0
  70 getfield #1109 <Field java.io.BufferedOutputStream a>
  73 ldc #105 <String ",">
  75 invokestatic #1208 <Method void i(java.io.BufferedOutputStream, java.lang.String)>
  78 aload_1
  79 ifnull 151
  82 aload_1
  83 getfield #1157 <Field S a>
  86 dup
  87 astore_2
  88 getfield #1147 <Field int $>
  91 aload_1
  92 getfield #1090 <Field Rj b>
  95 astore_1
  96 tableswitch 0 to 1: default=136
	    0: 120
	    1: 3
 120 aload_2
 121 checkcast #816 <Class Sb>
 124 getfield #1118 <Field int a>
 127 istore_3
 128 ldc #108 <String "(D ">
 130 astore 4
 132 goto 15
 135 return
 136 aload_2
 137 checkcast #816 <Class Sb>
 140 getfield #1118 <Field int a>
 143 istore_3
 144 ldc #110 <String "(T ">
 146 astore 4
 148 goto 15
 151 return
 152 iconst_0
 153 istore 6
 155 goto 64

Method int aU(Rd, int)
   0 goto 12
   3 iload_1
   4 iconst_1
   5 iadd
   6 istore_1
   7 aload_0
   8 getfield #1145 <Field Rd b>
  11 astore_0
  12 aload_0
  13 ifnonnull 3
  16 iload_1
  17 ireturn

Method void aV(Rq, Rf)
   0 goto 85
   3 aload_0
   4 aload_0
   5 aload_1
   6 getfield #1156 <Field Re a>
   9 dup
  10 astore_2
  11 getfield #1160 <Field int b>
  14 bipush 10
  16 aload_0
  17 aload_0
  18 aload_0
  19 aload_0
  20 getfield #1109 <Field java.io.BufferedOutputStream a>
  23 ldc #40 <String "val ">
  25 invokestatic #1208 <Method void i(java.io.BufferedOutputStream, java.lang.String)>
  28 getfield #1109 <Field java.io.BufferedOutputStream a>
  31 aload_2
  32 getfield #1087 <Field java.lang.String a>
  35 invokestatic #1208 <Method void i(java.io.BufferedOutputStream, java.lang.String)>
  38 getfield #1109 <Field java.io.BufferedOutputStream a>
  41 ldc #112 <String " = ">
  43 invokestatic #1208 <Method void i(java.io.BufferedOutputStream, java.lang.String)>
  46 getfield #1109 <Field java.io.BufferedOutputStream a>
  49 ldc #114 <String "STARTSTATE ">
  51 invokestatic #1208 <Method void i(java.io.BufferedOutputStream, java.lang.String)>
  54 invokestatic #1341 <Method java.lang.String toString(int, int)>
  57 bipush 45
  59 bipush 126
  61 invokevirtual #1245 <Method java.lang.String replace(char, char)>
  64 astore_3
  65 getfield #1109 <Field java.io.BufferedOutputStream a>
  68 aload_3
  69 invokestatic #1208 <Method void i(java.io.BufferedOutputStream, java.lang.String)>
  72 getfield #1109 <Field java.io.BufferedOutputStream a>
  75 ldc #116 <String ";
">
  77 invokestatic #1208 <Method void i(java.io.BufferedOutputStream, java.lang.String)>
  80 aload_1
  81 getfield #1139 <Field Rf b>
  84 astore_1
  85 aload_1
  86 ifnonnull 3
  89 return

Method Rf aW(Rf, Rf)
   0 goto 21
   3 new #775 <Class Rf>
   6 dup
   7 aload_0
   8 getfield #1156 <Field Re a>
  11 aload_1
  12 invokespecial #1229 <Method Rf(Re,Rf)>
  15 astore_1
  16 aload_0
  17 getfield #1139 <Field Rf b>
  20 astore_0
  21 aload_0
  22 ifnonnull 3
  25 aconst_null
  26 astore_2
  27 goto 48
  30 new #775 <Class Rf>
  33 dup
  34 aload_1
  35 getfield #1156 <Field Re a>
  38 aload_2
  39 invokespecial #1229 <Method Rf(Re,Rf)>
  42 astore_2
  43 aload_1
  44 getfield #1139 <Field Rf b>
  47 astore_1
  48 aload_1
  49 ifnonnull 30
  52 aload_2
  53 areturn

Method void aX(Rq, Rh, int)
   0 goto 50
   3 aload_0
   4 getfield #1109 <Field java.io.BufferedOutputStream a>
   7 ldc #118 <String "  ">
   9 invokestatic #1208 <Method void i(java.io.BufferedOutputStream, java.lang.String)>
  12 aload_0
  13 aload_0
  14 aload_0
  15 aload_0
  16 getfield #1109 <Field java.io.BufferedOutputStream a>
  19 aload 6
  21 invokestatic #1208 <Method void i(java.io.BufferedOutputStream, java.lang.String)>
  24 getfield #1109 <Field java.io.BufferedOutputStream a>
  27 ldc #120 <String " => (">
  29 invokestatic #1208 <Method void i(java.io.BufferedOutputStream, java.lang.String)>
  32 getfield #1109 <Field java.io.BufferedOutputStream a>
  35 aload 5
  37 invokestatic #1208 <Method void i(java.io.BufferedOutputStream, java.lang.String)>
  40 getfield #1109 <Field java.io.BufferedOutputStream a>
  43 ldc #122 <String ")
">
  45 invokestatic #1208 <Method void i(java.io.BufferedOutputStream, java.lang.String)>
  48 iconst_0
  49 istore_2
  50 aload_1
  51 ifnull 96
  54 iload_2
  55 aload_1
  56 getfield #1105 <Field Rh b>
  59 astore_3
  60 aload_1
  61 getfield #1099 <Field Rg a>
  64 dup
  65 astore 4
  67 getfield #1194 <Field java.lang.String a>
  70 astore 6
  72 aload 4
  74 getfield #1173 <Field java.lang.String b>
  77 astore 5
  79 aload_3
  80 astore_1
  81 ifne 3
  84 aload_0
  85 getfield #1109 <Field java.io.BufferedOutputStream a>
  88 ldc #125 <String "| ">
  90 invokestatic #1208 <Method void i(java.io.BufferedOutputStream, java.lang.String)>
  93 goto 12
  96 iload_2
  97 ifne 112
 100 aload_0
 101 getfield #1109 <Field java.io.BufferedOutputStream a>
 104 ldc #125 <String "| ">
 106 invokestatic #1208 <Method void i(java.io.BufferedOutputStream, java.lang.String)>
 109 goto 121
 112 aload_0
 113 getfield #1109 <Field java.io.BufferedOutputStream a>
 116 ldc #118 <String "  ">
 118 invokestatic #1208 <Method void i(java.io.BufferedOutputStream, java.lang.String)>
 121 aload_0
 122 getfield #1109 <Field java.io.BufferedOutputStream a>
 125 ldc #127 <String "_ => raise Internal.LexerError
">
 127 invokestatic #1208 <Method void i(java.io.BufferedOutputStream, java.lang.String)>
 130 return

Method Rh aY(Rh, Rh)
   0 goto 21
   3 new #802 <Class Rh>
   6 dup
   7 aload_0
   8 getfield #1099 <Field Rg a>
  11 aload_1
  12 invokespecial #1239 <Method Rh(Rg,Rh)>
  15 astore_1
  16 aload_0
  17 getfield #1105 <Field Rh b>
  20 astore_0
  21 aload_0
  22 ifnonnull 3
  25 aconst_null
  26 astore_2
  27 goto 48
  30 new #802 <Class Rh>
  33 dup
  34 aload_1
  35 getfield #1099 <Field Rg a>
  38 aload_2
  39 invokespecial #1239 <Method Rh(Rg,Rh)>
  42 astore_2
  43 aload_1
  44 getfield #1105 <Field Rh b>
  47 astore_1
  48 aload_1
  49 ifnonnull 30
  52 aload_2
  53 areturn

Method void aZ(F, F, java.io.BufferedOutputStream, java.io.BufferedOutputStream, Ro, Ro, Ro, Ro, Ro, Ro, Rp, Rp, Ro, Rp, Ro, Rq, Ro, Rx, Ro, Ry, Ro, R3, R4, Ro, Ro, java.lang.String, int)
   0 goto 74
   3 return
   4 iconst_0
   5 istore 27
   7 iload 27
   9 ifeq 3
  12 iload 26
  14 iconst_m1
  15 iadd
  16 istore 26
  18 aload_0
  19 aload_1
  20 aload_2
  21 aload_3
  22 aload 4
  24 aload 5
  26 aload 6
  28 aload 7
  30 aload 8
  32 aload 9
  34 aload 10
  36 aload 11
  38 aload 12
  40 aload 13
  42 aload 14
  44 aload 15
  46 aload 16
  48 aload 17
  50 aload 18
  52 aload 19
  54 aload 20
  56 aload 21
  58 aload 22
  60 aload 23
  62 aload 24
  64 aload 25
  66 ldc #130 <String "/DATA/ml.lex">
  68 invokevirtual #1235 <Method java.lang.String concat(java.lang.String)>
  71 invokestatic #1281 <Method void ad(F, F, java.io.BufferedOutputStream, java.io.BufferedOutputStream, Ro, Ro, Ro, Ro, Ro, Ro, Rp, Rp, Ro, Rp, Ro, Rq, Ro, Rx, Ro, Ry, Ro, R3, R4, Ro, Ro, java.lang.String)>
  74 iload 26
  76 ifle 4
  79 iconst_1
  80 istore 27
  82 goto 7

Method Ra ba(java.lang.String, int, int, int, int, int)
   0 iload 5
   2 ifne 15
   5 iload_2
   6 ifne 17
   9 iload_3
  10 istore 15
  12 goto 254
  15 aconst_null
  16 areturn
  17 iload 4
  19 ineg
  20 istore 7
  22 iload_3
  23 istore 9
  25 goto 144
  28 iload 7
  30 ifgt 120
  33 iconst_0
  34 istore 11
  36 iload 11
  38 ifne 52
  41 new #791 <Class Ra>
  44 dup
  45 iload 7
  47 iload_3
  48 invokespecial #1201 <Method Ra(int,int)>
  51 areturn
  52 new #799 <Class Ek>
  55 dup
  56 invokespecial #1305 <Method Ek()>
  59 athrow
  60 new #799 <Class Ek>
  63 dup
  64 invokespecial #1305 <Method Ek()>
  67 athrow
  68 iload 4
  70 iflt 230
  73 iconst_0
  74 istore 17
  76 iload 17
  78 ifne 92
  81 new #791 <Class Ra>
  84 dup
  85 iload 4
  87 iload_3
  88 invokespecial #1201 <Method Ra(int,int)>
  91 areturn
  92 new #799 <Class Ek>
  95 dup
  96 invokespecial #1305 <Method Ek()>
  99 athrow
 100 new #799 <Class Ek>
 103 dup
 104 invokespecial #1305 <Method Ek()>
 107 athrow
 108 aconst_null
 109 astore 6
 111 goto 169
 114 iconst_0
 115 istore 10
 117 goto 200
 120 iconst_1
 121 istore 11
 123 goto 36
 126 iconst_0
 127 istore 12
 129 iload 12
 131 ifne 60
 134 iload 7
 136 bipush 10
 138 imul
 139 iload 8
 141 isub
 142 istore 7
 144 iload 9
 146 iload_1
 147 if_icmpge 108
 150 new #781 <Class Rb>
 153 dup
 154 aload_0
 155 iload 9
 157 invokevirtual #1283 <Method char charAt(int)>
 160 iload 9
 162 iconst_1
 163 iadd
 164 invokespecial #1255 <Method Rb(char,int)>
 167 astore 6
 169 aload 6
 171 ifnull 28
 174 aload 6
 176 getfield #1191 <Field char a>
 179 bipush 10
 181 invokestatic #1291 <Method int digit(char, int)>
 184 dup
 185 istore 8
 187 aload 6
 189 getfield #1158 <Field int b>
 192 istore 9
 194 ifge 114
 197 iconst_1
 198 istore 10
 200 iload 10
 202 ifne 28
 205 iload 7
 207 ldc #1 <Integer -214748364>
 209 if_icmpge 126
 212 iconst_1
 213 istore 12
 215 goto 129
 218 aconst_null
 219 astore 13
 221 goto 279
 224 iconst_0
 225 istore 16
 227 goto 310
 230 iconst_1
 231 istore 17
 233 goto 76
 236 iconst_0
 237 istore 18
 239 iload 18
 241 ifne 100
 244 iload 4
 246 bipush 10
 248 imul
 249 iload 14
 251 iadd
 252 istore 4
 254 iload 15
 256 iload_1
 257 if_icmpge 218
 260 new #781 <Class Rb>
 263 dup
 264 aload_0
 265 iload 15
 267 invokevirtual #1283 <Method char charAt(int)>
 270 iload 15
 272 iconst_1
 273 iadd
 274 invokespecial #1255 <Method Rb(char,int)>
 277 astore 13
 279 aload 13
 281 ifnull 68
 284 aload 13
 286 getfield #1191 <Field char a>
 289 bipush 10
 291 invokestatic #1291 <Method int digit(char, int)>
 294 dup
 295 istore 14
 297 aload 13
 299 getfield #1158 <Field int b>
 302 istore 15
 304 ifge 224
 307 iconst_1
 308 istore 16
 310 iload 16
 312 ifne 68
 315 iload 4
 317 ldc #2 <Integer 214748364>
 319 if_icmple 236
 322 iconst_1
 323 istore 18
 325 goto 239
